Workbook
Name TABLAPD: 'PUNT-DIRECTA'!$B$3:$AB$33
Name TABLAPER: PERCENTIL2!$A$3:$Z$119

Sheet APLICACION
B9: Nombre :Estefania Milagros Negron Huapaya
A11: Instrucciones: La persona deberá responder las afirmaciones con una "1" en la casilla correspondiente. Elegirá la opción de "Verdadero" " casilla izquierda. Elegirá la opción de "Falso" casilla derecha. Trate de marcar cada frase aún cuando no está seguro de su decisión. Si ha intentado y todavía no se puede decidir, marque el Falso. Procure no hacer dobles respuestas.
A12: ITEMS | D12: V | E12: F
A13: 1 | B13: Ultimamente parece que me quedo sin fuerzas incluso por las mañanas. | C13: 1 | E13: 1 | AG13: 1
A14: 2 | B14: Siempre me aseguro de que mi trabajo esté bien planeado y organizado. | C14: 2 | D14: 1
A15: 3 | B15: Disfruto haciendo tantas cosas diferentes que no puedo decidir por cuál empezar. | C15: 3 | E15: 1
A16: 4 | B16: Me preocupa que las personas de las que dependo me abandonen. | C16: 4 | E16: 1
A17: 5 | B17: Aunque me da miedo hacer amistades, me gustaría tener más de las que tengo. | C17: 5 | E17: 1 | F17: =(2*(D18+D27+D55+D102+D131+D151+D161+D192)+D29+D36+D42+D82+D104+E166+D202) -> 6
A18: 6 | B18: Raramente exteriorizo los pocos sentimientos que tengo. | C18: 6 | E18: 1 | F18: =(2*(D17+D24+D38+D111+D147+D207)+(D35+D36+D58+D64+E79+D104+D105+D124+E166+D190+D196+D205)) -> 1
A19: 7 | B19: Me cuesta mantener el equilibrio cuando camino. | C19: 7 | E19: 1 | F19: =(2*(D35+D63+D83+D105+D123+D181+D187+D196+D205)+(D29+D34+D51+E65+D71+D82+D102+D138+D182+D190)) -> 6
A20: 8 | B20: Siempre busco oportunidades nuevas que me resulten emocionantes. | C20: 8 | D20: 1 | F20: =(2*(D16+D54+D72+D89+D121+D145+D174+D185+D206)+(D17+D35+E79+D84+D187)) -> 6
A21: 9 | B21: Algunas veces puedo ser bastante duro y desagradable con mi familia | C21: 9 | E21: 1 | F21: =(2*(D22+D42+D58+D96+D129+D166+D183)+E18+D20+E27+E36+E38+D87+E151+D167+E190+E207) -> 15
A22: 10 | B22: Me gusta ser el centro de atención. | C22: 10 | E22: 1 | F22: =(2*(D20+D32+D65+D87+D141+D167+D186+D197)+(E38+D42+D58+D79+D96+E132+D154+D166+D190)) -> 22
A23: 11 | B23: De adolescente tuve muchos problemas por mi mal comportamiento en la escuela o instituto. | C23: 11 | E23: 1 | F23: =(2*(D41+D50+D66+D79+D99+D118+D144+D154+D171+D201)+(D22+D31+D95+D129+D183+D203)) -> 6
A24: 12 | B24: Me da miedo hacerme muy amigo de alquien por que podría acabar sintiéndome ridiculizado o avergonzado. | C24: 12 | E24: 1 | F24: =(2*(D23+D31+D77+D95+D159+D195+D203)+(D48+D50+E60+D117+D164+E170+D171)) -> 1
A25: 13 | B25: Noto que la gente está hablando de mí cuando paso a su lado. | C25: 13 | E25: 1 | F25: =(2*(D21+D62+D78+D109+D115+D127+D153+D164)+(D23+D28+D33+D86+D157+D184)) -> 1
A26: 14 | B26: Hace uno años comencé a sentirme un fracasado. | C26: 14 | E26: 1 | F26: =(2*(D14+D47+D60+D75+D85+D140+D152+D170+D191+D200)+(E95+E159+E164)) -> 13
A27: 15 | B27: Si puedo elegir, prefiero hacer las cosas solo. | C27: 15 | D27: 1 | F27: =(2*(D29+D44+D94+D108+D134+D149+D179+D199)+(D33+D49+D64+D91+D100+D109+D112+D180+D184+D196)) -> 9
A28: 16 | B28: Últimamente he comenzado a sentir deseos de destrozar cosas. | C28: 16 | E28: 1 | F28: =(2*(D51+D71+D97+D112+D138+D178+D204)+(D16+D24+E32+D35+D82+E87+D105+D168+D176+D190+D207)) -> 5
A29: 17 | B29: Las cosas que hoy van bien no durarán mucho tiempo. | C29: 17 | E29: 1 | F29: =(2*(D25+D36+D56+D104+D124+D168+D177+D202)+(D30+D70+D82+D102+D105+D133+D135+D138+D160+D175+D179+D184+D207)) -> 2
A30: 18 | B30: A veces, cuando las cosas empiezan a irme mal, me siento como si estuviera loco o fuera de la realidad. | C30: 18 | E30: 1 | F30: =(2*(D28+D30+D49+D82+D146+D176+D190)+(D16+D71+D92+D94+D105+D112+D123+D138+D149+D168+D178+D204+D205)) -> 6
A31: 19 | B31: Hago lo que quiero sin preocuparme de las consecuencias que tenga en los demás. | C31: 19 | E31: 1 | F31: =(2*(D33+D64+D91+D100+D116+D148+D165+D184)+(D25+D36+D80+D108+D160+D179+D192+D207)) -> 9
A32: 20 | B32: Afronto mis actividades diarias con mucha energía y persistencia. | C32: 20 | D32: 1
A33: 21 | B33: Nunca perdono una ofensa ni olvido una situación embarazosa que alguien me haya causado. | C33: 21 | D33: 1
A34: 22 | B34: Me siento extremadamente deprimido y triste gran parte del tiempo. | C34: 22 | E34: 1
A35: 23 | B35: Siempre tiendo a culparme cuando las cosas van mal. | C35: 23 | E35: 1 | F35: =(2*(D45+D84+D101+D125+D135+D155)+(D43+D53+D56+D63+D103+D120+D121)) -> 2
A36: 24 | B36: Hace mucho decidí que es mejor tener poca relación con la gente. | C36: 24 | E36: 1 | F36: =(2*(D19+D40+D53+D132+D158)+(D13+E32+D69+D125+D130)) -> 0
A37: 25 | B37: Tengo un problema con el alcohol que nos ha creado dificultades a mí y a mi familia. | C37: 25 | E37: 1 | F37: =(2*(D15+D39+D68+D120+D175+D189)+(D49+D62+D66+D94+D95+D117+D167)) -> 3
A38: 26 | B38: Soy una persona socialmente muy reservada y tímida. | C38: 26 | E38: 1 | F38: =(2*(D26+D46+D76+D130+D163+D182)+(D29+D40+D51+D63+D83+E87+D89+D97+D105+D113+D123+D126+D132+D190+D205)) -> 6
A39: 27 | B39: Muchas veces me siento muy alegre y animado sin ninguna razón. | C39: 27 | E39: 1 | F39: =(2*(D37+D57+D106+D142+D173)+(D77+D95+D138)) -> 0
A40: 28 | B40: En las últimas semanas me he sentido agotado sin ningún motivo en particular. | C40: 28 | E40: 1 | F40: =(2*(D48+D73+D93+D117+D128+D136+D156)+(D23+D77+D164+D170)) -> 0
A41: 29 | B41: Mi tiempo es más valioso que el de los demás. | C41: 29 | E41: 1 | F41: =(2*(D74+D88+D103+D137+D162)+(D56+D59+D69+D86+D101+D122+D125+D155+D169)) -> 4
A42: 30 | B42: Siempre estoy buscando hacer nuevas amistades y conocer gente nueva. | C42: 30 | D42: 1 | F42: =(2*(D45+D70+D92+D133+D143+D150)+(D30+D36+D64+D94+D101+D104+D107+D116+D135+D148+D160+D168+D177+D184+D194)) -> 6
A43: 31 | B43: Desde hace unas semanas estoy muy nervioso. | C43: 31 | E43: 1 | F43: =(2*(D13+D34+D69+D90+D113+D119+D126)+(D40+D53+D71+D76+D82+D92+D123+D130+D132+D182)) -> 6
A44: 32 | B44: Simplemente, no he tenido la suerte que otras personas han tenido en la vida. | C44: 32 | D44: 1 | F44: =(2*(D80+D107+D139+D160+D194)+(D25+D66+D91+D100+D124+D133+D148+D184+D201)) -> 2
A45: 33 | B45: Las ideas me dan vueltas en la cabeza una y otra vez y no desaparecen. | C45: 33 | D45: 1 | F45: Validez
A46: 34 | B46: Desde hace uno o dos años, al pensar sobre la vida, me siento muy triste y desanimado. | C46: 34 | E46: 1 | F46: =D61+D110+D172 -> 1
A47: 35 | B47: Intento hacerlo todo tan perfecto como sea posible. | C47: 35 | D47: 1
A48: 36 | B48: Mi adicción a las drogas hizo que faltara al trabajo. | C48: 36 | E48: 1 | F48: 22-170 | H48: 125-143 | J48: 47-157 | L48: 40 - 181 | N48: 81 - 116 | P48: 85-116 | R48: 76-150 | T48: 25-94 | V48: 44 -121
A49: 37 | B49: Mi estado de ánimo varía mucho de un día para otro. | C49: 37 | E49: 1 | F49: =D34+D182 -> 1 | G49: =E34+E182 -> 1 | H49: =D137+D155 -> 1 | I49: =E137+E155 -> 1 | J49: =D59+D169 -> 2 | K49: =E59+E169 -> 0 | L49: =D52+D193 -> 0 | M49: =E52+E193 -> 2 | N49: =D93+D128 -> 0 | O49: =E93+E128 -> 2 | P49: =D97+D138 -> 1 | Q49: =E97+E138 -> 1 | R49: =D88+D162 -> 0 | S49: =E88+E162 -> 2 | T49: =D37+D106 -> 0 | U49: =E37+E106 -> 2 | V49: =D56+D133 -> 0 | W49: =E56+E133 -> 2
A50: 38 | B50: Utilizo mi encanto para conseguir lo que quiero. | C50: 38 | E50: 1 | F50: =IF(F49=1,1,0) -> 1 | G50: =IF(G49=1,1,0) -> 1 | H50: =IF(H49=1,1,0) -> 1 | I50: =IF(I49=1,1,0) -> 1 | J50: =IF(J49=1,1,0) -> 0 | K50: =IF(K49=1,1,0) -> 0 | L50: =IF(L49=1,1,0) -> 0 | M50: =IF(M49=1,1,0) -> 0 | ... W50: =IF(W49=1,1,0) -> 0
A51: 39 | B51: A menudo pienso que no merezco las cosas buenas que me pasan. | C51: 39 | E51: 1 | F51: =((F50+G50)/2) -> 1 | H51: =((H50+I50)/2) -> 1 | J51: =((J50+K50)/2) -> 0 | L51: =((L50+M50)/2) -> 0 | N51: =((N50+O50)/2) -> 0 | P51: =((P50+Q50)/2) -> 1 | R51: =((R50+S50)/2) -> 0 | T51: =((T50+U50)/2) -> 0 | V51: =((V50+W50)/2) -> 0
A52: 40 | B52: En el pasado me corté o autolesioné a propósito | C52: 40 | E52: 1 | F52: 39-59 | H52: 17-184 | J52: 33- 89 | L52: 78-164 | N52: 38-171 | P52: 74-115 | R52: 46 - 154 | T52: 26-99 | V52: 20-174
A53: 41 | B53: Tengo la sensación de que no duermo, y me levanto tan cansado como al acostarme. | C53: 41 | E53: 1 | F53: =D51+D71 -> 0 | G53: =E51+E71 -> 2 | H53: =D29+D196 -> 0 | I53: =E29+E196 -> 2 | J53: =D45+D101 -> 1 | K53: =E45+E101 -> 1 | L53: =D90+D176 -> 0 | M53: =E90+E176 -> 2 | N53: =D50+D183 -> 0 | O53: =E50+E183 -> 2 | P53: =D86+D127 -> 0 | Q53: =E86+E127 -> 2 | R53: =D58+D166 -> 1 | S53: =E58+E166 -> 1 | T53: =D38+D111 -> 0 | U53: =E38+E111 -> 2 | V53: =D32+D186 -> 2 | W53: =E32+E186 -> 0
A54: 42 | B54: A menudo dejo que los demás tomen por mi desiciones importantes. | C54: 42 | E54: 1 | F54: =IF(F53=1,1,0) -> 0 | G54: =IF(G53=1,1,0) -> 0 | H54: =IF(H53=1,1,0) -> 0 | I54: =IF(I53=1,1,0) -> 0 | J54: =IF(J53=1,1,0) -> 1 | K54: =IF(K53=1,1,0) -> 1 | L54: =IF(L53=1,1,0) -> 0 | M54: =IF(M53=1,1,0) -> 0 | ... W54: =IF(W53=1,1,0) -> 0
A55: 43 | B55: Parece que pocas cosas me entristecen o me alegran. | C55: 43 | D55: 1 | F55: =((F54+G54)/2) -> 0 | H55: =((H54+I54)/2) -> 0 | J55: =((J54+K54)/2) -> 1 | L55: =((L54+M54)/2) -> 0 | N55: =((N54+O54)/2) -> 0 | P55: =((P54+Q54)/2) -> 0 | R55: =((R54+S54)/2) -> 1 | T55: =((T54+U54)/2) -> 0 | V55: =((V54+W54)/2) -> 0
A56: 44 | B56: A menudo tengo pensamiento extraños de los que desearía librarme. | C56: 44 | E56: 1 | F56: 32-122 | H56: 13-112 | J56: 55-110 | L56: 173- 194 | N56: 95-127 | P56: 60-162 | R56: 15-149
A57: 45 | B57: Tengo muchos problemas para controlar el impulso de beber alcohol en exceso. | C57: 45 | E57: 1 | F57: =D44+D134 -> 1 | G57: =E44+E134 -> 1 | H57: =D25+D124 -> 0 | I57: =E25+E124 -> 2 | J57: =D67+D122 -> 0 | K57: =E67+E122 -> 2 | L57: =D185+D206 -> 2 | M57: =E185+E206 -> 0 | N57: =D107+D139 -> 0 | O57: =E107+E139 -> 2 | P57: =D72+D174 -> 0 | Q57: =E72+E174 -> 2 | R57: =D27+D161 -> 1 | S57: =E27+E161 -> 1
A58: 46 | B58: Hago amistades con mucha más facilidad que la mayoría de la gente que conozco. | C58: 46 | E58: 1 | F58: =IF(F57=1,1,0) -> 1 | G58: =IF(G57=1,1,0) -> 1 | H58: =IF(H57=1,1,0) -> 0 | I58: =IF(I57=1,1,0) -> 0 | J58: =IF(J57=1,1,0) -> 0 | K58: =IF(K57=1,1,0) -> 0 | L58: =IF(L57=1,1,0) -> 0 | M58: =IF(M57=1,1,0) -> 0 | ... S58: =IF(S57=1,1,0) -> 1
A59: 47 | B59: Me da vergüenza el maltrato que sufrí cuando era joven. | C59: 47 | D59: 1 | F59: =((F58+G58)/2) -> 1 | H59: =((H58+I58)/2) -> 0 | J59: =((J58+K58)/2) -> 0 | L59: =((L58+M58)/2) -> 0 | N59: =((N58+O58)/2) -> 0 | P59: =((P58+Q58)/2) -> 0 | R59: =((R58+S58)/2) -> 1
A60: 48 | B60: Me parece muy bien que haya normas porque son una buena guía a seguir. | C60: 48 | D60: 1 | J60: Total | K60: =(SUM(F51:W51)+SUM(F55:W55)+SUM(F59:S59)) -> 7
A61: 49 | B61: El año pasado aparecí en la portada de varias revistas. | C61: 49 | E61: 1
A62: 50 | B62: A menudo me enfado con la gente que hace las cosas lentamente. | C62: 50 | E62: 1
A63: 51 | B63: Me paso la vida preocupándome por una cosa u otra. | C63: 51 | E63: 1 | G63: =E14+D16+E17+D18+E20+D21+D22+D23+D24+D27+D28+D29+D31+E32+D33+D34+D35+D36+D38+E41+E42+D44+D47+D48+D49+D50+D51+D54+D55+E58+E60+D62+D63+D64+E65+D66+D71+D72+E75+D77+D78+E79+D82+D83+D84+E85+D86+E87+D89+D91+D94+D95+E96+D97+D99+D100+D102+D104+D105+D108+D109+D111+D112+D115+D117+D118+D121+D123+D124+D127+D129+D131+D132+D134+D138+D140+D141+D144+D145+D147+D149+D151+D152+D153+E154+D157+D159+D161+D164+E166+E167+D168+E170+D171+D174+D176+D178+D179+D180+D181+D182+D183+D184+D185+E186+D187+D190+D191+D192+D195+D196+E197+D199+D200+D201+D202+D203+D204+D205+D206+D207 -> 26
A64: 52 | B64: Siempre me pregunto cuál es la razón real de que alguien sea especificamente agradable conmigo. | C64: 52 | D64: 1 | G64: =D14+D15+D20+D32+D42+D58+E77+D79+E83+D85+D87+D96+E102+E111+D166+D167+D170+E171+E174+E185+D186+D197+E199+D200 -> 18
A65: 53 | B65: Mis actividades cotidianas me animan y motivan. | C65: 53 | D65: 1 | G65: =D13+D26+D28+D29+D30+D34+D40+D43+D44+D46+D49+D51+D53+D56+D63+D76+D86+D90+D92+D113+D119+D121+D124+D125+D132+D163+D176+D182+D190+D205 -> 4
A66: 54 | B66: Tengo mcuhas ideas que son avanzadas para los tiempos actuales. | C66: 54 | D66: 1
A67: 55 | B67: Desde que sufrí una conmoción cerebral grave, ya no puedo concentrarme en nada. | C67: 55 | E67: 1 | G67: 1.1 | H67: ID | I67: =D24+D27+D36+D116+D161+E166+D192+E197+D202 -> 1
A68: 56 | B68: Antes la gente decía que me interesaba y me entusiasmaba demasiado por muchas cosas. | C68: 56 | E68: 1 | H68: CE | I68: =D38+E42+E58+E79+D111+D151+D187+D190+D207 -> 1
A69: 57 | B69: He perdido el apetito por completo, y la mayoria de las noches tengo problemas para dormir. | C69: 57 | E69: 1 | H69: TA | I69: =D18+D29+D55+D82+D102+D104+D123+D130+D131 -> 3
A70: 58 | B70: Desde que era niño he ido perdiendo contacto con la realidad. | C70: 58 | E70: 1
A71: 59 | B71: No puedo sentir mucho placer por que no creo que lo merezca . | C71: 59 | E71: 1
A72: 60 | B72: Prefiero que me digan lo que tengo que hacer en lugar de decidir por mí mismo. | C72: 60 | E72: 1
A73: 61 | B73: Consumir drogas me ha causado discusiones con mi familia. | C73: 61 | E73: 1
A74: 62 | B74: El recuerdo de una experiencia muy pertubadora sigue presente en mis pensamientos y me obsesiona. | C74: 62 | E74: 1
A75: 63 | B75: La mayoría de la gente me considera una persona prudente y cuidadosa. | C75: 63 | D75: 1
A76: 64 | B76: Parece que he perdido el interés en la mayoría de las cosas que solia encontrar placenteras, como el sexo. | C76: 64 | E76: 1
A77: 65 | B77: He tenido problemas con la ley un par de veces. | C77: 65 | E77: 1
A78: 66 | B78: He tenido que ser muy duro con algunas personas para mantenerlas a raya. | C78: 66 | E78: 1
A79: 67 | B79: Estoy muy seguro de mí mismo. | C79: 67 | D79: 1
A80: 68 | B80: La gente intenta hacerme creer que estoy loco. | C80: 68 | E80: 1
A81: 69 | B81: Me doy atracones de comida un par de veces en la semana. | C81: 69 | E81: 1
A82: 70 | B82: Frecuentemente siento que no hay nada dentro de mí, como si estuviera vacío y hueco. | C82: 70 | D82: 1
A83: 71 | B83: Siempre me ha resultado difícil dejar de sentirme deprimido y triste. | C83: 71 | D83: 1
A84: 72 | B84: Cuando estoy solo y lejos de casa a menudo comienzo a sentirme tenso y entro en pánico. | C84: 72 | E84: 1
A85: 73 | B85: La gente dice que soy una persona formal y con valores morales. | C85: 73 | D85: 1
A86: 74 | B86: Me cuesta controlar mi ira. | C86: 74 | E86: 1
A87: 75 | B87: Soy una persona muy optimista. | C87: 75 | D87: 1
A88: 76 | B88: Años después, aún tengo pesadillas sobre un hecho que fue una amenaza real para mi vida. | C88: 76 | E88: 1
A89: 77 | B89: Me parece que necesito que alguien me oriente para hacer las cosas. | C89: 77 | E89: 1
A90: 78 | B90: Recientemente he pensado muy en serio en quitarme la vida. | C90: 78 | E90: 1
A91: 79 | B91: Hay gente mala que intenta llevarse el mérito de lo que he hecho o pensado. | C91: 79 | E91: 1
A92: 80 | B92: Últimamente estoy destrozado. | C92: 80 | D92: 1
A93: 81 | B93: Consumir drogas puede ser irresponsable, pero en el pasado las he necesitado. | C93: 81 | E93: 1
A94: 82 | B94: Soy una persona muy variable, cambio de opinión y sentimientos continuamente. | C94: 82 | D94: 1
A95: 83 | B95: Se me da muy bien inventar excusas cuando me meto en problemas. | C95: 83 | E95: 1
A96: 84 | B96: Cuando estoy en una fiesta, nunca me aíslo de los demás. | C96: 84 | D96: 1
A97: 85 | B97: Parece que echo a perder las buenas oportunidades que se cruzan en mi camino. | C97: 85 | D97: 1
A98: 86 | B98: Algunas veces me provoco el vómito después de comer. | C98: 86 | E98: 1
A99: 87 | B99: Soy una persona especial, así que no me importa lo que piensen los demás. | C99: 87 | E99: 1
A100: 88 | B100: Observo atentamente a mi familia para saber en quíen se puede confiar y en quién no. | C100: 88 | D100: 1
A101: 89 | B101: Ciertos pensamientos vuelven a mi mente una y otra vez. | C101: 89 | E101: 1
A102: 90 | B102: Pocas cosas en la vida me resultan placenteras. | C102: 90 | E102: 1
A103: 91 | B103: Me siento agitado y me cuesta conciliar el sueño por que tengo recuerdos dolorosos dando vueltas en mi cabeza. | C103: 91 | E103: 1
A104: 92 | B104: A menudo me pierdo en mis pensamientos y me olvido de lo que está pasando a mi alrededor. | C104: 92 | E104: 1
A105: 93 | B105: Nunca he podido dejar de sentir que no valgo nada para los demás. | C105: 93 | E105: 1
A106: 94 | B106: Tengo un problema con la bebida que he tratado de solucionar sin éxito. | C106: 94 | E106: 1
A107: 95 | B107: Alguien ha estado intentando controlar mi mente. | C107: 95 | E107: 1
A108: 96 | B108: La mayoría de las personas que han triunfado han tenido suerte o han sido deshonestas. | C108: 96 | E108: 1
A109: 97 | B109: A menudo irrito a la gente dándoles órdenes. | C109: 97 | E109: 1
...

Sheet RESULTADOS 
P5: =APLICACION!B9 -> Nombre :Estefania Milagros Negron Huapaya
B9: ESCALA DE VALIDEZ | C9: Escalas de Validez | D9: PD
B10: V | C10: Invalidez | D10: =APLICACION!F46 -> 1 | O10: ='Interpretacion '!R8 -> válido pero dudable, cuestionable.
B11: W | C11: Inconsistencia | D11: =APLICACION!K60 -> 7 | O11: ='Interpretacion '!R9 -> consistente.
B12: X | C12: Sinceridad | D12: =VLOOKUP(K12,RESULTADOS!A3:B117,2,FALSE) -> 30 | K12: =APLICACION!G63 -> 26 | O12: ='Interpretacion '!R10 -> clínicamente interpretable
B13: Y | C13: Deseabilidad Social | D13: =VLOOKUP(K13,RESULTADOS!A3:C27,3,FALSE) -> 78 | K13: =APLICACION!G64 -> 18 | O13: ='Interpretacion '!R11 -> Tendencia a parecer socialmente agradable, moralmente admirable o emocionalmente equilibrado. Tendencia a mostrar una imagen de sí mismo positiva e interesante. Cuanto más alta sea la puntuación, más probable es que el paciente haya ocultado ciertos aspectos de sus dificultades psicológicas o interpersonales.
B14: Z | C14: Devaluación | D14: =VLOOKUP('RESULTADOS '!K14,RESULTADOS!A3:D33,4,FALSE) -> 37 | K14: =APLICACION!G65 -> 4 | O14: ='Interpretacion '!R12 -> Tendencia del sujeto a menospreciarse o subestimarse manifestando más problemas emocionales y perso¬nales de los que un análisis posterior pueda reflejar.
B16: Patrones de Personalidad | D16: PE | H16: PERCENTIL | L16: PD
B17: 1 | C17: Esquizoide | D17: =CORRECCION!D17 -> 40 | E17: 3 | G17: 2 | H17: =IFERROR(VLOOKUP(D17,TABLAPER,G17,FALSE),"") -> 31 | L17: =APLICACION!F17 -> 6 | O17: =CORRECCION!O17 -> No presenta
B18: 2A | C18: Evitativo | D18: =CORRECCION!D18 -> 6 | E18: 4 | G18: 3 | H18: =IFERROR(VLOOKUP(D18,TABLAPER,G18,FALSE),"") -> 5 | L18: =APLICACION!F18 -> 1 | O18: =CORRECCION!O18 -> No presenta
B19: 2B | C19: Melancólico | D19: =CORRECCION!D19 -> 30 | E19: 5 | G19: 4 | H19: =IFERROR(VLOOKUP(D19,TABLAPER,G19,FALSE),"") -> 28 | L19: =APLICACION!F19 -> 6 | O19: =CORRECCION!O19 -> No presenta
B20: 3 | C20: Dependiente | D20: =CORRECCION!D20 -> 36 | E20: 6 | G20: 5 | H20: =IFERROR(VLOOKUP(D20,TABLAPER,G20,FALSE),"") -> 25 | L20: =APLICACION!F20 -> 6 | O20: =CORRECCION!O20 -> No presenta
B21: 4A | C21: Histriónico | D21: =CORRECCION!D21 -> 75 | E21: 7 | G21: 6 | H21: =IFERROR(VLOOKUP(D21,TABLAPER,G21,FALSE),"") -> 83 | L21: =APLICACION!F21 -> 15 | O21: =CORRECCION!O21 -> Patrones menos adaptativos y Trastornos
B22: 4B | C22: Tempestuoso | D22: =CORRECCION!D22 -> 80 | E22: 8 | G22: 7 | H22: =IFERROR(VLOOKUP(D22,TABLAPER,G22,FALSE),"") -> 93 | L22: =APLICACION!F22 -> 22
B23: 5 | C23: Narcisista | D23: =CORRECCION!D23 -> 62 | E23: 9 | G23: 8 | H23: =IFERROR(VLOOKUP(D23,TABLAPER,G23,FALSE),"") -> 56 | L23: =APLICACION!F23 -> 6 | O23: =CORRECCION!O23 -> Categoría de Riesgo
B24: 6A | C24: Antisocial | D24: =CORRECCION!D24 -> 20 | E24: 10 | G24: 9 | H24: =IFERROR(VLOOKUP(D24,TABLAPER,G24,FALSE),"") -> 25 | L24: =APLICACION!F24 -> 1 | O24: =CORRECCION!O24 -> No presenta
B25: 6B | C25: Sádico | D25: =CORRECCION!D25 -> 10 | E25: 11 | G25: 10 | H25: =IFERROR(VLOOKUP(D25,TABLAPER,G25,FALSE),"") -> 13 | L25: =APLICACION!F25 -> 1 | O25: =CORRECCION!O25 -> No presenta
B26: 7 | C26: Compulsivo | D26: =CORRECCION!D26 -> 49 | E26: 12 | G26: 11 | H26: =IFERROR(VLOOKUP(D26,TABLAPER,G26,FALSE),"") -> 26 | L26: =APLICACION!F26 -> 13 | O26: =CORRECCION!O26 -> No presenta
B27: 8A | C27: Negativista | D27: =CORRECCION!D27 -> 60 | E27: 13 | G27: 12 | H27: =IFERROR(VLOOKUP(D27,TABLAPER,G27,FALSE),"") -> 48 | L27: =APLICACION!F27 -> 9 | O27: =CORRECCION!O27 -> No presenta
B28: 8B | C28: Masoquista | D28: =CORRECCION!D28 -> 38 | E28: 14 | G28: 13 | H28: =IFERROR(VLOOKUP(D28,TABLAPER,G28,FALSE),"") -> 33 | L28: =APLICACION!F28 -> 5 | O28: =CORRECCION!O28 -> No presenta
B29: Patologías Graves Personalidad | D29: =CORRECCION!D29 -> PE | H29: PERCENTIL | L29: PD
B30: S | C30: Esquizotípico | D30: =CORRECCION!D30 -> 12 | E30: 15 | G30: 14 | H30: =IFERROR(VLOOKUP(D30,TABLAPER,G30,FALSE),"") -> 14 | L30: =APLICACION!F29 -> 2 | O30: =CORRECCION!O30 -> No presenta
B31: C | C31: Límite | D31: =CORRECCION!D31 -> 45 | E31: 16 | G31: 15 | H31: =IFERROR(VLOOKUP(D31,TABLAPER,G31,FALSE),"") -> 40 | L31: =APLICACION!F30 -> 6 | O31: =CORRECCION!O31 -> No presenta
B32: P | C32: Paranoide | D32: =CORRECCION!D32 -> 66 | E32: 17 | G32: 16 | H32: =IFERROR(VLOOKUP(D32,TABLAPER,G32,FALSE),"") -> 62 | L32: =APLICACION!F31 -> 9 | O32: =CORRECCION!O32 -> Categoría de Riesgo
D33: =CORRECCION!D33 -> 0 | O33: =CORRECCION!O33 -> No presenta
B34: Sindromes Clínicos | D34: =CORRECCION!D34 -> PE | H34: PERCENTIL | L34: PD
B35: A | C35: Ansiedad Generalizada | D35: =CORRECCION!D35 -> 15 | E35: 18 | G35: 17 | H35: =IFERROR(VLOOKUP(D35,TABLAPER,G35,FALSE),"") -> 14 | L35: =APLICACION!F35 -> 2 | O35: =CORRECCION!O35 -> No presenta
B36: H | C36: Síntomas Somáticos | D36: =CORRECCION!D36 -> 0 | E36: 19 | G36: 18 | H36: =IFERROR(VLOOKUP(D36,TABLAPER,G36,FALSE),"") -> 11 | L36: =APLICACION!F36 -> 0 | O36: =CORRECCION!O36 -> No presenta
B37: N | C37: Espectro Bípolar | D37: =CORRECCION!D37 -> 30 | E37: 20 | G37: 19 | H37: =IFERROR(VLOOKUP(D37,TABLAPER,G37,FALSE),"") -> 22 | L37: =APLICACION!F37 -> 3 | O37: =CORRECCION!O37 -> No presenta
B38: D | C38: Depresión Persistente | D38: =CORRECCION!D38 -> 30 | E38: 21 | G38: 20 | H38: =IFERROR(VLOOKUP(D38,TABLAPER,G38,FALSE),"") -> 28 | L38: =APLICACION!F38 -> 6 | O38: =CORRECCION!O38 -> No presenta
B39: B | C39: Consumo de Alcohol | D39: =CORRECCION!D39 -> 0 | E39: 22 | G39: 21 | H39: =IFERROR(VLOOKUP(D39,TABLAPER,G39,FALSE),"") -> 34 | L39: =APLICACION!F39 -> 0 | O39: =CORRECCION!O39 -> No presenta
B40: T | C40: Consumo de Drogas | D40: =CORRECCION!D40 -> 0 | E40: 23 | G40: 22 | H40: =IFERROR(VLOOKUP(D40,TABLAPER,G40,FALSE),"") -> 24 | L40: =APLICACION!F40 -> 0 | O40: =CORRECCION!O40 -> No presenta
B41: R | C41: Estrés Postraumático | D41: =CORRECCION!D41 -> 48 | E41: 24 | G41: 23 | H41: =IFERROR(VLOOKUP(D41,TABLAPER,G41,FALSE),"") -> 42 | L41: =APLICACION!F41 -> 4 | O41: =CORRECCION!O41 -> No presenta
B42: SS | C42: Espectro Esquizofrénico | D42: =CORRECCION!D42 -> 40 | E42: 25 | G42: 24 | H42: =IFERROR(VLOOKUP(D42,TABLAPER,G42,FALSE),"") -> 33 | L42: =APLICACION!F42 -> 6 | O42: =CORRECCION!O42 -> No presenta
B43: CC | C43: Depresión Mayor | D43: =CORRECCION!D43 -> 51 | E43: 26 | G43: 25 | H43: =IFERROR(VLOOKUP(D43,TABLAPER,G43,FALSE),"") -> 46 | L43: =APLICACION!F43 -> 6 | O43: =CORRECCION!O43 -> No presenta
B44: PP | C44: Delirante | D44: =CORRECCION!D44 -> 60 | E44: 27 | G44: 26 | H44: =IFERROR(VLOOKUP(D44,TABLAPER,G44,FALSE),"") -> 51 | L44: =APLICACION!F44 -> 2 | O44: =CORRECCION!O44 -> No presenta

Sheet FACETAS GROSSMAN Y RESPUESTAS S
A8: Patrones de Personalidad | C8: PD | D8: PE | G8: Respuestas Siginificativas | I8: PD | J8: %
A9: 1 | B9: Esquizoide | D9: =CORRECCION!D17 -> 40 | E9: =REPT("g",D9/2) -> gggggggggggggggggggg | G9: 1 | H9: TDAH | I9: ='RPTA SIGNIFICATIVAS'!C9 -> 2 | J9: ='RPTA SIGNIFICATIVAS'!D9 -> 0.33333333
A10: 1.1 | B10: Interpersonalmente Desvinculado | C10: =APLICACION!D24+APLICACION!D27+APLICACION!D36+APLICACION!D116+APLICACION!D161+APLICACION!E166+APLICACION!D192+APLICACION!E197+APLICACION!D202 -> 1 | D10: =IF(C10=0,'PERCENTIL GROSSMAN'!B3,IF(C10=1,'PERCENTIL GROSSMAN'!D3,IF(C10=2,'PERCENTIL GROSSMAN'!F3,IF(C10=3,'PERCENTIL GROSSMAN'!H3,IF(C10=4,'PERCENTIL GROSSMAN'!J3,IF(C10=5,'PERCENTIL GROSSMAN'!L3,IF(C10=6,'PERCENTIL GROSSMAN'!N3,IF(C10=7,'PERCENTIL GROSSMAN'!P3,IF(C10=8,'PERCENTIL GROSSMAN'!R3,IF(C10=9,'PERCENTIL GROSSMAN'!T3)))))))))) -> 20 | E10: =REPT("g",D10/2) -> gggggggggg | G10: 2 | H10: Espectro Autista | I10: ='RPTA SIGNIFICATIVAS'!C10 -> 0 | J10: ='RPTA SIGNIFICATIVAS'!D10 -> 0
A11: 1.2 | B11: Contenido Escaso | C11: =APLICACION!D38+APLICACION!E42+APLICACION!E58+APLICACION!E79+APLICACION!D111+APLICACION!D151+APLICACION!D187+APLICACION!E190+APLICACION!D207 -> 2 | D11: =IF(C11=0,'PERCENTIL GROSSMAN'!B4,IF(C11=1,'PERCENTIL GROSSMAN'!D4,IF(C11=2,'PERCENTIL GROSSMAN'!F4,IF(C11=3,'PERCENTIL GROSSMAN'!H4,IF(C11=4,'PERCENTIL GROSSMAN'!J4,IF(C11=5,'PERCENTIL GROSSMAN'!L4,IF(C11=6,'PERCENTIL GROSSMAN'!N4,IF(C11=7,'PERCENTIL GROSSMAN'!P4,IF(C11=8,'PERCENTIL GROSSMAN'!R4,IF(C11=9,'PERCENTIL GROSSMAN'!T4)))))))))) -> 30 | E11: =REPT("g",D11/2) -> ggggggggggggggg | G11: 3 | H11: Maltrato Infantil | I11: ='RPTA SIGNIFICATIVAS'!C11 -> 2 | J11: ='RPTA SIGNIFICATIVAS'!D11 -> 1
A12: 1.3 | B12: Temperalmente apático | C12: =APLICACION!D39+APLICACION!E43+APLICACION!E59+APLICACION!E80+APLICACION!D112+APLICACION!D152+APLICACION!D188+APLICACION!E191+APLICACION!D208 -> 3 | D12: =IF(C12=0,'PERCENTIL GROSSMAN'!B5,IF(C12=1,'PERCENTIL GROSSMAN'!D5,IF(C12=2,'PERCENTIL GROSSMAN'!F5,IF(C12=3,'PERCENTIL GROSSMAN'!H5,IF(C12=4,'PERCENTIL GROSSMAN'!J5,IF(C12=5,'PERCENTIL GROSSMAN'!L5,IF(C12=6,'PERCENTIL GROSSMAN'!N5,IF(C12=7,'PERCENTIL GROSSMAN'!P5,IF(C12=8,'PERCENTIL GROSSMAN'!R5,IF(C12=9,'PERCENTIL GROSSMAN'!T5)))))))))) -> 60 | E12: =REPT("g",D12/2) -> gggggggggggggggggggggggggggggg | G12: 4 | H12: Trastornos de la conducta alimentaria | I12: ='RPTA SIGNIFICATIVAS'!C12 -> 0 | J12: ='RPTA SIGNIFICATIVAS'!D12 -> 0
A13: 2A | B13: Evitativo | D13: =CORRECCION!D18 -> 6 | E13: =REPT("g",D13/2) -> ggg | G13: 5 | H13: Falta de Control Emocional | I13: ='RPTA SIGNIFICATIVAS'!C13 -> 1 | J13: ='RPTA SIGNIFICATIVAS'!D13 -> 0.125
A14: 2A.1 | B14: Interpersonalmente Aversivo | C14: =APLICACION!D27+APLICACION!D38+APLICACION!E42+APLICACION!E58+APLICACION!E96+APLICACION!D111+APLICACION!D151+APLICACION!E166 -> 2 | D14: =IF(C14=0,'PERCENTIL GROSSMAN'!B6,IF(C14=1,'PERCENTIL GROSSMAN'!D6,IF(C14=2,'PERCENTIL GROSSMAN'!F6,IF(C14=3,'PERCENTIL GROSSMAN'!H6,IF(C14=4,'PERCENTIL GROSSMAN'!J6,IF(C14=5,'PERCENTIL GROSSMAN'!L6,IF(C14=6,'PERCENTIL GROSSMAN'!N6,IF(C14=7,'PERCENTIL GROSSMAN'!P6,IF(C14=8,'PERCENTIL GROSSMAN'!R6,IF(C14=9,'PERCENTIL GROSSMAN'!T6)))))))))) -> 30 | E14: =REPT("g",D14/2) -> ggggggggggggggg | G14: 6 | H14: Explosiones de Ira | I14: ='RPTA SIGNIFICATIVAS'!C14 -> 0 | J14: ='RPTA SIGNIFICATIVAS'!D14 -> 0
A15: 2A.2 | B15: Autoimagen Alienada | C15: =APLICACION!D35+APLICACION!D70+APLICACION!E79+APLICACION!D123+APLICACION!D147+APLICACION!D168+APLICACION!D190+APLICACION!D204+APLICACION!D205 -> 2 | D15: =IF(C15=0,'PERCENTIL GROSSMAN'!B7,IF(C15=1,'PERCENTIL GROSSMAN'!D7,IF(C15=2,'PERCENTIL GROSSMAN'!F7,IF(C15=3,'PERCENTIL GROSSMAN'!H7,IF(C15=4,'PERCENTIL GROSSMAN'!J7,IF(C15=5,'PERCENTIL GROSSMAN'!L7,IF(C15=6,'PERCENTIL GROSSMAN'!N7,IF(C15=7,'PERCENTIL GROSSMAN'!P7,IF(C15=8,'PERCENTIL GROSSMAN'!R7,IF(C15=9,'PERCENTIL GROSSMAN'!T7)))))))))) -> 30 | E15: =REPT("g",D15/2) -> ggggggggggggggg | G15: 7 | H15: Preocupación por su salud | I15: ='RPTA SIGNIFICATIVAS'!C15 -> 0 | J15: ='RPTA SIGNIFICATIVAS'!D15 -> 0
A16: 2A.3 | B16: Contenido Vejatorio | C16: =APLICACION!E17+APLICACION!D24+APLICACION!D36+APLICACION!D64+APLICACION!D104+APLICACION!D105+APLICACION!D124+APLICACION!D196+APLICACION!D207 -> 2 | D16: =IF(C16=0,'PERCENTIL GROSSMAN'!B8,IF(C16=1,'PERCENTIL GROSSMAN'!D8,IF(C16=2,'PERCENTIL GROSSMAN'!F8,IF(C16=3,'PERCENTIL GROSSMAN'!H8,IF(C16=4,'PERCENTIL GROSSMAN'!J8,IF(C16=5,'PERCENTIL GROSSMAN'!L8,IF(C16=6,'PERCENTIL GROSSMAN'!N8,IF(C16=7,'PERCENTIL GROSSMAN'!P8,IF(C16=8,'PERCENTIL GROSSMAN'!R8,IF(C16=9,'PERCENTIL GROSSMAN'!T8)))))))))) -> 40 | E16: =REPT("g",D16/2) -> gggggggggggggggggggg | G16: 8 | H16: Alienación Interpersonal | I16: ='RPTA SIGNIFICATIVAS'!C16 -> 0 | J16: ='RPTA SIGNIFICATIVAS'!D16 -> 0
A17: 2B | B17: Melancólico | D17: =CORRECCION!D19 -> 30 | E17: =REPT("g",D17/2) -> ggggggggggggggg | G17: 9 | H17: Abuso de Medicación | I17: ='RPTA SIGNIFICATIVAS'!C17 -> 0 | J17: ='RPTA SIGNIFICATIVAS'!D17 -> 0
A18: 2B.1 | B18: Cognitivamente Fatalista | C18: =APLICACION!D29+APLICACION!D35+APLICACION!D45+APLICACION!D63+APLICACION!D64+APLICACION!D83+APLICACION!D101+APLICACION!D138+APLICACION!D196 -> 3 | D18: =IF(C18=0,'PERCENTIL GROSSMAN'!B9,IF(C18=1,'PERCENTIL GROSSMAN'!D9,IF(C18=2,'PERCENTIL GROSSMAN'!F9,IF(C18=3,'PERCENTIL GROSSMAN'!H9,IF(C18=4,'PERCENTIL GROSSMAN'!J9,IF(C18=5,'PERCENTIL GROSSMAN'!L9,IF(C18=6,'PERCENTIL GROSSMAN'!N9,IF(C18=7,'PERCENTIL GROSSMAN'!P9,IF(C18=8,'PERCENTIL GROSSMAN'!R9,IF(C18=9,'PERCENTIL GROSSMAN'!T9)))))))))) -> 30 | E18: =REPT("g",D18/2) -> ggggggggggggggg | G18: 10 | H18: Potencial Conducta autodestructiva | I18: ='RPTA SIGNIFICATIVAS'!C18 -> 2 | J18: ='RPTA SIGNIFICATIVAS'!D18 -> 0.16666667
A19: 2B.2 | B19: Autoimagen Inutil | C19: =APLICACION!D51+APLICACION!D71+APLICACION!D105+APLICACION!D124+APLICACION!D181+APLICACION!D187+APLICACION!D190+APLICACION!D204+APLICACION!D207 -> 1 | D19: =IF(C19=0,'PERCENTIL GROSSMAN'!B10,IF(C19=1,'PERCENTIL GROSSMAN'!D10,IF(C19=2,'PERCENTIL GROSSMAN'!F10,IF(C19=3,'PERCENTIL GROSSMAN'!H10,IF(C19=4,'PERCENTIL GROSSMAN'!J10,IF(C19=5,'PERCENTIL GROSSMAN'!L10,IF(C19=6,'PERCENTIL GROSSMAN'!N10,IF(C19=7,'PERCENTIL GROSSMAN'!P10,IF(C19=8,'PERCENTIL GROSSMAN'!R10,IF(C19=9,'PERCENTIL GROSSMAN'!T10)))))))))) -> 30 | E19: =REPT("g",D19/2) -> ggggggggggggggg | G19: 11 | H19: Conductas/Tendencias Autolesivas | I19: ='RPTA SIGNIFICATIVAS'!C19 -> 0 | J19: ='RPTA SIGNIFICATIVAS'!D19 -> 0
A20: 2B.3 | B20: Temperalmente Afligido | C20: =APLICACION!D34+APLICACION!E65+APLICACION!D82+APLICACION!D102+APLICACION!D113+APLICACION!D119+APLICACION!D123+APLICACION!D182+APLICACION!D205 -> 4 | D20: =IF(C20=0,'PERCENTIL GROSSMAN'!B11,IF(C20=1,'PERCENTIL GROSSMAN'!D11,IF(C20=2,'PERCENTIL GROSSMAN'!F11,IF(C20=3,'PERCENTIL GROSSMAN'!H11,IF(C20=4,'PERCENTIL GROSSMAN'!J11,IF(C20=5,'PERCENTIL GROSSMAN'!L11,IF(C20=6,'PERCENTIL GROSSMAN'!N11,IF(C20=7,'PERCENTIL GROSSMAN'!P11,IF(C20=8,'PERCENTIL GROSSMAN'!R11,IF(C20=9,'PERCENTIL GROSSMAN'!T11)))))))))) -> 75 | E20: =REPT("g",D20/2) -> ggggggggggggggggggggggggggggggggggggg | G20: 12 | H20: Lesión Cerebral | I20: ='RPTA SIGNIFICATIVAS'!C20 -> 0 | J20: ='RPTA SIGNIFICATIVAS'!D20 -> 0
A21: 3 | B21: Dependiente | D21: =CORRECCION!D20 -> 36 | E21: =REPT("g",D21/2) -> gggggggggggggggggg | G21: 13 | H21: Tendencias Vengativas | I21: ='RPTA SIGNIFICATIVAS'!C21 -> 2 | J21: ='RPTA SIGNIFICATIVAS'!D21 -> 0.25
A22: 3.1 | B22: Expresivamente Pueril | C22: =APLICACION!D16+APLICACION!D17+APLICACION!D35+APLICACION!D63+APLICACION!D84+APLICACION!D111+APLICACION!D121+APLICACION!D147+APLICACION!D196 -> 0 | D22: =IF(C22=0,'PERCENTIL GROSSMAN'!B12,IF(C22=1,'PERCENTIL GROSSMAN'!D12,IF(C22=2,'PERCENTIL GROSSMAN'!F12,IF(C22=3,'PERCENTIL GROSSMAN'!H12,IF(C22=4,'PERCENTIL GROSSMAN'!J12,IF(C22=5,'PERCENTIL GROSSMAN'!L12,IF(C22=6,'PERCENTIL GROSSMAN'!N12,IF(C22=7,'PERCENTIL GROSSMAN'!P12,IF(C22=8,'PERCENTIL GROSSMAN'!R12,IF(C22=9,'PERCENTIL GROSSMAN'!T12)))))))))) -> 0 | E22: =REPT("g",D22/2)
A23: 3.2 | B23: Interpersonalmente Sumiso | C23: =APLICACION!D38+APLICACION!D72+APLICACION!D174+APLICACION!D181+APLICACION!D185+APLICACION!D197+APLICACION!D206 -> 3 | D23: =IF(C23=0,'PERCENTIL GROSSMAN'!B13,IF(C23=1,'PERCENTIL GROSSMAN'!D13,IF(C23=2,'PERCENTIL GROSSMAN'!F13,IF(C23=3,'PERCENTIL GROSSMAN'!H13,IF(C23=4,'PERCENTIL GROSSMAN'!J13,IF(C23=5,'PERCENTIL GROSSMAN'!L13,IF(C23=6,'PERCENTIL GROSSMAN'!N13,IF(C23=7,'PERCENTIL GROSSMAN'!P13,IF(C23=8,'PERCENTIL GROSSMAN'!R13,IF(C23=9,'PERCENTIL GROSSMAN'!T13)))))))))) -> 60 | E23: =REPT("g",D23/2) -> gggggggggggggggggggggggggggggg
A24: 3.3 | B24: Autoimagen Inepta | C24: =APLICACION!D54+APLICACION!E65+APLICACION!E79+APLICACION!D89+APLICACION!D97+APLICACION!D105+APLICACION!D145+APLICACION!D163+APLICACION!D187 -> 2 | D24: =IF(C24=0,'PERCENTIL GROSSMAN'!B14,IF(C24=1,'PERCENTIL GROSSMAN'!D14,IF(C24=2,'PERCENTIL GROSSMAN'!F14,IF(C24=3,'PERCENTIL GROSSMAN'!H14,IF(C24=4,'PERCENTIL GROSSMAN'!J14,IF(C24=5,'PERCENTIL GROSSMAN'!L14,IF(C24=6,'PERCENTIL GROSSMAN'!N14,IF(C24=7,'PERCENTIL GROSSMAN'!P14,IF(C24=8,'PERCENTIL GROSSMAN'!R14,IF(C24=9,'PERCENTIL GROSSMAN'!T14)))))))))) -> 30 | E24: =REPT("g",D24/2) -> ggggggggggggggg
A25: 4A | B25: Histriónico | D25: =CORRECCION!D21 -> 75 | E25: =REPT("g",D25/2) -> ggggggggggggggggggggggggggggggggggggg
A26: 4A.1 | B26: Expresivamente Dramatico | C26: =APLICACION!D22+APLICACION!D50+APLICACION!D95+APLICACION!D129+APLICACION!D144+APLICACION!D154+APLICACION!D183 -> 1 | D26: =IF(C26=0,'PERCENTIL GROSSMAN'!B15,IF(C26=1,'PERCENTIL GROSSMAN'!D15,IF(C26=2,'PERCENTIL GROSSMAN'!F15,IF(C26=3,'PERCENTIL GROSSMAN'!H15,IF(C26=4,'PERCENTIL GROSSMAN'!J15,IF(C26=5,'PERCENTIL GROSSMAN'!L15,IF(C26=6,'PERCENTIL GROSSMAN'!N15,IF(C26=7,'PERCENTIL GROSSMAN'!P15,IF(C26=8,'PERCENTIL GROSSMAN'!R15,IF(C26=9,'PERCENTIL GROSSMAN'!T15)))))))))) -> 60 | E26: =REPT("g",D26/2) -> gggggggggggggggggggggggggggggg | H26: Respuestas Siginificativas
A27: 4A.2 | B27: Interpersonalmente buscador de Atención | C27: =APLICACION!E18+APLICACION!E27+APLICACION!E36+APLICACION!E38+APLICACION!E38+APLICACION!D42+APLICACION!D58+APLICACION!D96+APLICACION!E151+APLICACION!D166+APLICACION!E207 -> 9 | D27: =IF(C27=0,'PERCENTIL GROSSMAN'!B16,IF(C27=1,'PERCENTIL GROSSMAN'!D16,IF(C27=2,'PERCENTIL GROSSMAN'!F16,IF(C27=3,'PERCENTIL GROSSMAN'!H16,IF(C27=4,'PERCENTIL GROSSMAN'!J16,IF(C27=5,'PERCENTIL GROSSMAN'!L16,IF(C27=6,'PERCENTIL GROSSMAN'!N16,IF(C27=7,'PERCENTIL GROSSMAN'!P16,IF(C27=8,'PERCENTIL GROSSMAN'!R16,IF(C27=9,'PERCENTIL GROSSMAN'!T16)))))))))) -> 93 | E27: =REPT("g",D27/2) -> gggggggggggggggggggggggggggggggggggggggggggggg | G27: 1 | H27: TDAH | I27: =REPT("g",J9*100/5) -> gggggg
A28: 4A.3 | B28: Temperamentalmente Inconstante | C28: =APLICACION!D20+APLICACION!D32+APLICACION!D39+APLICACION!D65+APLICACION!D79+APLICACION!D87+APLICACION!E147+APLICACION!D167+APLICACION!E182+APLICACION!D186+APLICACION!D190 -> 8 | D28: =IF(C28=0,'PERCENTIL GROSSMAN'!B17,IF(C28=1,'PERCENTIL GROSSMAN'!D17,IF(C28=2,'PERCENTIL GROSSMAN'!F17,IF(C28=3,'PERCENTIL GROSSMAN'!H17,IF(C28=4,'PERCENTIL GROSSMAN'!J17,IF(C28=5,'PERCENTIL GROSSMAN'!L17,IF(C28=6,'PERCENTIL GROSSMAN'!N17,IF(C28=7,'PERCENTIL GROSSMAN'!P17,IF(C28=8,'PERCENTIL GROSSMAN'!R17,IF(C28=9,'PERCENTIL GROSSMAN'!T17)))))))))) -> 75 | E28: =REPT("g",D28/2) -> ggggggggggggggggggggggggggggggggggggg | G28: 2 | H28: Espectro Autista | I28: =REPT("g",J10*100/5)
A29: 4B | B29: Tempestuoso | D29: =CORRECCION!D22 -> 80 | E29: =REPT("g",D29/2) -> gggggggggggggggggggggggggggggggggggggggg | G29: 3 | H29: Maltrato Infantil | I29: =REPT("g",J11*100/5) -> gggggggggggggggggggg
A30: 4B.1 | B30: Expresivamente Impetuoso | C30: =APLICACION!D20+APLICACION!D32+APLICACION!D65+APLICACION!D87+APLICACION!D141+APLICACION!D167+APLICACION!D186 -> 7 | D30: =IF(C30=0,'PERCENTIL GROSSMAN'!B18,IF(C30=1,'PERCENTIL GROSSMAN'!D18,IF(C30=2,'PERCENTIL GROSSMAN'!F18,IF(C30=3,'PERCENTIL GROSSMAN'!H18,IF(C30=4,'PERCENTIL GROSSMAN'!J18,IF(C30=5,'PERCENTIL GROSSMAN'!L18,IF(C30=6,'PERCENTIL GROSSMAN'!N18,IF(C30=7,'PERCENTIL GROSSMAN'!P18,IF(C30=8,'PERCENTIL GROSSMAN'!R18,IF(C30=9,'PERCENTIL GROSSMAN'!T18)))))))))) -> 75 | E30: =REPT("g",D30/2) -> ggggggggggggggggggggggggggggggggggggg | G30: 4 | H30: Trastornos de la conducta alimentaria | I30: =REPT("g",J12*100/5)
A31: 4B.2 | B31: Interpersonamente Eufórico | C31: =APLICACION!D17+APLICACION!D22+APLICACION!E38+APLICACION!D42+APLICACION!D58+APLICACION!D96+APLICACION!D129+APLICACION!E161+APLICACION!D166 -> 5 | D31: =IF(C31=0,'PERCENTIL GROSSMAN'!B19,IF(C31=1,'PERCENTIL GROSSMAN'!D19,IF(C31=2,'PERCENTIL GROSSMAN'!F19,IF(C31=3,'PERCENTIL GROSSMAN'!H19,IF(C31=4,'PERCENTIL GROSSMAN'!J19,IF(C31=5,'PERCENTIL GROSSMAN'!L19,IF(C31=6,'PERCENTIL GROSSMAN'!N19,IF(C31=7,'PERCENTIL GROSSMAN'!P19,IF(C31=8,'PERCENTIL GROSSMAN'!R19,IF(C31=9,'PERCENTIL GROSSMAN'!T19)))))))))) -> 70 | E31: =REPT("g",D31/2) -> ggggggggggggggggggggggggggggggggggg | G31: 5 | H31: Falta de Control Emocional | I31: =REPT("g",J13*100/5) -> gg
A32: 4B.3 | B32: Autoimagen Sobreestimada | C32: =APLICACION!E26+APLICACION!D79+APLICACION!E105+APLICACION!E132+APLICACION!D154+APLICACION!E168+APLICACION!E187+APLICACION!E190 -> 7 | D32: =IF(C32=0,'PERCENTIL GROSSMAN'!B20,IF(C32=1,'PERCENTIL GROSSMAN'!D20,IF(C32=2,'PERCENTIL GROSSMAN'!F20,IF(C32=3,'PERCENTIL GROSSMAN'!H20,IF(C32=4,'PERCENTIL GROSSMAN'!J20,IF(C32=5,'PERCENTIL GROSSMAN'!L20,IF(C32=6,'PERCENTIL GROSSMAN'!N20,IF(C32=7,'PERCENTIL GROSSMAN'!P20,IF(C32=8,'PERCENTIL GROSSMAN'!R20,IF(C32=9,'PERCENTIL GROSSMAN'!T20)))))))))) -> 85 | E32: =REPT("g",D32/2) -> gggggggggggggggggggggggggggggggggggggggggg | G32: 6 | H32: Explosiones de Ira | I32: =REPT("g",J14*100/5)
A33: 5 | B33: Narcisista | D33: =CORRECCION!D23 -> 62 | E33: =REPT("g",D33/2) -> ggggggggggggggggggggggggggggggg | G33: 7 | H33: Preocupación por su salud | I33: =REPT("g",J15*100/5)
A34: 5.1 | B34: Interpersonalmente Explotador | C34: =APLICACION!D22+APLICACION!D31+APLICACION!D50+APLICACION!D95+APLICACION!D129+APLICACION!D144+APLICACION!D171+APLICACION!D183+APLICACION!D195 -> 1 | D34: =IF(C34=0,'PERCENTIL GROSSMAN'!B21,IF(C34=1,'PERCENTIL GROSSMAN'!D21,IF(C34=2,'PERCENTIL GROSSMAN'!F21,IF(C34=3,'PERCENTIL GROSSMAN'!H21,IF(C34=4,'PERCENTIL GROSSMAN'!J21,IF(C34=5,'PERCENTIL GROSSMAN'!L21,IF(C34=6,'PERCENTIL GROSSMAN'!N21,IF(C34=7,'PERCENTIL GROSSMAN'!P21,IF(C34=8,'PERCENTIL GROSSMAN'!R21,IF(C34=9,'PERCENTIL GROSSMAN'!T21)))))))))) -> 60 | E34: =REPT("g",D34/2) -> gggggggggggggggggggggggggggggg | G34: 8 | H34: Alienación Interpersonal | I34: =REPT("g",J16*100/5)
A35: 5.2 | B35: Cognitivamente Expansivo | C35: =APLICACION!D20+APLICACION!D79+APLICACION!D87+APLICACION!E105+APLICACION!D154+APLICACION!D166+APLICACION!D167+APLICACION!D186+APLICACION!E190+APLICACION!D197 -> 9 | D35: =IF(C35=0,'PERCENTIL GROSSMAN'!B22,IF(C35=1,'PERCENTIL GROSSMAN'!D22,IF(C35=2,'PERCENTIL GROSSMAN'!F22,IF(C35=3,'PERCENTIL GROSSMAN'!H22,IF(C35=4,'PERCENTIL GROSSMAN'!J22,IF(C35=5,'PERCENTIL GROSSMAN'!L22,IF(C35=6,'PERCENTIL GROSSMAN'!N22,IF(C35=7,'PERCENTIL GROSSMAN'!P22,IF(C35=8,'PERCENTIL GROSSMAN'!R22,IF(C35=9,'PERCENTIL GROSSMAN'!T22)))))))))) -> 85 | E35: =REPT("g",D35/2) -> gggggggggggggggggggggggggggggggggggggggggg | G35: 9 | H35: Abuso de Medicación | I35: =REPT("g",J17*100/5)
A36: 5.3 | B36: Autoimagen Admirable | C36: =APLICACION!D41+APLICACION!D66+APLICACION!D91+APLICACION!D99+APLICACION!D118+APLICACION!D192+APLICACION!D201 -> 1 | D36: =IF(C36=0,'PERCENTIL GROSSMAN'!B23,IF(C36=1,'PERCENTIL GROSSMAN'!D23,IF(C36=2,'PERCENTIL GROSSMAN'!F23,IF(C36=3,'PERCENTIL GROSSMAN'!H23,IF(C36=4,'PERCENTIL GROSSMAN'!J23,IF(C36=5,'PERCENTIL GROSSMAN'!L23,IF(C36=6,'PERCENTIL GROSSMAN'!N23,IF(C36=7,'PERCENTIL GROSSMAN'!P23,IF(C36=8,'PERCENTIL GROSSMAN'!R23,IF(C36=9,'PERCENTIL GROSSMAN'!T23)))))))))) -> 60 | E36: =REPT("g",D36/2) -> gggggggggggggggggggggggggggggg | G36: 10 | H36: Potencial Conducta autodestructiva | I36: =REPT("g",J18*100/5) -> ggg
A37: 6A | B37: Antisocial | D37: =CORRECCION!D24 -> 20 | E37: =REPT("g",D37/2) -> gggggggggg | G37: 11 | H37: Conductas/Tendencias Autolesivas | I37: =REPT("g",J19*100/5)
A38: 6A.1 | B38: Intepersonalmente Responsable | C38: =APLICACION!E22+APLICACION!E50+APLICACION!D95+APLICACION!D115+APLICACION!D171+APLICACION!E183+APLICACION!D195+APLICACION!E200 -> 4 | D38: =IF(C38=0,'PERCENTIL GROSSMAN'!B24,IF(C38=1,'PERCENTIL GROSSMAN'!D24,IF(C38=2,'PERCENTIL GROSSMAN'!F24,IF(C38=3,'PERCENTIL GROSSMAN'!H24,IF(C38=4,'PERCENTIL GROSSMAN'!J24,IF(C38=5,'PERCENTIL GROSSMAN'!L24,IF(C38=6,'PERCENTIL GROSSMAN'!N24,IF(C38=7,'PERCENTIL GROSSMAN'!P24,IF(C38=8,'PERCENTIL GROSSMAN'!R24,IF(C38=9,'PERCENTIL GROSSMAN'!T24)))))))))) -> 75 | E38: =REPT("g",D38/2) -> ggggggggggggggggggggggggggggggggggggg | G38: 12 | H38: Lesión Cerebral | I38: =REPT("g",J20*100/5)
A39: 6A.2 | B39: Autoimagen Autónoma | C39: =APLICACION!D23+APLICACION!D31+APLICACION!E60+APLICACION!E85+APLICACION!D159+APLICACION!D164+APLICACION!D165+APLICACION!E170+APLICACION!D180+APLICACION!E203 -> 3 | D39: =IF(C39=0,'PERCENTIL GROSSMAN'!B25,IF(C39=1,'PERCENTIL GROSSMAN'!D25,IF(C39=2,'PERCENTIL GROSSMAN'!F25,IF(C39=3,'PERCENTIL GROSSMAN'!H25,IF(C39=4,'PERCENTIL GROSSMAN'!J25,IF(C39=5,'PERCENTIL GROSSMAN'!L25,IF(C39=6,'PERCENTIL GROSSMAN'!N25,IF(C39=7,'PERCENTIL GROSSMAN'!P25,IF(C39=8,'PERCENTIL GROSSMAN'!R25,IF(C39=9,'PERCENTIL GROSSMAN'!T25)))))))))) -> 65 | E39: =REPT("g",D39/2) -> gggggggggggggggggggggggggggggggg | G39: 13 | H39: Tendencias Vengativas | I39: =REPT("g",J21*100/5) -> ggggg
A40: 6A.3 | B40: Dinámicas de Irreflexión | C40: =APLICACION!D37+APLICACION!D48+APLICACION!D73+APLICACION!E75+APLICACION!D97+APLICACION!D117+APLICACION!D138+APLICACION!D142+APLICACION!D156 -> 1 | D40: =IF(C40=0,'PERCENTIL GROSSMAN'!B26,IF(C40=1,'PERCENTIL GROSSMAN'!D26,IF(C40=2,'PERCENTIL GROSSMAN'!F26,IF(C40=3,'PERCENTIL GROSSMAN'!H26,IF(C40=4,'PERCENTIL GROSSMAN'!J26,IF(C40=5,'PERCENTIL GROSSMAN'!L26,IF(C40=6,'PERCENTIL GROSSMAN'!N26,IF(C40=7,'PERCENTIL GROSSMAN'!P26,IF(C40=8,'PERCENTIL GROSSMAN'!R26,IF(C40=9,'PERCENTIL GROSSMAN'!T26)))))))))) -> 60 | E40: =REPT("g",D40/2) -> gggggggggggggggggggggggggggggg
A41: 6B | B41: Sádico | D41: =CORRECCION!D25 -> 10 | E41: =REPT("g",D41/2) -> ggggg
A42: 6B.1 | B42: Expresivamente Precipitado | C42: =APLICACION!D21+APLICACION!D23+APLICACION!D77+APLICACION!D78+APLICACION!D100+APLICACION!D115+APLICACION!D164+APLICACION!D165+APLICACION!D171 -> 2 | D42: =IF(C42=0,'PERCENTIL GROSSMAN'!B27,IF(C42=1,'PERCENTIL GROSSMAN'!D27,IF(C42=2,'PERCENTIL GROSSMAN'!F27,IF(C42=3,'PERCENTIL GROSSMAN'!H27,IF(C42=4,'PERCENTIL GROSSMAN'!J27,IF(C42=5,'PERCENTIL GROSSMAN'!L27,IF(C42=6,'PERCENTIL GROSSMAN'!N27,IF(C42=7,'PERCENTIL GROSSMAN'!P27,IF(C42=8,'PERCENTIL GROSSMAN'!R27,IF(C42=9,'PERCENTIL GROSSMAN'!T27)))))))))) -> 40 | E42: =REPT("g",D42/2) -> gggggggggggggggggggg
A43: 6B.2 | B43: Interpersonalmente Desagradable | C43: =APLICACION!D31+APLICACION!D33+APLICACION!D62+APLICACION!D109+APLICACION!D153+APLICACION!E178+APLICACION!D199 -> 2 | D43: =IF(C43=0,'PERCENTIL GROSSMAN'!B28,IF(C43=1,'PERCENTIL GROSSMAN'!D28,IF(C43=2,'PERCENTIL GROSSMAN'!F28,IF(C43=3,'PERCENTIL GROSSMAN'!H28,IF(C43=4,'PERCENTIL GROSSMAN'!J28,IF(C43=5,'PERCENTIL GROSSMAN'!L28,IF(C43=6,'PERCENTIL GROSSMAN'!N28,IF(C43=7,'PERCENTIL GROSSMAN'!P28,IF(C43=8,'PERCENTIL GROSSMAN'!R28,IF(C43=9,'PERCENTIL GROSSMAN'!T28)))))))))) -> 64 | E43: =REPT("g",D43/2) -> gggggggggggggggggggggggggggggggg
A44: 6B.3 | B44: Arquitectura Eruptiva | C44: =APLICACION!D28+APLICACION!D49+APLICACION!D86+APLICACION!D127+APLICACION!D149+APLICACION!D157+APLICACION!D180 -> 0 | D44: =IF(C44=0,'PERCENTIL GROSSMAN'!B29,IF(C44=1,'PERCENTIL GROSSMAN'!D29,IF(C44=2,'PERCENTIL GROSSMAN'!F29,IF(C44=3,'PERCENTIL GROSSMAN'!H29,IF(C44=4,'PERCENTIL GROSSMAN'!J29,IF(C44=5,'PERCENTIL GROSSMAN'!L29,IF(C44=6,'PERCENTIL GROSSMAN'!N29,IF(C44=7,'PERCENTIL GROSSMAN'!P29,IF(C44=8,'PERCENTIL GROSSMAN'!R29,IF(C44=9,'PERCENTIL GROSSMAN'!T29)))))))))) -> 0 | E44: =REPT("g",D44/2)
A45: 7 | B45: Compulsivo | D45: =CORRECCION!D26 -> 49 | E45: =REPT("g",D45/2) -> gggggggggggggggggggggggg
A46: 7.1 | B46: Expresivamente Disciplinado | C46: =APLICACION!D14+APLICACION!D32+APLICACION!D47+APLICACION!D75+APLICACION!E97+APLICACION!E130+APLICACION!D186+APLICACION!D200 -> 6 | D46: =IF(C46=0,'PERCENTIL GROSSMAN'!B30,IF(C46=1,'PERCENTIL GROSSMAN'!D30,IF(C46=2,'PERCENTIL GROSSMAN'!F30,IF(C46=3,'PERCENTIL GROSSMAN'!H30,IF(C46=4,'PERCENTIL GROSSMAN'!J30,IF(C46=5,'PERCENTIL GROSSMAN'!L30,IF(C46=6,'PERCENTIL GROSSMAN'!N30,IF(C46=7,'PERCENTIL GROSSMAN'!P30,IF(C46=8,'PERCENTIL GROSSMAN'!R30,IF(C46=9,'PERCENTIL GROSSMAN'!T30)))))))))) -> 75 | E46: =REPT("g",D46/2) -> ggggggggggggggggggggggggggggggggggggg
A47: 7.2 | B47: Cognitivamente Constreñido | C47: =APLICACION!D35+APLICACION!D56+APLICACION!D63+APLICACION!D64+APLICACION!D111+APLICACION!D140+APLICACION!D143+APLICACION!D147+APLICACION!D149 -> 1 | D47: =IF(C47=0,'PERCENTIL GROSSMAN'!B31,IF(C47=1,'PERCENTIL GROSSMAN'!D31,IF(C47=2,'PERCENTIL GROSSMAN'!F31,IF(C47=3,'PERCENTIL GROSSMAN'!H31,IF(C47=4,'PERCENTIL GROSSMAN'!J31,IF(C47=5,'PERCENTIL GROSSMAN'!L31,IF(C47=6,'PERCENTIL GROSSMAN'!N31,IF(C47=7,'PERCENTIL GROSSMAN'!P31,IF(C47=8,'PERCENTIL GROSSMAN'!R31,IF(C47=9,'PERCENTIL GROSSMAN'!T31)))))))))) -> 9 | E47: =REPT("g",D47/2) -> gggg
A48: 7.3 | B48: Autoimagen Escrupulosa | C48: =APLICACION!E31+APLICACION!D60+APLICACION!D85+APLICACION!E95+APLICACION!E159+APLICACION!E164+APLICACION!D170+APLICACION!E195+APLICACION!D203 -> 7 | D48: =IF(C48=0,'PERCENTIL GROSSMAN'!B32,IF(C48=1,'PERCENTIL GROSSMAN'!D32,IF(C48=2,'PERCENTIL GROSSMAN'!F32,IF(C48=3,'PERCENTIL GROSSMAN'!H32,IF(C48=4,'PERCENTIL GROSSMAN'!J32,IF(C48=5,'PERCENTIL GROSSMAN'!L32,IF(C48=6,'PERCENTIL GROSSMAN'!N32,IF(C48=7,'PERCENTIL GROSSMAN'!P32,IF(C48=8,'PERCENTIL GROSSMAN'!R32,IF(C48=9,'PERCENTIL GROSSMAN'!T32)))))))))) -> 60 | E48: =REPT("g",D48/2) -> gggggggggggggggggggggggggggggg
A49: 8A | B49: Negativista | D49: =CORRECCION!D27 -> 60 | E49: =REPT("g",D49/2) -> gggggggggggggggggggggggggggggg
A50: 8A.1 | B50: Expresivamente Resentido | C50: =APLICACION!D33+APLICACION!D44+APLICACION!D91+APLICACION!D100+APLICACION!D108+APLICACION!D112+APLICACION!D134+APLICACION!D179+APLICACION!D184 -> 4 | D50: =IF(C50=0,'PERCENTIL GROSSMAN'!B33,IF(C50=1,'PERCENTIL GROSSMAN'!D33,IF(C50=2,'PERCENTIL GROSSMAN'!F33,IF(C50=3,'PERCENTIL GROSSMAN'!H33,IF(C50=4,'PERCENTIL GROSSMAN'!J33,IF(C50=5,'PERCENTIL GROSSMAN'!L33,IF(C50=6,'PERCENTIL GROSSMAN'!N33,IF(C50=7,'PERCENTIL GROSSMAN'!P33,IF(C50=8,'PERCENTIL GROSSMAN'!R33,IF(C50=9,'PERCENTIL GROSSMAN'!T33)))))))))) -> 68 | E50: =REPT("g",D50/2) -> gggggggggggggggggggggggggggggggggg
A51: 8A.2 | B51: Autoimagen Descontenta | C51: =APLICACION!D24+APLICACION!D29+APLICACION!D36+APLICACION!D46+APLICACION!D51+APLICACION!D63+APLICACION!D64+APLICACION!D71+APLICACION!E87+APLICACION!D165 -> 2 | D51: =IF(C51=0,'PERCENTIL GROSSMAN'!B34,IF(C51=1,'PERCENTIL GROSSMAN'!D34,IF(C51=2,'PERCENTIL GROSSMAN'!F34,IF(C51=3,'PERCENTIL GROSSMAN'!H34,IF(C51=4,'PERCENTIL GROSSMAN'!J34,IF(C51=5,'PERCENTIL GROSSMAN'!L34,IF(C51=6,'PERCENTIL GROSSMAN'!N34,IF(C51=7,'PERCENTIL GROSSMAN'!P34,IF(C51=8,'PERCENTIL GROSSMAN'!R34,IF(C51=9,'PERCENTIL GROSSMAN'!T34)))))))))) -> 30 | E51: =REPT("g",D51/2) -> ggggggggggggggg
A52: 8A.3 | B52: Temperalmente Irritable | C52: =APLICACION!D21+APLICACION!D49+APLICACION!D86+APLICACION!D94+APLICACION!D109+APLICACION!D127+APLICACION!D149+APLICACION!D157+APLICACION!D180 -> 1 | D52: =IF(C52=0,'PERCENTIL GROSSMAN'!B35,IF(C52=1,'PERCENTIL GROSSMAN'!D35,IF(C52=2,'PERCENTIL GROSSMAN'!F35,IF(C52=3,'PERCENTIL GROSSMAN'!H35,IF(C52=4,'PERCENTIL GROSSMAN'!J35,IF(C52=5,'PERCENTIL GROSSMAN'!L35,IF(C52=6,'PERCENTIL GROSSMAN'!N35,IF(C52=7,'PERCENTIL GROSSMAN'!P35,IF(C52=8,'PERCENTIL GROSSMAN'!R35,IF(C52=9,'PERCENTIL GROSSMAN'!T35)))))))))) -> 20 | E52: =REPT("g",D52/2) -> gggggggggg
A53: 8B | B53: Masoquista | D53: =CORRECCION!D28 -> 38 | E53: =REPT("g",D53/2) -> ggggggggggggggggggg
A54: 8B.1 | B54: Autoimagen Desmerecedora | C54: =APLICACION!D16+APLICACION!D24+APLICACION!D35+APLICACION!D51+APLICACION!D64+APLICACION!D71+APLICACION!D82+APLICACION!D105+APLICACION!D176 -> 2 | D54: =IF(C54=0,'PERCENTIL GROSSMAN'!B36,IF(C54=1,'PERCENTIL GROSSMAN'!D36,IF(C54=2,'PERCENTIL GROSSMAN'!F36,IF(C54=3,'PERCENTIL GROSSMAN'!H36,IF(C54=4,'PERCENTIL GROSSMAN'!J36,IF(C54=5,'PERCENTIL GROSSMAN'!L36,IF(C54=6,'PERCENTIL GROSSMAN'!N36,IF(C54=7,'PERCENTIL GROSSMAN'!P36,IF(C54=8,'PERCENTIL GROSSMAN'!R36,IF(C54=9,'PERCENTIL GROSSMAN'!T36)))))))))) -> 30 | E54: =REPT("g",D54/2) -> ggggggggggggggg
A55: 8B.2 | B55: Arquitectura Invertida | C55: =APLICACION!D29+APLICACION!D52+APLICACION!D97+APLICACION!D112+APLICACION!D138+APLICACION!D168+APLICACION!D178+APLICACION!D179+APLICACION!D196 -> 2 | D55: =IF(C55=0,'PERCENTIL GROSSMAN'!B37,IF(C55=1,'PERCENTIL GROSSMAN'!D37,IF(C55=2,'PERCENTIL GROSSMAN'!F37,IF(C55=3,'PERCENTIL GROSSMAN'!H37,IF(C55=4,'PERCENTIL GROSSMAN'!J37,IF(C55=5,'PERCENTIL GROSSMAN'!L37,IF(C55=6,'PERCENTIL GROSSMAN'!N37,IF(C55=7,'PERCENTIL GROSSMAN'!P37,IF(C55=8,'PERCENTIL GROSSMAN'!R37,IF(C55=9,'PERCENTIL GROSSMAN'!T37)))))))))) -> 40 | E55: =REPT("g",D55/2) -> gggggggggggggggggggg
A56: 8B.3 | B56: Temperamentalmente Disfórico | C56: =APLICACION!D32+APLICACION!D65+APLICACION!E79+APLICACION!D87+APLICACION!D104+APLICACION!D119+APLICACION!D166+APLICACION!D167+APLICACION!E182 -> 5 | D56: =IF(C56=0,'PERCENTIL GROSSMAN'!B38,IF(C56=1,'PERCENTIL GROSSMAN'!D38,IF(C56=2,'PERCENTIL GROSSMAN'!F38,IF(C56=3,'PERCENTIL GROSSMAN'!H38,IF(C56=4,'PERCENTIL GROSSMAN'!J38,IF(C56=5,'PERCENTIL GROSSMAN'!L38,IF(C56=6,'PERCENTIL GROSSMAN'!N38,IF(C56=7,'PERCENTIL GROSSMAN'!P38,IF(C56=8,'PERCENTIL GROSSMAN'!R38,IF(C56=9,'PERCENTIL GROSSMAN'!T38)))))))))) -> 60 | E56: =REPT("g",D56/2) -> gggggggggggggggggggggggggggggg
A57: S | B57: Esquizotípico | D57: =CORRECCION!D30 -> 12 | E57: =REPT("g",D57/2) -> gggggg
A58: S1 | B58: Cognitivamente Circunstancial | C58: =APLICACION!D30+APLICACION!D45+APLICACION!D56+APLICACION!D101+APLICACION!D133+APLICACION!D135+APLICACION!D143+APLICACION!D175 -> 1 | D58: =IF(C58=0,'PERCENTIL GROSSMAN'!B39,IF(C58=1,'PERCENTIL GROSSMAN'!D39,IF(C58=2,'PERCENTIL GROSSMAN'!F39,IF(C58=3,'PERCENTIL GROSSMAN'!H39,IF(C58=4,'PERCENTIL GROSSMAN'!J39,IF(C58=5,'PERCENTIL GROSSMAN'!L39,IF(C58=6,'PERCENTIL GROSSMAN'!N39,IF(C58=7,'PERCENTIL GROSSMAN'!P39,IF(C58=8,'PERCENTIL GROSSMAN'!R39,IF(C58=9,'PERCENTIL GROSSMAN'!T39)))))))))) -> 15 | E58: =REPT("g",D58/2) -> ggggggg
A59: S2 | B59: Autoimagen Disociada | C59: =APLICACION!D17+APLICACION!D70+APLICACION!D82+APLICACION!D102+APLICACION!D105+APLICACION!D123+APLICACION!D138+APLICACION!E166+APLICACION!D168+APLICACION!D178 -> 2 | D59: =IF(C59=0,'PERCENTIL GROSSMAN'!B40,IF(C59=1,'PERCENTIL GROSSMAN'!D40,IF(C59=2,'PERCENTIL GROSSMAN'!F40,IF(C59=3,'PERCENTIL GROSSMAN'!H40,IF(C59=4,'PERCENTIL GROSSMAN'!J40,IF(C59=5,'PERCENTIL GROSSMAN'!L40,IF(C59=6,'PERCENTIL GROSSMAN'!N40,IF(C59=7,'PERCENTIL GROSSMAN'!P40,IF(C59=8,'PERCENTIL GROSSMAN'!R40,IF(C59=9,'PERCENTIL GROSSMAN'!T40)))))))))) -> 40 | E59: =REPT("g",D59/2) -> gggggggggggggggggggg
A60: S3 | B60: Contenido Caótico | C60: =APLICACION!D25+APLICACION!D36+APLICACION!D80+APLICACION!D91+APLICACION!D100+APLICACION!D118+APLICACION!D124+APLICACION!D160+APLICACION!D179 -> 2 | D60: =IF(C60=0,'PERCENTIL GROSSMAN'!B41,IF(C60=1,'PERCENTIL GROSSMAN'!D41,IF(C60=2,'PERCENTIL GROSSMAN'!F41,IF(C60=3,'PERCENTIL GROSSMAN'!H41,IF(C60=4,'PERCENTIL GROSSMAN'!J41,IF(C60=5,'PERCENTIL GROSSMAN'!L41,IF(C60=6,'PERCENTIL GROSSMAN'!N41,IF(C60=7,'PERCENTIL GROSSMAN'!P41,IF(C60=8,'PERCENTIL GROSSMAN'!R41,IF(C60=9,'PERCENTIL GROSSMAN'!T41)))))))))) -> 60 | E60: =REPT("g",D60/2) -> gggggggggggggggggggggggggggggg
A61: C | B61: Límite | D61: =CORRECCION!D31 -> 45 | E61: =REPT("g",D61/2) -> gggggggggggggggggggggg
A62: C1 | B62: Autoimagen Inestable | C62: =APLICACION!D26+APLICACION!D82+APLICACION!D113+APLICACION!D123+APLICACION!D163+APLICACION!D168+APLICACION!D182+APLICACION!D190 -> 4 | D62: =IF(C62=0,'PERCENTIL GROSSMAN'!B42,IF(C62=1,'PERCENTIL GROSSMAN'!D42,IF(C62=2,'PERCENTIL GROSSMAN'!F42,IF(C62=3,'PERCENTIL GROSSMAN'!H42,IF(C62=4,'PERCENTIL GROSSMAN'!J42,IF(C62=5,'PERCENTIL GROSSMAN'!L42,IF(C62=6,'PERCENTIL GROSSMAN'!N42,IF(C62=7,'PERCENTIL GROSSMAN'!P42,IF(C62=8,'PERCENTIL GROSSMAN'!R42,IF(C62=9,'PERCENTIL GROSSMAN'!T42)))))))))) -> 65 | E62: =REPT("g",D62/2) -> gggggggggggggggggggggggggggggggg
A63: C2 | B63: Arquitectura Disgregada | C63: =APLICACION!D16+APLICACION!D29+APLICACION!D51+APLICACION!D71+APLICACION!D105+APLICACION!D112+APLICACION!D138+APLICACION!D146+APLICACION!D178 -> 0 | D63: =IF(C63=0,'PERCENTIL GROSSMAN'!B43,IF(C63=1,'PERCENTIL GROSSMAN'!D43,IF(C63=2,'PERCENTIL GROSSMAN'!F43,IF(C63=3,'PERCENTIL GROSSMAN'!H43,IF(C63=4,'PERCENTIL GROSSMAN'!J43,IF(C63=5,'PERCENTIL GROSSMAN'!L43,IF(C63=6,'PERCENTIL GROSSMAN'!N43,IF(C63=7,'PERCENTIL GROSSMAN'!P43,IF(C63=8,'PERCENTIL GROSSMAN'!R43,IF(C63=9,'PERCENTIL GROSSMAN'!T43)))))))))) -> 0 | E63: =REPT("g",D63/2)
A64: C3 | B64: Temperalmente Labil | C64: =APLICACION!D28+APLICACION!D30+APLICACION!D49+APLICACION!D86+APLICACION!D92+APLICACION!D94+APLICACION!D127+APLICACION!D149+APLICACION!D176 -> 2 | D64: =IF(C64=0,'PERCENTIL GROSSMAN'!B44,IF(C64=1,'PERCENTIL GROSSMAN'!D44,IF(C64=2,'PERCENTIL GROSSMAN'!F44,IF(C64=3,'PERCENTIL GROSSMAN'!H44,IF(C64=4,'PERCENTIL GROSSMAN'!J44,IF(C64=5,'PERCENTIL GROSSMAN'!L44,IF(C64=6,'PERCENTIL GROSSMAN'!N44,IF(C64=7,'PERCENTIL GROSSMAN'!P44,IF(C64=8,'PERCENTIL GROSSMAN'!R44,IF(C64=9,'PERCENTIL GROSSMAN'!T44)))))))))) -> 40 | E64: =REPT("g",D64/2) -> gggggggggggggggggggg
A65: P | B65: Paranoide | D65: =CORRECCION!D32 -> 66 | E65: =REPT("g",D65/2) -> ggggggggggggggggggggggggggggggggg
A66: P1 | B66: Expresivamente Defensivo | C66: =APLICACION!D24+APLICACION!D27+APLICACION!D33+APLICACION!D36+APLICACION!D116+APLICACION!D161+APLICACION!D165+APLICACION!D192+APLICACION!D207 -> 3 | D66: =IF(C66=0,'PERCENTIL GROSSMAN'!B45,IF(C66=1,'PERCENTIL GROSSMAN'!D45,IF(C66=2,'PERCENTIL GROSSMAN'!F45,IF(C66=3,'PERCENTIL GROSSMAN'!H45,IF(C66=4,'PERCENTIL GROSSMAN'!J45,IF(C66=5,'PERCENTIL GROSSMAN'!L45,IF(C66=6,'PERCENTIL GROSSMAN'!N45,IF(C66=7,'PERCENTIL GROSSMAN'!P45,IF(C66=8,'PERCENTIL GROSSMAN'!R45,IF(C66=9,'PERCENTIL GROSSMAN'!T45)))))))))) -> 60 | E66: =REPT("g",D66/2) -> gggggggggggggggggggggggggggggg
A67: P2 | B67: Cognitivamente Desconfiado | C67: =APLICACION!D29+APLICACION!D64+APLICACION!D91+APLICACION!D100+APLICACION!D184+APLICACION!D194+APLICACION!D196 -> 2 | D67: =IF(C67=0,'PERCENTIL GROSSMAN'!B46,IF(C67=1,'PERCENTIL GROSSMAN'!D46,IF(C67=2,'PERCENTIL GROSSMAN'!F46,IF(C67=3,'PERCENTIL GROSSMAN'!H46,IF(C67=4,'PERCENTIL GROSSMAN'!J46,IF(C67=5,'PERCENTIL GROSSMAN'!L46,IF(C67=6,'PERCENTIL GROSSMAN'!N46,IF(C67=7,'PERCENTIL GROSSMAN'!P46,IF(C67=8,'PERCENTIL GROSSMAN'!R46,IF(C67=9,'PERCENTIL GROSSMAN'!T46)))))))))) -> 60 | E67: =REPT("g",D67/2) -> gggggggggggggggggggggggggggggg
A68: P3 | B68: Dinámicas de Proyección | C68: =APLICACION!D25+APLICACION!D44+APLICACION!D80+APLICACION!D108+APLICACION!D118+APLICACION!D124+APLICACION!D134+APLICACION!D148+APLICACION!D160 -> 1 | D68: =IF(C68=0,'PERCENTIL GROSSMAN'!B47,IF(C68=1,'PERCENTIL GROSSMAN'!D47,IF(C68=2,'PERCENTIL GROSSMAN'!F47,IF(C68=3,'PERCENTIL GROSSMAN'!H47,IF(C68=4,'PERCENTIL GROSSMAN'!J47,IF(C68=5,'PERCENTIL GROSSMAN'!L47,IF(C68=6,'PERCENTIL GROSSMAN'!N47,IF(C68=7,'PERCENTIL GROSSMAN'!P47,IF(C68=8,'PERCENTIL GROSSMAN'!R47,IF(C68=9,'PERCENTIL GROSSMAN'!T47)))))))))) -> 30 | E68: =REPT("g",D68/2) -> ggggggggggggggg
E69: =REPT("g",D69/2)

Sheet CORRECCION
C3: Nombre:
C4: =APLICACION!B10 -> 0
B9: ESCALA DE VALIDEZ | C9: Escalas de Validez | D9: PD
B10: V | C10: Invalidez | D10: ='RESULTADOS '!D10 -> 1 | O10: ='RESULTADOS '!O10:T10 -> válido pero dudable, cuestionable.
B11: W | C11: Inconsistencia | D11: ='RESULTADOS '!D11 -> 7 | O11: ='RESULTADOS '!O11:T11 -> consistente.
B12: X | C12: Sinceridad | D12: ='RESULTADOS '!D12 -> 30 | K12: =APLICACION!G63 -> 26 | O12: ='RESULTADOS '!O12:T12 -> clínicamente interpretable
B13: Y | C13: Deseabilidad Social | D13: ='RESULTADOS '!D13 -> 78 | K13: =APLICACION!G64 -> 18 | O13: ='RESULTADOS '!O13:T13 -> Tendencia a parecer socialmente agradable, moralmente admirable o emocionalmente equilibrado. Tendencia a mostrar una imagen de sí mismo positiva e interesante. Cuanto más alta sea la puntuación, más probable es que el paciente haya ocultado ciertos aspectos de sus dificultades psicológicas o interpersonales.
B14: Z | C14: Devaluación | D14: ='RESULTADOS '!D14 -> 37 | K14: =APLICACION!G65 -> 4 | O14: ='RESULTADOS '!O14:T14 -> Tendencia del sujeto a menospreciarse o subestimarse manifestando más problemas emocionales y perso¬nales de los que un análisis posterior pueda reflejar.
B16: Patrones de Personalidad | D16: PE | H16: PERCENTIL | L16: PD
B17: 1 | C17: Esquizoide | D17: =VLOOKUP(L17,TABLAPD,E17,FALSE) -> 40 | E17: 3 | G17: 2 | H17: =IFERROR(VLOOKUP(D17,TABLAPER,G17,FALSE),"") -> 31 | L17: =APLICACION!F17 -> 6 | O17: =IF(D17<=60,"No presenta",IF(D17>=85,"Trastornos Críticos",IF(D17>=75,"Patrones menos adaptativos y Trastornos","Categoría de Riesgo"))) -> No presenta
B18: 2A | C18: Evitativo | D18: =VLOOKUP(L18,TABLAPD,E18,FALSE) -> 6 | E18: 4 | G18: 3 | H18: =IFERROR(VLOOKUP(D18,TABLAPER,G18,FALSE),"") -> 5 | L18: =APLICACION!F18 -> 1 | O18: =IF(D18<=60,"No presenta",IF(D18>=85,"Trastornos Críticos",IF(D18>=75,"Patrones menos adaptativos y Trastornos","Categoría de Riesgo"))) -> No presenta
B19: 2B | C19: Melancólico | D19: =VLOOKUP(L19,TABLAPD,E19,FALSE) -> 30 | E19: 5 | G19: 4 | H19: =IFERROR(VLOOKUP(D19,TABLAPER,G19,FALSE),"") -> 28 | L19: =APLICACION!F19 -> 6 | O19: =IF(D19<=60,"No presenta",IF(D19>=85,"Trastornos Críticos",IF(D19>=75,"Patrones menos adaptativos y Trastornos","Categoría de Riesgo"))) -> No presenta
B20: 3 | C20: Dependiente | D20: =VLOOKUP(L20,TABLAPD,E20,FALSE) -> 36 | E20: 6 | G20: 5 | H20: =IFERROR(VLOOKUP(D20,TABLAPER,G20,FALSE),"") -> 25 | L20: =APLICACION!F20 -> 6 | O20: =IF(D20<=60,"No presenta",IF(D20>=85,"Trastornos Críticos",IF(D20>=75,"Patrones menos adaptativos y Trastornos","Categoría de Riesgo"))) -> No presenta
B21: 4A | C21: Histriónico | D21: =VLOOKUP(L21,TABLAPD,E21,FALSE) -> 75 | E21: 7 | G21: 6 | H21: =IFERROR(VLOOKUP(D21,TABLAPER,G21,FALSE),"") -> 83 | L21: =APLICACION!F21 -> 15 | O21: =IF(D21<=60,"No presenta",IF(D21>=85,"Trastornos Críticos",IF(D21>=75,"Patrones menos adaptativos y Trastornos","Categoría de Riesgo"))) -> Patrones menos adaptativos y Trastornos
B22: 4B | C22: Tempestuoso | D22: =VLOOKUP(L22,TABLAPD,E22,FALSE) -> 80 | E22: 8 | G22: 7 | H22: =IFERROR(VLOOKUP(D22,TABLAPER,G22,FALSE),"") -> 93 | L22: =APLICACION!F22 -> 22 | O22: =IF(D22<=60,"No presenta",IF(D22>=85,"Trastornos Críticos",IF(D22>=75,"Patrones menos adaptativos y Trastornos","Categoría de Riesgo"))) -> Patrones menos adaptativos y Trastornos
B23: 5 | C23: Narcisista | D23: =VLOOKUP(L23,TABLAPD,E23,FALSE) -> 62 | E23: 9 | G23: 8 | H23: =IFERROR(VLOOKUP(D23,TABLAPER,G23,FALSE),"") -> 56 | L23: =APLICACION!F23 -> 6 | O23: =IF(D23<=60,"No presenta",IF(D23>=85,"Trastornos Críticos",IF(D23>=75,"Patrones menos adaptativos y Trastornos","Categoría de Riesgo"))) -> Categoría de Riesgo
B24: 6A | C24: Antisocial | D24: =VLOOKUP(L24,TABLAPD,E24,FALSE) -> 20 | E24: 10 | G24: 9 | H24: =IFERROR(VLOOKUP(D24,TABLAPER,G24,FALSE),"") -> 25 | L24: =APLICACION!F24 -> 1 | O24: =IF(D24<=60,"No presenta",IF(D24>=85,"Trastornos Críticos",IF(D24>=75,"Patrones menos adaptativos y Trastornos","Categoría de Riesgo"))) -> No presenta
B25: 6B | C25: Sádico | D25: =VLOOKUP(L25,TABLAPD,E25,FALSE) -> 10 | E25: 11 | G25: 10 | H25: =IFERROR(VLOOKUP(D25,TABLAPER,G25,FALSE),"") -> 13 | L25: =APLICACION!F25 -> 1 | O25: =IF(D25<=60,"No presenta",IF(D25>=85,"Trastornos Críticos",IF(D25>=75,"Patrones menos adaptativos y Trastornos","Categoría de Riesgo"))) -> No presenta
B26: 7 | C26: Compulsivo | D26: =VLOOKUP(L26,TABLAPD,E26,FALSE) -> 49 | E26: 12 | G26: 11 | H26: =IFERROR(VLOOKUP(D26,TABLAPER,G26,FALSE),"") -> 26 | L26: =APLICACION!F26 -> 13 | O26: =IF(D26<=60,"No presenta",IF(D26>=85,"Trastornos Críticos",IF(D26>=75,"Patrones menos adaptativos y Trastornos","Categoría de Riesgo"))) -> No presenta
B27: 8A | C27: Negativista | D27: =VLOOKUP(L27,TABLAPD,E27,FALSE) -> 60 | E27: 13 | G27: 12 | H27: =IFERROR(VLOOKUP(D27,TABLAPER,G27,FALSE),"") -> 48 | L27: =APLICACION!F27 -> 9 | O27: =IF(D27<=60,"No presenta",IF(D27>=85,"Trastornos Críticos",IF(D27>=75,"Patrones menos adaptativos y Trastornos","Categoría de Riesgo"))) -> No presenta
B28: 8B | C28: Masoquista | D28: =VLOOKUP(L28,TABLAPD,E28,FALSE) -> 38 | E28: 14 | G28: 13 | H28: =IFERROR(VLOOKUP(D28,TABLAPER,G28,FALSE),"") -> 33 | L28: =APLICACION!F28 -> 5 | O28: =IF(D28<=60,"No presenta",IF(D28>=85,"Trastornos Críticos",IF(D28>=75,"Patrones menos adaptativos y Trastornos","Categoría de Riesgo"))) -> No presenta
B29: Patologías Graves Personalidad | D29: PE | H29: PERCENTIL | L29: PD | O29: =IF(D29<=60,"No presenta",IF(D29>=85,"Trastornos Críticos",IF(D29>=75,"Patrones menos adaptativos y Trastornos","Categoría de Riesgo"))) -> Trastornos Críticos
B30: S | C30: Esquizotípico | D30: =VLOOKUP(L30,TABLAPD,E30,FALSE) -> 12 | E30: 15 | G30: 14 | H30: =IFERROR(VLOOKUP(D30,TABLAPER,G30,FALSE),"") -> 14 | L30: =APLICACION!F29 -> 2 | O30: =IF(D30<=60,"No presenta",IF(D30>=85,"Trastornos Críticos",IF(D30>=75,"Patrones menos adaptativos y Trastornos","Categoría de Riesgo"))) -> No presenta
B31: C | C31: Límite | D31: =VLOOKUP(L31,TABLAPD,E31,FALSE) -> 45 | E31: 16 | G31: 15 | H31: =IFERROR(VLOOKUP(D31,TABLAPER,G31,FALSE),"") -> 40 | L31: =APLICACION!F30 -> 6 | O31: =IF(D31<=60,"No presenta",IF(D31>=85,"Trastornos Críticos",IF(D31>=75,"Patrones menos adaptativos y Trastornos","Categoría de Riesgo"))) -> No presenta
B32: P | C32: Paranoide | D32: =VLOOKUP(L32,TABLAPD,E32,FALSE) -> 66 | E32: 17 | G32: 16 | H32: =IFERROR(VLOOKUP(D32,TABLAPER,G32,FALSE),"") -> 62 | L32: =APLICACION!F31 -> 9 | O32: =IF(D32<=60,"No presenta",IF(D32>=85,"Trastornos Críticos",IF(D32>=75,"Patrones menos adaptativos y Trastornos","Categoría de Riesgo"))) -> Categoría de Riesgo
O33: =IF(D33<=60,"No presenta",IF(D33>=85,"Trastornos Críticos",IF(D33>=75,"Patrones menos adaptativos y Trastornos","Categoría de Riesgo"))) -> No presenta
B34: Sindromes Clínicos | D34: PE | H34: PERCENTIL | L34: PD | O34: =IF(D34<=60,"No presenta",IF(D34>=85,"Trastornos Críticos",IF(D34>=75,"Patrones menos adaptativos y Trastornos","Categoría de Riesgo"))) -> Trastornos Críticos
B35: A | C35: Ansiedad Generalizada | D35: =VLOOKUP(L35,TABLAPD,E35,FALSE) -> 15 | E35: 18 | G35: 17 | H35: =IFERROR(VLOOKUP(D35,TABLAPER,G35,FALSE),"") -> 14 | L35: =APLICACION!F35 -> 2 | O35: =IF(D35<=60,"No presenta",IF(D35>=85,"Trastornos Críticos",IF(D35>=75,"Patrones menos adaptativos y Trastornos","Categoría de Riesgo"))) -> No presenta
B36: H | C36: Síntomas Somáticos | D36: =VLOOKUP(L36,TABLAPD,E36,FALSE) -> 0 | E36: 19 | G36: 18 | H36: =IFERROR(VLOOKUP(D36,TABLAPER,G36,FALSE),"") -> 11 | L36: =APLICACION!F36 -> 0 | O36: =IF(D36<=60,"No presenta",IF(D36>=85,"Trastornos Críticos",IF(D36>=75,"Patrones menos adaptativos y Trastornos","Categoría de Riesgo"))) -> No presenta
B37: N | C37: Espectro Bípolar | D37: =VLOOKUP(L37,TABLAPD,E37,FALSE) -> 30 | E37: 20 | G37: 19 | H37: =IFERROR(VLOOKUP(D37,TABLAPER,G37,FALSE),"") -> 22 | L37: =APLICACION!F37 -> 3 | O37: =IF(D37<=60,"No presenta",IF(D37>=85,"Trastornos Críticos",IF(D37>=75,"Patrones menos adaptativos y Trastornos","Categoría de Riesgo"))) -> No presenta
B38: D | C38: Depresión Persistente | D38: =VLOOKUP(L38,TABLAPD,E38,FALSE) -> 30 | E38: 21 | G38: 20 | H38: =IFERROR(VLOOKUP(D38,TABLAPER,G38,FALSE),"") -> 28 | L38: =APLICACION!F38 -> 6 | O38: =IF(D38<=60,"No presenta",IF(D38>=85,"Trastornos Críticos",IF(D38>=75,"Patrones menos adaptativos y Trastornos","Categoría de Riesgo"))) -> No presenta
B39: B | C39: Consumo de Alcohol | D39: =VLOOKUP(L39,TABLAPD,E39,FALSE) -> 0 | E39: 22 | G39: 21 | H39: =IFERROR(VLOOKUP(D39,TABLAPER,G39,FALSE),"") -> 34 | L39: =APLICACION!F39 -> 0 | O39: =IF(D39<=60,"No presenta",IF(D39>=85,"Trastornos Críticos",IF(D39>=75,"Patrones menos adaptativos y Trastornos","Categoría de Riesgo"))) -> No presenta
B40: T | C40: Consumo de Drogas | D40: =VLOOKUP(L40,TABLAPD,E40,FALSE) -> 0 | E40: 23 | G40: 22 | H40: =IFERROR(VLOOKUP(D40,TABLAPER,G40,FALSE),"") -> 24 | L40: =APLICACION!F40 -> 0 | O40: =IF(D40<=60,"No presenta",IF(D40>=85,"Trastornos Críticos",IF(D40>=75,"Patrones menos adaptativos y Trastornos","Categoría de Riesgo"))) -> No presenta
B41: R | C41: Estrés Postraumático | D41: =VLOOKUP(L41,TABLAPD,E41,FALSE) -> 48 | E41: 24 | G41: 23 | H41: =IFERROR(VLOOKUP(D41,TABLAPER,G41,FALSE),"") -> 42 | L41: =APLICACION!F41 -> 4 | O41: =IF(D41<=60,"No presenta",IF(D41>=85,"Trastornos Críticos",IF(D41>=75,"Patrones menos adaptativos y Trastornos","Categoría de Riesgo"))) -> No presenta
B42: SS | C42: Espectro Esquizofrénico | D42: =VLOOKUP(L42,TABLAPD,E42,FALSE) -> 40 | E42: 25 | G42: 24 | H42: =IFERROR(VLOOKUP(D42,TABLAPER,G42,FALSE),"") -> 33 | L42: =APLICACION!F42 -> 6 | O42: =IF(D42<=60,"No presenta",IF(D42>=85,"Trastornos Críticos",IF(D42>=75,"Patrones menos adaptativos y Trastornos","Categoría de Riesgo"))) -> No presenta
B43: CC | C43: Depresión Mayor | D43: =VLOOKUP(L43,TABLAPD,E43,FALSE) -> 51 | E43: 26 | G43: 25 | H43: =IFERROR(VLOOKUP(D43,TABLAPER,G43,FALSE),"") -> 46 | L43: =APLICACION!F43 -> 6 | O43: =IF(D43<=60,"No presenta",IF(D43>=85,"Trastornos Críticos",IF(D43>=75,"Patrones menos adaptativos y Trastornos","Categoría de Riesgo"))) -> No presenta
B44: PP | C44: Delirante | D44: =VLOOKUP(L44,TABLAPD,E44,FALSE) -> 60 | E44: 27 | G44: 26 | H44: =IFERROR(VLOOKUP(D44,TABLAPER,G44,FALSE),"") -> 51 | L44: =APLICACION!F44 -> 2 | O44: =IF(D44<=60,"No presenta",IF(D44>=85,"Trastornos Críticos",IF(D44>=75,"Patrones menos adaptativos y Trastornos","Categoría de Riesgo"))) -> No presenta

Sheet RPTA SIGNIFICATIVAS
A8: Respuestas Siginificativas | C8: PD | D8: %
A9: 1 | B9: TDAH | C9: =APLICACION!D68+APLICACION!D75+APLICACION!D89+APLICACION!D94+APLICACION!D104+APLICACION!D120 -> 2 | D9: =((C9/F9)) -> 0.33333333 | F9: 6
A10: 2 | B10: Espectro Autista | C10: =APLICACION!D104+APLICACION!D131+APLICACION!D150+APLICACION!D175+APLICACION!D177+APLICACION!D191+APLICACION!D202 -> 0 | D10: =((C10/F10)) -> 0 | F10: 7
A11: 3 | B11: Maltrato Infantil | C11: =APLICACION!D59+APLICACION!D169 -> 2 | D11: =((C11/F11)) -> 1 | F11: 2
A12: 4 | B12: Trastornos de la conducta alimentaria | C12: =APLICACION!D81+APLICACION!D98+APLICACION!D114+APLICACION!D198 -> 0 | D12: =((C12/F12)) -> 0 | F12: 4
A13: 5 | B13: Falta de Control Emocional | C13: =APLICACION!D39+APLICACION!D48+APLICACION!D57+APLICACION!D68+APLICACION!D84+APLICACION!D92+APLICACION!D139+APLICACION!D189 -> 1 | D13: =((C13/F13)) -> 0.125 | F13: 8
A14: 6 | B14: Explosiones de Ira | C14: =APLICACION!D23+APLICACION!D86+APLICACION!D127+APLICACION!D157+APLICACION!D180+APLICACION!D203 -> 0 | D14: =((C14/F14)) -> 0 | F14: 6
A15: 7 | B15: Preocupación por su salud | C15: =APLICACION!D19+APLICACION!D53+APLICACION!D69+APLICACION!D125+APLICACION!D132+APLICACION!D158 -> 0 | D15: =((C15/F15)) -> 0 | F15: 6
A16: 8 | B16: Alienación Interpersonal | C16: =APLICACION!D16+APLICACION!D116+APLICACION!D194+APLICACION!D202 -> 0 | D16: =((C16/F16)) -> 0 | F16: 4
A17: 9 | B17: Abuso de Medicación | C17: =APLICACION!D136+APLICACION!D188 -> 0 | D17: =((C17/F17)) -> 0 | F17: 2
A18: 10 | B18: Potencial Conducta autodestructiva | C18: =APLICACION!D26+APLICACION!D44+APLICACION!D46+APLICACION!D51+APLICACION!D71+APLICACION!D90+APLICACION!D113+APLICACION!D119+APLICACION!D126+APLICACION!D138+APLICACION!D163+APLICACION!D176 -> 2 | D18: =((C18/F18)) -> 0.16666667 | F18: 12
A19: 11 | B19: Conductas/Tendencias Autolesivas | C19: =APLICACION!D52+APLICACION!D193 -> 0 | D19: =((C19/F19)) -> 0 | F19: 2
A20: 12 | B20: Lesión Cerebral | C20: =APLICACION!D67+APLICACION!D122 -> 0 | D20: =((C20/F20)) -> 0 | F20: 2
A21: 13 | B21: Tendencias Vengativas | C21: =APLICACION!D34+APLICACION!D49+APLICACION!D112+APLICACION!D115+APLICACION!D148+APLICACION!D179+APLICACION!D190+APLICACION!D204 -> 2 | D21: =((C21/F21)) -> 0.25 | F21: 8

Sheet Interpretacion
E6: =APLICACION!B9 -> Nombre :Estefania Milagros Negron Huapaya
A10: Interpretacion
A12: ='Interpretacion '!A12:G12 -> La escala V señala que sus respuestas son válido pero dudable, cuestionable.
A13: ='Interpretacion '!A13:G13 -> La escala W señala que sus respuestas son consistente.
A14: ='Interpretacion '!A14:G14 -> La escala X señala que sus respuestas son clínicamente interpretable
A15: ='Interpretacion '!A15:G15 -> La escala Y señala que Tendencia a parecer socialmente agradable, moralmente admirable o emocionalmente equilibrado. Tendencia a mostrar una imagen de sí mismo positiva e interesante. Cuanto más alta sea la puntuación, más probable es que el paciente haya ocultado ciertos aspectos de sus dificultades psicológicas o interpersonales.
A16: ='Interpretacion '!A16:G16 -> La escala Z señala que trata deTendencia del sujeto a menospreciarse o subestimarse manifestando más problemas emocionales y perso¬nales de los que un análisis posterior pueda reflejar.
A19: ='Interpretacion '!A19:G19 -> En los patrones de la escala clínica de personalidad presenta
A20: ='Interpretacion '!A20:G20
A21: ='Interpretacion '!A21:G21
A22: ='Interpretacion '!A22:G22
A23: ='Interpretacion '!A23:G23
A24: ='Interpretacion '!A24:G24 -> Histriónico presenta Patrones menos adaptativos y Trastornos Se caracteriza por Los sujetos histriónicos, al igual que los dependientes, recurren a los demás, pero maximizan la atención y los favores que reciben, manipulando los hechos de una forma superficial y entusiasta. Su comportamiento social inteligente y a menudo ingenioso transmite confianza y seguridad en sí mismo; sin embargo, debajo de esta apariencia, subyace el miedo a la autonomía real y la necesidad de recibir señales recurrentes de aceptación y aprobación casi constantemente.
A25: ='Interpretacion '!A25:G25 -> Tempestuoso presenta Patrones menos adaptativos y Trastornos Se caracteriza por Los sujetos tempestuosos son muy alegres y animados, pero su persistente euforia, entrometimiento y vo¬lubilidad puede resultar irritante para los demás. Aunque son apasionados y entusiastas, se aburren con demasiada facilidad y carecen de los recursos y la regularidad necesarios para llevar a término sus objetivos y planes. Sin control, su conducta puede llegar a ser más extrema, temeraria y errática. Con bastante fre¬cuencia, este patrón tipo maníaco, puede conducir al agotamiento depresivo. De todo ello resulta un patrón de conducta impredecible, de pensamiento disperso y de acciones y estados de ánimo impetuosos e impul¬sivos, interrumpidos por arrebatos de ira momentánea y ansiedad temerosa.
... A47: ='Interpretacion '!A47:G47

Sheet Interpretacion 
R5: inferior a 7 o superior a 114, el protocolo debe considerarse inválido.
R6: Tendencia a parecer socialmente agradable, moralmente admirable o emocionalmente equilibrado. Tendencia a mostrar una imagen de sí mismo positiva e interesante. Cuanto más alta sea la puntuación, más probable es que el paciente haya ocultado ciertos aspectos de sus dificultades psicológicas o interpersonales.
A7: =CORRECCION!C4 -> 0 | N7: ESCALA DE VALIDEZ | O7: Escalas de Validez | R7: Tendencia del sujeto a menospreciarse o subestimarse manifestando más problemas emocionales y perso¬nales de los que un análisis posterior pueda reflejar.
J8: La escala V señala que sus respuestas son | N8: V | O8: Invalidez | P8: =CORRECCION!D10 -> 1 | Q8: =IF(P8=0,"100% válida.",IF(P8=1,"válido pero dudable, cuestionable.","prueba no tiene valor alguno, invalida.")) -> válido pero dudable, cuestionable. | R8: =Q8 -> válido pero dudable, cuestionable.
J9: La escala W señala que sus respuestas son | N9: W | O9: Inconsistencia | P9: =CORRECCION!D11 -> 7 | Q9: =IF(P9>18,"cuestionables o inválidos por posibles respuestas aleatorias.","consistente.") -> consistente. | R9: =Q9 -> consistente.
A10: Interpretacion | J10: La escala X señala que sus respuestas son | N10: X | O10: Sinceridad | P10: =CORRECCION!D12 -> 30 | Q10: =IF(P10<6,"el protocolo debe considerarse inválido.",IF(P10>113,"el protocolo debe considerarse inválido.","clínicamente interpretable")) -> clínicamente interpretable | R10: =Q10 -> clínicamente interpretable
J11: La escala Y señala que | N11: Y | O11: Deseabilidad Social | P11: 75 | Q11: =IF(P11<75,"1","2") -> 2 | R11: =IF(Q11="1","se muestra revelador, abierto y expresivo en sus respuestas.",R6) -> Tendencia a parecer socialmente agradable, moralmente admirable o emocionalmente equilibrado. Tendencia a mostrar una imagen de sí mismo positiva e interesante. Cuanto más alta sea la puntuación, más probable es que el paciente haya ocultado ciertos aspectos de sus dificultades psicológicas o interpersonales.
A12: =CONCATENATE(J8,R8) -> La escala V señala que sus respuestas son válido pero dudable, cuestionable. | J12: La escala Z señala que trata de | N12: Z | O12: Devaluación | P12: 76 | Q12: =IF(P12<75,"1","2") -> 2 | R12: =IF(Q12="1","tiende a presentarse tal como se ve a sí mismo, sin ocultar aquello que le parece importante sobre sus sentimientos, emociones y comportamientos.",R7) -> Tendencia del sujeto a menospreciarse o subestimarse manifestando más problemas emocionales y perso¬nales de los que un análisis posterior pueda reflejar.
A13: =CONCATENATE(J9,R9) -> La escala W señala que sus respuestas son consistente.
A14: =CONCATENATE(J10,R10) -> La escala X señala que sus respuestas son clínicamente interpretable | I14: En los patrones de la escala clínica de personalidad presenta | N14: Patrones de Personalidad
A15: =CONCATENATE(J11,R11) -> La escala Y señala que Tendencia a parecer socialmente agradable, moralmente admirable o emocionalmente equilibrado. Tendencia a mostrar una imagen de sí mismo positiva e interesante. Cuanto más alta sea la puntuación, más probable es que el paciente haya ocultado ciertos aspectos de sus dificultades psicológicas o interpersonales. | I15: =IF(R15=1,J15," ") | J15: =CONCATENATE(O15," presenta ",Q15, "Se caracteriza por ",S15) -> Esquizoide presenta No presenta Se caracteriza por | N15: 1 | O15: Esquizoide | P15: =CORRECCION!D17 -> 40 | Q15: =IF(P15<=60,"No presenta ",IF(P15>=85,"Trastornos Críticos ",IF(P15>=75,"Patrones menos adaptativos y Trastornos ","Categoría de Riesgo "))) -> No presenta | R15: =IF(P15<=60,"0",1) -> 0 | S15: =IF(R15=1,V15," ") | V15: Destacan por su falta de deseo e incapacidad de sentir placer o dolor intenso, indiferentes a las relaciones sociales, con necesidades afectivas mínimas.
A16: =CONCATENATE(J12,R12) -> La escala Z señala que trata deTendencia del sujeto a menospreciarse o subestimarse manifestando más problemas emocionales y perso¬nales de los que un análisis posterior pueda reflejar. | I16: =IF(R16=1,J16," ") | J16: =CONCATENATE(O16," presenta ",Q16, "Se caracteriza por ",S16) -> Evitativo presenta No presenta Se caracteriza por | N16: 2A | O16: Evitativo | P16: =CORRECCION!D18 -> 6 | Q16: =IF(P16<=60,"No presenta ",IF(P16>=85,"Trastornos Críticos ",IF(P16>=75,"Patrones menos adaptativos y Trastornos ","Categoría de Riesgo "))) -> No presenta | R16: =IF(P16<=60,"0",1) -> 0 | S16: =IF(R16=1,V16," ") | V16: Los sujetos evitativos experimentan pocos refuerzos positivos procedentes de sí mismos o de los demás, siempre están alerta, preparados para distanciarse de las experiencias dolorosas o negativas de la vida. Su estrategia adaptative refleja miedo y desconfianza hacia los demás. Mantienen una vigilancia constante para evitar que su anhelo de afecto resulte en la repetición del dolor y la angustia que han experimentado con otras personas. A pesar de sus deseos de relacionarse con los demás, han aprendido que es mejor negar estos sentimientos y mantener la distancia interpersonal necesaria
I17: =IF(R17=1,J17," ") | J17: =CONCATENATE(O17," presenta ",Q17, "Se caracteriza por ",S17) -> Melancólico presenta No presenta Se caracteriza por | N17: 2B | O17: Melancólico | P17: =CORRECCION!D19 -> 30 | Q17: =IF(P17<=60,"No presenta ",IF(P17>=85,"Trastornos Críticos ",IF(P17>=75,"Patrones menos adaptativos y Trastornos ","Categoría de Riesgo "))) -> No presenta | R17: =IF(P17<=60,"0",1) -> 0 | S17: =IF(R17=1,V17," ") | V17: A diferencia de los sujetos esquizoides y de los evitativos, los sujetos melancólicos experimentan el dolor como un estado permanente en el que el placer ya no se considera posible. Algunos individuos melancólicos pueden tener una predisposición biológica o química hacia el pesimismo y el desánimo, mientras que otros muestran un estilo de desesperanza ante las pérdidas importantes determinado por la experiencia. El estilo de carácter melancólico puede verse determinado por el hecho de pertenecer a una familia muy triste o des¬animada, estar en un entorno sin interés y tener una perspectiva sin esperanzas.
I18: =IF(R18=1,J18," ") | J18: =CONCATENATE(O18," presenta ",Q18, "Se caracteriza por ",S18) -> Dependiente presenta No presenta Se caracteriza por | N18: 3 | O18: Dependiente | P18: =CORRECCION!D20 -> 36 | Q18: =IF(P18<=60,"No presenta ",IF(P18>=85,"Trastornos Críticos ",IF(P18>=75,"Patrones menos adaptativos y Trastornos ","Categoría de Riesgo "))) -> No presenta | R18: =IF(P18<=60,"0",1) -> 0 | S18: =IF(R18=1,V18," ") | V18: Los sujetos dependientes destacan por su falta de iniciativa y autonomía y han aprendido no solo a recurrir a los demás para obtener afecto, cuidados y seguridad, sino también a esperar pasivamente a que sean ellos quienes los dirijan. Se caracterizan por buscar relaciones en las que puedan apoyarse para conseguir afecto y orientación; y han aprendido que es más cómodo asumir un rol pasivo en las relaciones interpersonales, aceptar las atenciones y el apoyo que puedan encontrar, y someterse voluntariamente a los deseos de los demás a fin de conservar su afecto.
A19: =I14 -> En los patrones de la escala clínica de personalidad presenta | I19: =IF(R19=1,J19," ") -> Histriónico presenta Patrones menos adaptativos y Trastornos Se caracteriza por Los sujetos histriónicos, al igual que los dependientes, recurren a los demás, pero maximizan la atención y los favores que reciben, manipulando los hechos de una forma superficial y entusiasta. Su comportamiento social inteligente y a menudo ingenioso transmite confianza y seguridad en sí mismo; sin embargo, debajo de esta apariencia, subyace el miedo a la autonomía real y la necesidad de recibir señales recurrentes de aceptación y aprobación casi constantemente. | J19: =CONCATENATE(O19," presenta ",Q19, "Se caracteriza por ",S19) -> Histriónico presenta Patrones menos adaptativos y Trastornos Se caracteriza por Los sujetos histriónicos, al igual que los dependientes, recurren a los demás, pero maximizan la atención y los favores que reciben, manipulando los hechos de una forma superficial y entusiasta. Su comportamiento social inteligente y a menudo ingenioso transmite confianza y seguridad en sí mismo; sin embargo, debajo de esta apariencia, subyace el miedo a la autonomía real y la necesidad de recibir señales recurrentes de aceptación y aprobación casi constantemente. | N19: 4A | O19: Histriónico | P19: =CORRECCION!D21 -> 75 | Q19: =IF(P19<=60,"No presenta ",IF(P19>=85,"Trastornos Críticos ",IF(P19>=75,"Patrones menos adaptativos y Trastornos ","Categoría de Riesgo "))) -> Patrones menos adaptativos y Trastornos | R19: =IF(P19<=60,"0",1) -> 1 | S19: =IF(R19=1,V19," ") -> Los sujetos histriónicos, al igual que los dependientes, recurren a los demás, pero maximizan la atención y los favores que reciben, manipulando los hechos de una forma superficial y entusiasta. Su comportamiento social inteligente y a menudo ingenioso transmite confianza y seguridad en sí mismo; sin embargo, debajo de esta apariencia, subyace el miedo a la autonomía real y la necesidad de recibir señales recurrentes de aceptación y aprobación casi constantemente. | V19: Los sujetos histriónicos, al igual que los dependientes, recurren a los demás, pero maximizan la atención y los favores que reciben, manipulando los hechos de una forma superficial y entusiasta. Su comportamiento social inteligente y a menudo ingenioso transmite confianza y seguridad en sí mismo; sin embargo, debajo de esta apariencia, subyace el miedo a la autonomía real y la necesidad de recibir señales recurrentes de aceptación y aprobación casi constantemente.
A20: =I15 | I20: =IF(R20=1,J20," ") -> Tempestuoso presenta Patrones menos adaptativos y Trastornos Se caracteriza por Los sujetos tempestuosos son muy alegres y animados, pero su persistente euforia, entrometimiento y vo¬lubilidad puede resultar irritante para los demás. Aunque son apasionados y entusiastas, se aburren con demasiada facilidad y carecen de los recursos y la regularidad necesarios para llevar a término sus objetivos y planes. Sin control, su conducta puede llegar a ser más extrema, temeraria y errática. Con bastante fre¬cuencia, este patrón tipo maníaco, puede conducir al agotamiento depresivo. De todo ello resulta un patrón de conducta impredecible, de pensamiento disperso y de acciones y estados de ánimo impetuosos e impul¬sivos, interrumpidos por arrebatos de ira momentánea y ansiedad temerosa. | J20: =CONCATENATE(O20," presenta ",Q20, "Se caracteriza por ",S20) -> Tempestuoso presenta Patrones menos adaptativos y Trastornos Se caracteriza por Los sujetos tempestuosos son muy alegres y animados, pero su persistente euforia, entrometimiento y vo¬lubilidad puede resultar irritante para los demás. Aunque son apasionados y entusiastas, se aburren con demasiada facilidad y carecen de los recursos y la regularidad necesarios para llevar a término sus objetivos y planes. Sin control, su conducta puede llegar a ser más extrema, temeraria y errática. Con bastante fre¬cuencia, este patrón tipo maníaco, puede conducir al agotamiento depresivo. De todo ello resulta un patrón de conducta impredecible, de pensamiento disperso y de acciones y estados de ánimo impetuosos e impul¬sivos, interrumpidos por arrebatos de ira momentánea y ansiedad temerosa. | N20: 4B | O20: Tempestuoso | P20: =CORRECCION!D22 -> 80 | Q20: =IF(P20<=60,"No presenta ",IF(P20>=85,"Trastornos Críticos ",IF(P20>=75,"Patrones menos adaptativos y Trastornos ","Categoría de Riesgo "))) -> Patrones menos adaptativos y Trastornos | R20: =IF(P20<=60,"0",1) -> 1 | S20: =IF(R20=1,V20," ") -> Los sujetos tempestuosos son muy alegres y animados, pero su persistente euforia, entrometimiento y vo¬lubilidad puede resultar irritante para los demás. Aunque son apasionados y entusiastas, se aburren con demasiada facilidad y carecen de los recursos y la regularidad necesarios para llevar a término sus objetivos y planes. Sin control, su conducta puede llegar a ser más extrema, temeraria y errática. Con bastante fre¬cuencia, este patrón tipo maníaco, puede conducir al agotamiento depresivo. De todo ello resulta un patrón de conducta impredecible, de pensamiento disperso y de acciones y estados de ánimo impetuosos e impul¬sivos, interrumpidos por arrebatos de ira momentánea y ansiedad temerosa. | V20: Los sujetos tempestuosos son muy alegres y animados, pero su persistente euforia, entrometimiento y vo¬lubilidad puede resultar irritante para los demás. Aunque son apasionados y entusiastas, se aburren con demasiada facilidad y carecen de los recursos y la regularidad necesarios para llevar a término sus objetivos y planes. Sin control, su conducta puede llegar a ser más extrema, temeraria y errática. Con bastante fre¬cuencia, este patrón tipo maníaco, puede conducir al agotamiento depresivo. De todo ello resulta un patrón de conducta impredecible, de pensamiento disperso y de acciones y estados de ánimo impetuosos e impul¬sivos, interrumpidos por arrebatos de ira momentánea y ansiedad temerosa.
A21: =I16 | I21: =IF(R21=1,J21," ") -> Narcisista presenta Categoría de Riesgo Se caracteriza por Los sujetos narcisistas destacan por su egocentrismo egotista, por sentir placer simplemente centrándose en sí mismos. Sus sentimientos de superioridad pueden no estar basados en logros reales o maduros; sin embargo, los narcisistas conservan un aire arrogante de seguridad en sí mismos y, sin pensarlo demasiado ni pretenderlo conscientemente, explotan a los demás en beneficio propio. Aunque agradecen y fomentan los elogios y las atenciones que reciben de los demás, no necesitan logros reales o aprobación social para mantener su aire de esnobismo y superioridad pretenciosa. Su confianza extrema hace que no se sientan motivados a implicarse en las interacciones propias de la vida social. | J21: =CONCATENATE(O21," presenta ",Q21, "Se caracteriza por ",S21) -> Narcisista presenta Categoría de Riesgo Se caracteriza por Los sujetos narcisistas destacan por su egocentrismo egotista, por sentir placer simplemente centrándose en sí mismos. Sus sentimientos de superioridad pueden no estar basados en logros reales o maduros; sin embargo, los narcisistas conservan un aire arrogante de seguridad en sí mismos y, sin pensarlo demasiado ni pretenderlo conscientemente, explotan a los demás en beneficio propio. Aunque agradecen y fomentan los elogios y las atenciones que reciben de los demás, no necesitan logros reales o aprobación social para mantener su aire de esnobismo y superioridad pretenciosa. Su confianza extrema hace que no se sientan motivados a implicarse en las interacciones propias de la vida social. | N21: 5 | O21: Narcisista | P21: =CORRECCION!D23 -> 62 | Q21: =IF(P21<=60,"No presenta ",IF(P21>=85,"Trastornos Críticos ",IF(P21>=75,"Patrones menos adaptativos y Trastornos ","Categoría de Riesgo "))) -> Categoría de Riesgo | R21: =IF(P21<=60,"0",1) -> 1 | S21: =IF(R21=1,V21," ") -> Los sujetos narcisistas destacan por su egocentrismo egotista, por sentir placer simplemente centrándose en sí mismos. Sus sentimientos de superioridad pueden no estar basados en logros reales o maduros; sin embargo, los narcisistas conservan un aire arrogante de seguridad en sí mismos y, sin pensarlo demasiado ni pretenderlo conscientemente, explotan a los demás en beneficio propio. Aunque agradecen y fomentan los elogios y las atenciones que reciben de los demás, no necesitan logros reales o aprobación social para mantener su aire de esnobismo y superioridad pretenciosa. Su confianza extrema hace que no se sientan motivados a implicarse en las interacciones propias de la vida social. | V21: Los sujetos narcisistas destacan por su egocentrismo egotista, por sentir placer simplemente centrándose en sí mismos. Sus sentimientos de superioridad pueden no estar basados en logros reales o maduros; sin embargo, los narcisistas conservan un aire arrogante de seguridad en sí mismos y, sin pensarlo demasiado ni pretenderlo conscientemente, explotan a los demás en beneficio propio. Aunque agradecen y fomentan los elogios y las atenciones que reciben de los demás, no necesitan logros reales o aprobación social para mantener su aire de esnobismo y superioridad pretenciosa. Su confianza extrema hace que no se sientan motivados a implicarse en las interacciones propias de la vida social.
A22: =I17 | I22: =IF(R22=1,J22," ") | J22: =CONCATENATE(O22," presenta ",Q22, "Se caracteriza por ",S22) -> Antisocial presenta No presenta Se caracteriza por | N22: 6A | O22: Antisocial | P22: =CORRECCION!D24 -> 20 | Q22: =IF(P22<=60,"No presenta ",IF(P22>=85,"Trastornos Críticos ",IF(P22>=75,"Patrones menos adaptativos y Trastornos ","Categoría de Riesgo "))) -> No presenta | R22: =IF(P22<=60,"0",1) -> 0 | S22: =IF(R22=1,V22," ") | V22: Los sujetos antisociales destacan por su desconfianza hacia los demás, su deseo de autonomía y su anhelo de venganza y recompensa por lo que consideran injusticias del pasado. Para contrarrestar el dolor y los estragos que prevén que les causen otras personas, se comportan de forma engañosa o cometen actos ile¬gales en beneficio propio. Son irresponsables e impulsivos, y justifican estas cualidades porque consideran que los demás son desleales y no se puede confiar en ellos. Su insensibilidad y crueldad son sus únicos medios de evitar el abuso y la vietimización.
A23: =I18 | I23: =IF(R23=1,J23," ") | J23: =CONCATENATE(O23," presenta ",Q23, "Se caracteriza por ",S23) -> Sádico presenta No presenta Se caracteriza por | N23: 6B | O23: Sádico | P23: =CORRECCION!D25 -> 10 | Q23: =IF(P23<=60,"No presenta ",IF(P23>=85,"Trastornos Críticos ",IF(P23>=75,"Patrones menos adaptativos y Trastornos ","Categoría de Riesgo "))) -> No presenta | R23: =IF(P23<=60,"0",1) -> 0 | S23: =IF(R23=1,V23," ") | V23: Los sujetos sádicos, a diferencia de los antisociales, pueden buscar placer y satisfacción personal humi¬llando a otras personas y dejando a un lado sus derechos y sentimientos. Por lo general, son hostiles y sumamente combativos; y parece que las consecuencias destructivas de su conducta conflictiva, ofensiva y brutal les son indiferentes o les satisfacen. Aunque muchos encubren sus tendencias más maliciosas y de búsqueda del poder con acciones o profesiones públicamente aceptadas, sus actos dominantes, hostiles y a menudo persecutorios los delatan.
A24: =I19 -> Histriónico presenta Patrones menos adaptativos y Trastornos Se caracteriza por Los sujetos histriónicos, al igual que los dependientes, recurren a los demás, pero maximizan la atención y los favores que reciben, manipulando los hechos de una forma superficial y entusiasta. Su comportamiento social inteligente y a menudo ingenioso transmite confianza y seguridad en sí mismo; sin embargo, debajo de esta apariencia, subyace el miedo a la autonomía real y la necesidad de recibir señales recurrentes de aceptación y aprobación casi constantemente. | I24: =IF(R24=1,J24," ") | J24: =CONCATENATE(O24," presenta ",Q24, "Se caracteriza por ",S24) -> Compulsivo presenta No presenta Se caracteriza por | N24: 7 | O24: Compulsivo | P24: =CORRECCION!D26 -> 49 | Q24: =IF(P24<=60,"No presenta ",IF(P24>=85,"Trastornos Críticos ",IF(P24>=75,"Patrones menos adaptativos y Trastornos ","Categoría de Riesgo "))) -> No presenta | R24: =IF(P24<=60,"0",1) -> 0 | S24: =IF(R24=1,V24," ") | V24: Los sujetos compulsivos han sido intimidados y coaccionados para que acepten las exigencias y las decisio¬nes que los demás les imponen. Su prudencia, control y perfeccionismo derivan de un conflicto entre la hos¬tilidad hacia los demás y el miedo a la desaprobación social. Esta ambivalencia la resuelven suprimiendo su resentimiento y exigiéndose mucho a sí mismos y exigiéndolo a los demás. Su disciplinada autocontención les permite controlar los sentimientos oposicionistas intensos, aunque ocultos; y de ello resulta una pasividad manifiesta y una aparente sumisión pública.
A25: =I20 -> Tempestuoso presenta Patrones menos adaptativos y Trastornos Se caracteriza por Los sujetos tempestuosos son muy alegres y animados, pero su persistente euforia, entrometimiento y vo¬lubilidad puede resultar irritante para los demás. Aunque son apasionados y entusiastas, se aburren con demasiada facilidad y carecen de los recursos y la regularidad necesarios para llevar a término sus objetivos y planes. Sin control, su conducta puede llegar a ser más extrema, temeraria y errática. Con bastante fre¬cuencia, este patrón tipo maníaco, puede conducir al agotamiento depresivo. De todo ello resulta un patrón de conducta impredecible, de pensamiento disperso y de acciones y estados de ánimo impetuosos e impul¬sivos, interrumpidos por arrebatos de ira momentánea y ansiedad temerosa. | I25: =IF(R25=1,J25," ") | J25: =CONCATENATE(O25," presenta ",Q25, "Se caracteriza por ",S25) -> Negativista presenta No presenta Se caracteriza por | N25: 8A | O25: Negativista | P25: =CORRECCION!D27 -> 60 | Q25: =IF(P25<=60,"No presenta ",IF(P25>=85,"Trastornos Críticos ",IF(P25>=75,"Patrones menos adaptativos y Trastornos ","Categoría de Riesgo "))) -> No presenta | R25: =IF(P25<=60,"0",1) -> 0 | S25: =IF(R25=1,V25," ") | V25: Los sujetos negativistas se debaten entre aceptar las gratificaciones que otros les ofrecen o perseguir sus propios deseos. Dado que vacilan entre la deferencia y el desafío y, a veces, la obediencia y la oposición agresiva, se enfrentan a interminables disputas y decepciones. Esta batalla representa una incapacidad para resolver conflictos similar a la de los sujetos compulsivos. Sin embargo, los conflictos de los negativistas persisten y permanecen cerca de la conciencia. Su conducta se caracteriza por un patrón errático de ira explosiva o resistencia completamente mezclado con periodos de culpa y vergüenza.
A26: =I21 -> Narcisista presenta Categoría de Riesgo Se caracteriza por Los sujetos narcisistas destacan por su egocentrismo egotista, por sentir placer simplemente centrándose en sí mismos. Sus sentimientos de superioridad pueden no estar basados en logros reales o maduros; sin embargo, los narcisistas conservan un aire arrogante de seguridad en sí mismos y, sin pensarlo demasiado ni pretenderlo conscientemente, explotan a los demás en beneficio propio. Aunque agradecen y fomentan los elogios y las atenciones que reciben de los demás, no necesitan logros reales o aprobación social para mantener su aire de esnobismo y superioridad pretenciosa. Su confianza extrema hace que no se sientan motivados a implicarse en las interacciones propias de la vida social. | I26: =IF(R26=1,J26," ") | J26: =CONCATENATE(O26," presenta ",Q26, "Se caracteriza por ",S26) -> Masoquista presenta No presenta Se caracteriza por | N26: 8B | O26: Masoquista | P26: =CORRECCION!D28 -> 38 | Q26: =IF(P26<=60,"No presenta ",IF(P26>=85,"Trastornos Críticos ",IF(P26>=75,"Patrones menos adaptativos y Trastornos ","Categoría de Riesgo "))) -> No presenta | R26: =IF(P26<=60,"0",1) -> 0 | S26: =IF(R26=1,V26," ") | V26: Los sujetos masoquistas se relacionan con los demás de una forma servil y autosacrificada, y les permiten que abusen o se aprovechen de ellos, quizá incluso los alientan a hacerlo. Cuando se muestran sus peores rasgos, muchos sostienen que merecen ser avergonzados y humillados. Para agravar su dolor y angustia, que pueden vivirlos como reconfortantes, los masoquistas rememoran activa y reiteradamente sus desgra¬cias del pasado y, ante situaciones afortunadas, esperan que el resultado sea problemático.
A27: =I22 | I27: En las Patologías Graves Personalidad presenta | J27: =CONCATENATE(O27," presenta ",Q27, "Se caracteriza por ",S27) -> presenta Se caracteriza por | N27: Patologías Graves Personalidad | R27: =IF(P27<=60,"0",1) -> 0
A28: =I23 | I28: =IF(R28=1,J28," ") | J28: =CONCATENATE(O28," presenta ",Q28, "Se caracteriza por ",S28) -> Esquizotípico presenta No presenta Se caracteriza por | N28: S | O28: Esquizotípico | P28: =CORRECCION!D30 -> 12 | Q28: =IF(P28<=60,"No presenta ",IF(P28>=85,"Trastornos Críticos ",IF(P28>=75,"Patrones menos adaptativos y Trastornos ","Categoría de Riesgo "))) -> No presenta | R28: =IF(P28<=60,"0",1) -> 0 | S28: =IF(R28=1,V28," ") | V28: Los sujetos esquizotípicos prefieren estar aislados socialmente y tener mínimos vínculos y obligaciones per¬sonales. Su funcionamiento cognitivo tiende a ser desorganizado, piensan tangencialmente y a menudo parecen estar absortos en sí mismos y pensativos. Se distinguen por sus excentricidades y a menudo son vistos por los demás como personas raras o diferentes. Si su patrón básico es activo, muestran desconfianza ansiosa e hipersensibilidad; si es pasivo, muestran aplanamiento emocional y afecto deficiente.
A29: =I24 | I29: =IF(R29=1,J29," ") | J29: =CONCATENATE(O29," presenta ",Q29, "Se caracteriza por ",S29) -> Límite presenta No presenta Se caracteriza por | N29: C | O29: Límite | P29: =CORRECCION!D31 -> 45 | Q29: =IF(P29<=60,"No presenta ",IF(P29>=85,"Trastornos Críticos ",IF(P29>=75,"Patrones menos adaptativos y Trastornos ","Categoría de Riesgo "))) -> No presenta | R29: =IF(P29<=60,"0",1) -> 0 | S29: =IF(R29=1,V29," ") | V29: Los sujetos límites se caracterizan por su inestabilidad y labilidad afectiva. Experimentan estados de ánimo endógenos intensos, con periodos recurrentes de abatimiento y apatía, a menudo intercalados con periodos de ira, ansiedad o euforia. Muchos de ellos tienen pensamientos recurrentes de autolesiones y suicidio, pare¬cen extremadamente preocupados por conservar el afecto de los demás y tienen dificultades para mantener el sentido de su propia identidad. Asimismo, a menudo muestran una ambivalencia cognitivo-afectiva que se evidencia en sus sentimientos conflictivos de rabia, amor y culpa hacia los demás.
A30: =I25 | I30: =IF(R30=1,J30," ") -> Paranoide presenta Categoría de Riesgo Se caracteriza por Los sujetos paranoides se muestran desconfiados y en alerta hacia los demás y tensos y a la defensiva ante posibles críticas y engaños. Presentan una irritabilidad desabrida y tienden a hacer que los demás se exas¬peren o se enfaden. Asimismo se distinguen por la inmutabilidad de sus sentimientos y la inflexlbilidad de su pensamiento. A menudo expresan miedo a perder la independencia, lo que los lleva a resistirse enérgicamen¬te a las influencias y al control externo. | J30: =CONCATENATE(O30," presenta ",Q30, "Se caracteriza por ",S30) -> Paranoide presenta Categoría de Riesgo Se caracteriza por Los sujetos paranoides se muestran desconfiados y en alerta hacia los demás y tensos y a la defensiva ante posibles críticas y engaños. Presentan una irritabilidad desabrida y tienden a hacer que los demás se exas¬peren o se enfaden. Asimismo se distinguen por la inmutabilidad de sus sentimientos y la inflexlbilidad de su pensamiento. A menudo expresan miedo a perder la independencia, lo que los lleva a resistirse enérgicamen¬te a las influencias y al control externo. | N30: P | O30: Paranoide | P30: =CORRECCION!D32 -> 66 | Q30: =IF(P30<=60,"No presenta ",IF(P30>=85,"Trastornos Críticos ",IF(P30>=75,"Patrones menos adaptativos y Trastornos ","Categoría de Riesgo "))) -> Categoría de Riesgo | R30: =IF(P30<=60,"0",1) -> 1 | S30: =IF(R30=1,V30," ") -> Los sujetos paranoides se muestran desconfiados y en alerta hacia los demás y tensos y a la defensiva ante posibles críticas y engaños. Presentan una irritabilidad desabrida y tienden a hacer que los demás se exas¬peren o se enfaden. Asimismo se distinguen por la inmutabilidad de sus sentimientos y la inflexlbilidad de su pensamiento. A menudo expresan miedo a perder la independencia, lo que los lleva a resistirse enérgicamen¬te a las influencias y al control externo. | V30: Los sujetos paranoides se muestran desconfiados y en alerta hacia los demás y tensos y a la defensiva ante posibles críticas y engaños. Presentan una irritabilidad desabrida y tienden a hacer que los demás se exas¬peren o se enfaden. Asimismo se distinguen por la inmutabilidad de sus sentimientos y la inflexlbilidad de su pensamiento. A menudo expresan miedo a perder la independencia, lo que los lleva a resistirse enérgicamen¬te a las influencias y al control externo.
A31: =I26 | I31: =IF(R31=1,J31," ") | R31: =IF(P31<=60,"0",1) -> 0
A32: =I27 -> En las Patologías Graves Personalidad presenta | I32: En los Sindromes Clínicos de la Personalidad presenta | N32: Sindromes Clínicos | R32: =IF(P32<=60,"0",1) -> 0
A33: =I28 | I33: =IF(R33=1,J33," ") | J33: =CONCATENATE(O33," presenta ",Q33, "Se caracteriza por ",S33) -> Ansiedad Generalizada presenta No presenta Se caracteriza por | N33: A | O33: Ansiedad Generalizada | P33: =CORRECCION!D35 -> 15 | Q33: =IF(P33<=60,"No presenta ",IF(P33>=85,"Trastornos Críticos ",IF(P33>=75,"Patrones menos adaptativos y Trastornos ","Categoría de Riesgo "))) -> No presenta | R33: =IF(P33<=60,"0",1) -> 0 | S33: =IF(R33=1,V33," ") | V33: Se muestra como un estado generalizado de tensión y la incapacidad de relajarse, con una tendencia a sobresaltarse fácilmente. A menudo se quejan de dolencias físicas: Dolores musculares, sudoración excesiva y nauseas, también es común un estado de preocupación por problemas inminentes, un estado de alerta excesivo hacia lo que los rodea e irritabilidad.
A34: =I29 | I34: =IF(R34=1,J34," ") | J34: =CONCATENATE(O34," presenta ",Q34, "Se caracteriza por ",S34) -> Síntomas Somáticos presenta No presenta Se caracteriza por | N34: H | O34: Síntomas Somáticos | P34: =CORRECCION!D36 -> 0 | Q34: =IF(P34<=60,"No presenta ",IF(P34>=85,"Trastornos Críticos ",IF(P34>=75,"Patrones menos adaptativos y Trastornos ","Categoría de Riesgo "))) -> No presenta | R34: =IF(P34<=60,"0",1) -> 0 | S34: =IF(R34=1,V34," ") | V34: Se muestra como un estado generalizado de tensión y la incapacidad de relajarse, con una tendencia a sobresaltarse fácilmente. A menudo se quejan de dolencias físicas: Dolores musculares, sudoración excesiva y nauseas, también es común un estado de preocupación por problemas inminentes, un estado de alerta excesivo hacia lo que los rodea e irritabilidad.
A35: =I30 -> Paranoide presenta Categoría de Riesgo Se caracteriza por Los sujetos paranoides se muestran desconfiados y en alerta hacia los demás y tensos y a la defensiva ante posibles críticas y engaños. Presentan una irritabilidad desabrida y tienden a hacer que los demás se exas¬peren o se enfaden. Asimismo se distinguen por la inmutabilidad de sus sentimientos y la inflexlbilidad de su pensamiento. A menudo expresan miedo a perder la independencia, lo que los lleva a resistirse enérgicamen¬te a las influencias y al control externo. | I35: =IF(R35=1,J35," ") | J35: =CONCATENATE(O35," presenta ",Q35, "Se caracteriza por ",S35) -> Espectro Bípolar presenta No presenta Se caracteriza por | N35: N | O35: Espectro Bípolar | P35: =CORRECCION!D37 -> 30 | Q35: =IF(P35<=60,"No presenta ",IF(P35>=85,"Trastornos Críticos ",IF(P35>=75,"Patrones menos adaptativos y Trastornos ","Categoría de Riesgo "))) -> No presenta | R35: =IF(P35<=60,"0",1) -> 0 | S35: =IF(R35=1,V35," ") | V35: Sujetos que experimentan síntomas ciclotímicos hasta bipolares, pasan por periodos de euforia superficial, autoestima exagerada, hiperactividad y falta atención con nerviosismo, irritabilidad e impulsividad. Duermen menos y llegan a tener estados psicóticos en casos extremos.
A36: =I31 | I36: =IF(R36=1,J36," ") | J36: =CONCATENATE(O36," presenta ",Q36, "Se caracteriza por ",S36) -> Depresión Persistente presenta No presenta Se caracteriza por | N36: D | O36: Depresión Persistente | P36: =CORRECCION!D38 -> 30 | Q36: =IF(P36<=60,"No presenta ",IF(P36>=85,"Trastornos Críticos ",IF(P36>=75,"Patrones menos adaptativos y Trastornos ","Categoría de Riesgo "))) -> No presenta | R36: =IF(P36<=60,"0",1) -> 0 | S36: =IF(R36=1,V36," ") | V36: Sujetos que han pasado años de su vida con angustia y sentimientos de desánimo o culpa, teniendo falta de iniciativa y apatía para la vida. Expresan sentimientos de inutilidad y hacen comentarios autodenigrantes. En los momentos de Depresión profunda existe llanto, ideación suicida, falta de apetito, fatiga crónica y falta de interés por las actividades placenteras
A37: =I32 -> En los Sindromes Clínicos de la Personalidad presenta | I37: =IF(R37=1,J37," ") | J37: =CONCATENATE(O37," presenta ",Q37, "Se caracteriza por ",S37) -> Consumo de Alcohol presenta No presenta Se caracteriza por | N37: B | O37: Consumo de Alcohol | P37: =CORRECCION!D39 -> 0 | Q37: =IF(P37<=60,"No presenta ",IF(P37>=85,"Trastornos Críticos ",IF(P37>=75,"Patrones menos adaptativos y Trastornos ","Categoría de Riesgo "))) -> No presenta | R37: =IF(P37<=60,"0",1) -> 0 | S37: =IF(R37=1,V37," ") | V37: Se da en personas con un historial de alcoholismo recurrente o reciente que han tratado de superar con poco éxito. Provocando malestar personal y familiar
A38: =I33 | I38: =IF(R38=1,J38," ") | J38: =CONCATENATE(O38," presenta ",Q38, "Se caracteriza por ",S38) -> Consumo de Drogas presenta No presenta Se caracteriza por | N38: T | O38: Consumo de Drogas | P38: =CORRECCION!D40 -> 0 | Q38: =IF(P38<=60,"No presenta ",IF(P38>=85,"Trastornos Críticos ",IF(P38>=75,"Patrones menos adaptativos y Trastornos ","Categoría de Riesgo "))) -> No presenta | R38: =IF(P38<=60,"0",1) -> 0 | S38: =IF(R38=1,V38," ") | V38: Se da en personas con un historial de consumo de drogas recurrente y que les cuesta superar, les suele costar reprimir sus impulsos o mantenerlos dentro de los límites sociales convencionales. No limitan su conducta y les cuesta ver las consecuencias de la misma.
A39: =I34 | I39: =IF(R39=1,J39," ") | J39: =CONCATENATE(O39," presenta ",Q39, "Se caracteriza por ",S39) -> Estrés Postraumático presenta No presenta Se caracteriza por | N39: R | O39: Estrés Postraumático | P39: =CORRECCION!D41 -> 48 | Q39: =IF(P39<=60,"No presenta ",IF(P39>=85,"Trastornos Críticos ",IF(P39>=75,"Patrones menos adaptativos y Trastornos ","Categoría de Riesgo "))) -> No presenta | R39: =IF(P39<=60,"0",1) -> 0 | S39: =IF(R39=1,V39," ") | V39: Sujetos que han vivido y presenciado un acontecimiento relacionado con la muerte o con lesiones graves, ya sea real o amenaza, producto de lo cual han sufrido un miedo intenso. Estos hechos se reviven a menudo en pesadillas o recuerdos que producen malestar. Los pacientes presentan activación ansiosa y sobresaltos exagerados.
A40: =I35 | I40: =IF(R40=1,J40," ") | J40: =CONCATENATE(O40," presenta ",Q40, "Se caracteriza por ",S40) -> Espectro Esquizofrénico presenta No presenta Se caracteriza por | N40: SS | O40: Espectro Esquizofrénico | P40: =CORRECCION!D42 -> 40 | Q40: =IF(P40<=60,"No presenta ",IF(P40>=85,"Trastornos Críticos ",IF(P40>=75,"Patrones menos adaptativos y Trastornos ","Categoría de Riesgo "))) -> No presenta | R40: =IF(P40<=60,"0",1) -> 0 | S40: =IF(R40=1,V40," ") | V40: Son pacientes que muestran conductas incongruentes, desorganizadas y regresivas. A menudo parecen confusos y desorientados; a veces muestran afectos inapropiados, alucinaciones aisladas y delirios no sistemáticos. Poseen pensamientos extraños y en ocasiones mostrarse aislados.
A41: =I36 | I41: =IF(R41=1,J41," ") | J41: =CONCATENATE(O41," presenta ",Q41, "Se caracteriza por ",S41) -> Depresión Mayor presenta No presenta Se caracteriza por | N41: CC | O41: Depresión Mayor | P41: =CORRECCION!D43 -> 51 | Q41: =IF(P41<=60,"No presenta ",IF(P41>=85,"Trastornos Críticos ",IF(P41>=75,"Patrones menos adaptativos y Trastornos ","Categoría de Riesgo "))) -> No presenta | R41: =IF(P41<=60,"0",1) -> 0 | S41: =IF(R41=1,V41," ") | V41: Son pacientes incapaces de funcionar en un entorno normal y poseen una visión pesimista del futuro, ideación suicida y una visión generalizada de resignación. También presentan miedos repetitivos y están meditabundos, con un notable deterioro motor. Entre otras conductas resaltan el insomnio, cansancio y perdida de peso.
A42: =I37 | I42: =IF(R42=1,J42," ") | J42: =CONCATENATE(O42," presenta ",Q42, "Se caracteriza por ",S42) -> Delirante presenta No presenta Se caracteriza por | N42: PP | O42: Delirante | P42: =CORRECCION!D44 -> 60 | Q42: =IF(P42<=60,"No presenta ",IF(P42>=85,"Trastornos Críticos ",IF(P42>=75,"Patrones menos adaptativos y Trastornos ","Categoría de Riesgo "))) -> No presenta | R42: =IF(P42<=60,"0",1) -> 0 | S42: =IF(R42=1,V42," ") | V42: Son pacientes en un estado paranoide agudo y periódicamente pueden demostrar agresividad y delirios irracionales con temática persecutoria o de grandeza. Tienen alteración de pensamiento e ideas de traición, estado de animo hostil y se sienten maltratados
A43: =I38
A44: =I39
A45: =I40
A46: =I41
A47: =I42

Sheet Sheet1

Sheet RESULTADOS
B2: X | C2: Y | D2: Z
A3: 0 | C3: 0 | D3: 0
A4: 1 | C4: 5 | D4: 12
A5: 2 | C5: 10 | D5: 23
A6: 3 | C6: 15 | D6: 35
A7: 4 | C7: 20 | D7: 37
A8: 5 | C8: 25 | D8: 40
A9: 6 | C9: 30 | D9: 42
A10: 7 | B10: 0 | C10: 35 | D10: 44
A11: 8 | B11: 2 | C11: 39 | D11: 47
A12: 9 | B12: 3 | C12: 43 | D12: 49
A13: 10 | B13: 5 | C13: 47 | D13: 51
A14: 11 | B14: 6 | C14: 51 | D14: 54
A15: 12 | B15: 8 | C15: 55 | D15: 56
A16: 13 | B16: 10 | C16: 59 | D16: 59
A17: 14 | B17: 11 | C17: 63 | D17: 61
A18: 15 | B18: 13 | C18: 67 | D18: 63
A19: 16 | B19: 14 | C19: 71 | D19: 66
A20: 17 | B20: 16 | C20: 75 | D20: 68
A21: 18 | B21: 18 | C21: 78 | D21: 70
... A27: 24 | B27: 27 | C27: 100 | D27: 82
A28: 25 | B28: 29 | D28: 83
A29: 26 | B29: 30 | D29: 85
A30: 27 | B30: 32 | D30: 89
A31: 28 | B31: 33 | D31: 93
A32: 29 | B32: 35 | D32: 96
A33: 30 | B33: 36 | D33: 100
A34: 31 | B34: 38
A35: 32 | B35: 39
A36: 33 | B36: 40
A37: 34 | B37: 41
A38: 35 | B38: 43
A39: 36 | B39: 44
A40: 37 | B40: 45
A41: 38 | B41: 47
A42: 39 | B42: 48
A43: 40 | B43: 49
A44: 41 | B44: 50
A45: 42 | B45: 52
... A117: 114 | B117: 100

Sheet PUNT-DIRECTA
A2: TASA BASE
B3: Punt. Directa | D3: 1 | E3: 2A | F3: 2B | G3: 3 | H3: 4A | I3: 4B | J3: 5 | K3: 6A | L3: 6B | M3: 7 | N3: 8A | O3: 8B | P3: S | Q3: C | R3: P | S3: A | T3: H | U3: N | V3: D | W3: B | X3: T | Y3: R | Z3: SS | AA3: CC | AB3: PP
B4: 0 | D4: 0 | E4: 0 | F4: 0 | G4: 0 | H4: 0 | I4: 0 | J4: 0 | K4: 0 | L4: 0 | M4: 0 | N4: 0 | O4: 0 | P4: 0 | Q4: 0 | R4: 0 | S4: 0 | T4: 0 | U4: 0 | V4: 0 | W4: 0 | X4: 0 | Y4: 0 | Z4: 0 | AA4: 0 | AB4: 0
B5: 1 | D5: 7 | E5: 6 | F5: 5 | G5: 6 | H5: 7 | I5: 6 | J5: 12 | K5: 20 | L5: 10 | M5: 4 | N5: 7 | O5: 8 | P5: 6 | Q5: 8 | R5: 9 | S5: 8 | T5: 10 | U5: 10 | V5: 5 | W5: 60 | X5: 60 | Y5: 12 | Z5: 7 | AA5: 9 | AB5: 30
B6: 2 | D6: 13 | E6: 12 | F6: 10 | G6: 12 | H6: 13 | I6: 12 | J6: 24 | K6: 40 | L6: 20 | M6: 8 | N6: 13 | O6: 15 | P6: 12 | Q6: 15 | R6: 17 | S6: 15 | T6: 20 | U6: 20 | V6: 10 | W6: 68 | X6: 62 | Y6: 24 | Z6: 13 | AA6: 17 | AB6: 60
B7: 3 | D7: 20 | E7: 18 | F7: 15 | G7: 18 | H7: 20 | I7: 18 | J7: 36 | K7: 60 | L7: 30 | M7: 11 | N7: 20 | O7: 23 | P7: 18 | Q7: 23 | R7: 26 | S7: 23 | T7: 30 | U7: 30 | V7: 15 | W7: 75 | X7: 64 | Y7: 36 | Z7: 20 | AA7: 26 | AB7: 62
B8: 4 | D8: 27 | E8: 24 | F8: 20 | G8: 24 | H8: 27 | I8: 24 | J8: 48 | K8: 62 | L8: 40 | M8: 15 | N8: 27 | O8: 30 | P8: 24 | Q8: 30 | R8: 34 | S8: 30 | T8: 40 | U8: 40 | V8: 20 | W8: 85 | X8: 66 | Y8: 48 | Z8: 27 | AA8: 34 | AB8: 64
B9: 5 | D9: 33 | E9: 30 | F9: 25 | G9: 30 | H9: 33 | I9: 30 | J9: 60 | K9: 64 | L9: 50 | M9: 19 | N9: 33 | O9: 38 | P9: 30 | Q9: 38 | R9: 43 | S9: 38 | T9: 50 | U9: 50 | V9: 25 | W9: 88 | X9: 68 | Y9: 60 | Z9: 33 | AA9: 43 | AB9: 66
B10: 6 | D10: 40 | E10: 36 | F10: 30 | G10: 36 | H10: 40 | I10: 36 | J10: 62 | K10: 66 | L10: 60 | M10: 23 | N10: 40 | O10: 45 | P10: 36 | Q10: 45 | R10: 51 | S10: 45 | T10: 60 | U10: 60 | V10: 30 | W10: 92 | X10: 69 | Y10: 62 | Z10: 40 | AA10: 51 | AB10: 69
B11: 7 | D11: 47 | E11: 42 | F11: 35 | G11: 42 | H11: 47 | I11: 42 | J11: 64 | K11: 69 | L11: 62 | M11: 26 | N11: 47 | O11: 53 | P11: 42 | Q11: 53 | R11: 60 | S11: 53 | T11: 64 | U11: 63 | V11: 35 | W11: 95 | X11: 71 | Y11: 64 | Z11: 47 | AA11: 60 | AB11: 71
B12: 8 | D12: 53 | E12: 48 | F12: 40 | G12: 48 | H12: 53 | I12: 48 | J12: 66 | K12: 71 | L12: 63 | M12: 30 | N12: 53 | O12: 60 | P12: 48 | Q12: 60 | R12: 63 | S12: 60 | T12: 68 | U12: 66 | V12: 40 | W12: 98 | X12: 73 | Y12: 66 | Z12: 53 | AA12: 62 | AB12: 73
B13: 9 | D13: 60 | E13: 54 | F13: 45 | G13: 54 | H13: 60 | I13: 54 | J13: 69 | K13: 73 | L13: 65 | M13: 34 | N13: 60 | O13: 62 | P13: 54 | Q13: 62 | R13: 66 | S13: 75 | T13: 71 | U13: 69 | V13: 45 | W13: 102 | X13: 75 | Y13: 68 | Z13: 60 | AA13: 64 | AB13: 75
B14: 10 | D14: 63 | E14: 60 | F14: 50 | G14: 60 | H14: 63 | I14: 60 | J14: 71 | K14: 75 | L14: 67 | M14: 38 | N14: 62 | O14: 63 | P14: 60 | Q14: 64 | R14: 69 | S14: 78 | T14: 75 | U14: 72 | V14: 50 | W14: 105 | X14: 78 | Y14: 69 | Z14: 62 | AA14: 66 | AB14: 78
B15: 11 | D15: 65 | E15: 75 | F15: 55 | G15: 68 | H15: 65 | I15: 61 | J15: 73 | K15: 78 | L15: 68 | M15: 41 | N15: 64 | O15: 65 | P15: 62 | Q15: 66 | R15: 72 | S15: 80 | T15: 80 | U15: 75 | V15: 55 | W15: 108 | X15: 82 | Y15: 71 | Z15: 64 | AA15: 69 | AB15: 80
... B17: 13 | D17: 70 | E17: 78 | F17: 65 | G17: 78 | H17: 70 | I17: 64 | J17: 78 | K17: 85 | L17: 72 | M17: 49 | N17: 69 | O17: 68 | P17: 65 | Q17: 69 | R17: 78 | S17: 85 | T17: 95 | U17: 85 | V17: 63 | W17: 115 | X17: 90 | Y17: 75 | Z17: 68 | AA17: 73 | AB17: 85
B18: 14 | D18: 73 | E18: 80 | F18: 70 | G18: 80 | H18: 73 | I18: 65 | J18: 80 | K18: 89 | L18: 73 | M18: 53 | N18: 71 | O18: 70 | P18: 66 | Q18: 71 | R18: 82 | S18: 90 | T18: 105 | U18: 90 | V18: 66 | W18: - | X18: 95 | Y18: 80 | Z18: 69 | AA18: 75 | AB18: 90
B19: 15 | D19: 75 | E19: 82 | F19: 75 | G19: 83 | H19: 75 | I19: 67 | J19: 83 | K19: 93 | L19: 75 | M19: 56 | N19: 73 | O19: 72 | P19: 68 | Q19: 73 | R19: 85 | S19: 95 | T19: 115 | U19: 95 | V19: 69 | W19: - | X19: 100 | Y19: 85 | Z19: 71 | AA19: 78 | AB19: 95
B20: 16 | D20: 78 | E20: 83 | F20: 76 | G20: 85 | H20: 78 | I20: 68 | J20: 85 | K20: 96 | L20: 78 | M20: 60 | N20: 75 | O20: 73 | P20: 69 | Q20: 75 | R20: 88 | S20: 100 | T20: - | U20: 100 | V20: 72 | W20: - | X20: 105 | Y20: 93 | Z20: 73 | AA20: 82 | AB20: 100
B21: 17 | D21: 82 | E21: 85 | F21: 78 | G21: 89 | H21: 80 | I21: 70 | J21: 88 | K21: 100 | L21: 82 | M21: 64 | N21: 78 | O21: 75 | P21: 71 | Q21: 78 | R21: 92 | S21: 105 | T21: - | U21: 105 | V21: 75 | W21: - | X21: 110 | Y21: 100 | Z21: 75 | AA21: 85 | AB21: 105
B22: 18 | D22: 85 | E22: 89 | F22: 79 | G22: 94 | H22: 83 | I22: 71 | J22: 91 | K22: 104 | L22: 85 | M22: 68 | N22: 80 | O22: 78 | P22: 72 | Q22: 81 | R22: 95 | S22: 110 | T22: - | U22: 110 | V22: 78 | W22: - | X22: 115 | Y22: 108 | Z22: 80 | AA22: 89 | AB22: 110
B23: 19 | D23: 91 | E23: 94 | F23: 80 | G23: 98 | H23: 85 | I23: 72 | J23: 94 | K23: 108 | L23: 93 | M23: 71 | N23: 83 | O23: 80 | P23: 74 | Q23: 85 | R23: 98 | S23: 115 | T23: - | U23: 115 | V23: 80 | W23: - | X23: - | Y23: 115 | Z23: 85 | AA23: 94 | AB23: 115
B24: 20 | D24: 97 | E24: 98 | F24: 81 | G24: 102 | H24: 88 | I24: 74 | J24: 97 | K24: 111 | L24: 100 | M24: 75 | N24: 85 | O24: 83 | P24: 75 | Q24: 89 | R24: 102 | S24: - | T24: - | U24: - | V24: 83 | W24: - | X24: - | Y24: - | Z24: 89 | AA24: 98 | AB24: -
B25: 21 | D25: 103 | E25: 102 | F25: 83 | G25: 106 | H25: 91 | I25: 75 | J25: 100 | K25: 115 | L25: 108 | M25: 80 | N25: 90 | O25: 85 | P25: 78 | Q25: 93 | R25: 105 | S25: - | T25: - | U25: - | V25: 85 | W25: - | X25: - | Y25: - | Z25: 93 | AA25: 102 | AB25: -
B26: 22 | D26: 109 | E26: 106 | F26: 84 | G26: 111 | H26: 94 | I26: 80 | J26: 103 | K26: - | L26: 115 | M26: 85 | N26: 95 | O26: 93 | P26: 82 | Q26: 96 | R26: 108 | S26: - | T26: - | U26: - | V26: 90 | W26: - | X26: - | Y26: - | Z26: 96 | AA26: 106 | AB26: -
B27: 23 | D27: 115 | E27: 111 | F27: 85 | G27: 115 | H27: 97 | I27: 85 | J27: 106 | K27: - | L27: - | M27: 100 | N27: 100 | O27: 100 | P27: 85 | Q27: 100 | R27: 112 | S27: - | T27: - | U27: - | V27: 95 | W27: - | X27: - | Y27: - | Z27: 100 | AA27: 111 | AB27: -
B28: 24 | D28: - | E28: 115 | F28: 91 | G28: - | H28: 100 | I28: 93 | J28: 109 | K28: - | L28: - | M28: - | N28: 105 | O28: 108 | P28: 90 | Q28: 104 | R28: 115 | S28: - | T28: - | U28: - | V28: 100 | W28: - | X28: - | Y28: - | Z28: 104 | AA28: 115 | AB28: -
B29: 25 | D29: - | E29: - | F29: 97 | G29: - | H29: - | I29: 100 | J29: 112 | K29: - | L29: - | M29: - | N29: 110 | O29: 115 | P29: 95 | Q29: 108 | R29: - | S29: - | T29: - | U29: - | V29: 105 | W29: - | X29: - | Y29: - | Z29: 108 | AA29: - | AB29: -
B30: 26 | D30: - | E30: - | F30: 103 | G30: - | H30: - | I30: - | J30: 115 | K30: - | L30: - | M30: - | N30: 115 | O30: - | P30: 100 | Q30: 111 | R30: - | S30: - | T30: - | U30: - | V30: 110 | W30: - | X30: - | Y30: - | Z30: 111 | AA30: - | AB30: -
B31: 27 | D31: - | E31: - | F31: 109 | G31: - | H31: - | I31: - | J31: - | K31: - | L31: - | M31: - | N31: - | O31: - | P31: 105 | Q31: 115 | R31: - | S31: - | T31: - | U31: - | V31: 115 | W31: - | X31: - | Y31: - | Z31: 115 | AA31: - | AB31: -
B32: 28 | D32: - | E32: - | F32: 115 | G32: - | H32: - | I32: - | J32: - | K32: - | L32: - | M32: - | N32: - | O32: - | P32: 110 | Q32: - | R32: - | S32: - | T32: - | U32: - | V32: - | W32: - | X32: - | Y32: - | Z32: - | AA32: - | AB32: -
B33: 29 | D33: - | E33: - | F33: - | G33: - | H33: - | I33: - | J33: - | K33: - | L33: - | M33: - | N33: - | O33: - | P33: 115 | Q33: - | R33: - | S33: - | T33: - | U33: - | V33: - | W33: - | X33: - | Y33: - | Z33: - | AA33: - | AB33: -

Sheet PERCENTIL
A2: TASA BASE AJUSTADA
A3: Percentil | D3: 1 | F3: 2A | H3: 2B | J3: 3 | L3: 4A | N3: 4B | P3: 5 | R3: 6A | T3: 6B | V3: 7 | X3: 8A | Z3: 8B | AB3: S | AD3: C | AF3: P | AH3: A | AJ3: H | AL3: N | AN3: D | AP3: B | AR3: T | AT3: R | AV3: SS | AX3: CC | AZ3: PP
B4: 1 | V4: 0 | W4: 19 | BD4: 1
B5: 2 | D5: 0 | E5: 6 | F5: 0 | G5: 5 | J5: 0 | K5: 5 | V5: 20 | W5: 24 | BD5: 2
B6: 3 | D6: - | F6: - | J6: 6 | K6: 9 | V6: 25 | W6: 28 | X6: 0 | Y6: 0 | AL6: 0 | AM6: 0 | AN6: 0 | AO6: 0 | AV6: 0 | AW6: 0 | BD6: 3
B7: 4 | D7: - | F7: - | J7: 10 | K7: 11 | L7: 0 | M7: 5 | N7: 0 | O7: 4 | V7: 29 | W7: 29 | X7: 1 | Y7: 1 | AB7: 0 | AC7: 0 | AD7: 0 | AE7: 0 | AL7: 1 | AM7: 9 | AN7: 1 | AO7: 4 | AV7: 1 | AW7: 1 | BD7: 4
B8: 5 | D8: 7 | E8: 12 | F8: 6 | G8: 7 | H8: 0 | I8: 0 | J8: - | L8: - | N8: 5 | O8: 5 | V8: 30 | W8: 31 | X8: 2 | Y8: 2 | Z8: 0 | AA8: 2 | AB8: 1 | AC8: 1 | AD8: - | AH8: 0 | AI8: 1 | AL8: - | AN8: - | AV8: 2 | AW8: 6 | BD8: 5
B9: 6 | D9: - | F9: 8 | G9: 11 | H9: 1 | I9: 2 | J9: - | L9: - | N9: - | T9: 0 | U9: 0 | V9: 32 | W9: 33 | X9: 3 | Y9: 6 | Z9: 3 | AA9: 7 | AB9: 2 | AC9: 5 | AD9: 1 | AE9: 4 | AH9: 2 | AI9: 7 | AL9: - | AN9: - | AV9: - | BD9: 6
B10: 7 | D10: - | F10: - | H10: 3 | I10: 4 | J10: 12 | K10: 14 | L10: 6 | M10: 6 | N10: 6 | O10: 6 | T10: 1 | U10: 1 | V10: - | X10: - | Z10: - | AB10: - | AD10: 5 | AE10: 7 | AF10: 0 | AG10: 0 | AH10: - | AL10: - | AN10: - | AV10: - | BD10: 7
B11: 8 | D11: - | F11: - | H11: 5 | I11: 6 | J11: 15 | K11: 17 | L11: - | N11: 7 | O11: 10 | T11: 2 | U11: 9 | V11: - | X11: - | Z11: - | AB11: - | AD11: - | AF11: - | AH11: - | AL11: 10 | AM11: 10 | AN11: 5 | AO11: 6 | AT11: 0 | AU11: 0 | AV11: 7 | AW11: 8 | BD11: 8
B12: 9 | D12: 13 | E12: 19 | F12: - | H12: 7 | I12: 9 | J12: 18 | K12: 18 | L12: 7 | M12: 8 | N12: 11 | O12: 11 | T12: - | V12: 34 | W12: 36 | X12: 7 | Y12: 8 | Z12: - | AB12: 6 | AC12: 7 | AD12: - | AF12: 1 | AG12: 1 | AH12: - | AL12: 11 | AM12: 19 | AN12: 7 | AO12: 9 | AT12: 1 | AU12: 1 | AV12: 9 | AW12: 12 | BD12: 9
B13: 10 | D13: - | F13: 12 | G13: 17 | H13: - | J13: 19 | K13: 23 | L13: 9 | M13: 11 | N13: - | P13: 0 | Q13: 0 | T13: - | V13: 37 | W13: 37 | X13: 9 | Y13: 12 | Z13: 8 | AA13: 10 | AB13: 8 | AC13: 11 | AD13: - | AF13: 2 | AG13: 8 | AH13: 8 | AI13: 14 | AL13: - | AN13: - | AT13: 2 | AU13: 11 | AV13: - | BD13: 10
B14: 11 | D14: - | F14: - | H14: - | J14: - | L14: 12 | M14: 12 | N14: - | P14: 1 | Q14: 2 | R14: 0 | S14: 0 | T14: - | V14: - | X14: - | Z14: 11 | AA14: 14 | AB14: - | AD14: - | AF14: - | AH14: - | AJ14: 0 | AK14: 0 | AL14: - | AN14: - | AT14: - | AV14: - | BD14: 11
B15: 12 | D15: - | F15: - | H15: - | J15: - | L15: - | N15: - | P15: 3 | Q15: 11 | R15: 1 | S15: 15 | T15: - | V15: 38 | W15: 39 | X15: - | Z15: - | AB15: - | AD15: 8 | AE15: 8 | AF15: - | AH15: - | AJ15: 1 | AK15: 9 | AL15: - | AN15: - | AT15: - | AV15: - | BD15: 12
B16: 13 | D16: 20 | E16: 20 | F16: - | H16: 10 | I16: 11 | J16: - | L16: - | N16: 12 | O16: 13 | P16: - | R16: 16 | S16: 18 | T16: 10 | U16: 18 | V16: 40 | W16: 40 | X16: 13 | Y16: 13 | Z16: - | AB16: - | AD16: 9 | AE16: 14 | AF16: - | AH16: - | AJ16: - | AL16: - | AN16: 10 | AO16: 10 | AT16: - | AV16: 13 | AW16: 13 | AX16: 0 | AY16: 0 | BD16: 13
B17: 14 | D17: 21 | E17: 26 | F17: - | H17: 12 | I17: 14 | J17: 24 | K17: 24 | L17: 13 | M17: 18 | N17: 14 | O17: 16 | P17: - | R17: 19 | S17: 19 | T17: 19 | U17: 19 | V17: - | X17: 14 | Y17: 19 | Z17: - | AB17: 12 | AC17: 13 | AD17: - | AF17: - | AH17: 15 | AI17: 15 | AJ17: - | AL17: - | AN17: 11 | AO17: 14 | AT17: - | AV17: 14 | AW17: 19 | AX17: 1 | AY17: 1 | BD17: 14
B18: 15 | D18: - | F18: - | H18: - | J18: 25 | K18: 29 | L18: 19 | M18: 19 | N18: 17 | O18: 17 | P18: 12 | Q18: 22 | R18: - | T18: - | V18: - | X18: - | Z18: 15 | AA18: 15 | AB18: 14 | AC18: 17 | AD18: - | AF18: 9 | AG18: 16 | AH18: 16 | AI18: 22 | AJ18: - | AL18: 20 | AM18: 28 | AN18: - | AT18: - | AV18: - | AX18: 2 | AY18: 7 | BD18: 15
B19: 16 | D19: - | F19: 18 | G19: 23 | H19: - | J19: - | L19: - | N19: - | P19: 23 | Q19: 23 | R19: - | T19: - | V19: 41 | W19: 41 | X19: - | Z19: 16 | AA19: 22 | AB19: - | AD19: - | AF19: - | AH19: - | AJ19: - | AL19: 29 | AM19: 29 | AN19: - | AT19: - | AV19: - | AX19: 8 | AY19: 8 | BD19: 16
B20: 17 | D20: - | F20: - | H20: 15 | I20: 17 | J20: - | L20: - | N20: - | P20: - | R20: - | T20: - | V20: 42 | W20: 43 | X20: - | Z20: - | AB20: - | AD20: - | AF20: - | AH20: - | AJ20: 10 | AK20: 10 | AL20: - | AN20: - | AT20: - | AV20: - | AX20: - | AZ20: 0 | BA20: 0 | BD20: 17
B21: 18 | D21: 27 | E21: 27 | F21: - | H21: 18 | I21: 19 | J21: - | L21: 20 | M21: 25 | N21: - | P21: - | R21: - | T21: - | V21: 44 | W21: 44 | X21: - | Z21: - | AB21: 18 | AC21: 23 | AD21: 15 | AE21: 15 | AF21: - | AH21: - | AJ21: - | AL21: - | AN21: 15 | AO21: 19 | AT21: 12 | AU21: 12 | AV21: - | AX21: - | AZ21: - | BD21: 18
B22: 19 | D22: 28 | E22: 31 | F22: - | H22: - | J22: - | L22: 26 | M22: 26 | N22: 18 | O22: 22 | P22: - | R22: - | T22: - | V22: - | X22: 20 | Y22: 26 | Z22: - | AB22: - | AD22: 16 | AE22: 22 | AF22: - | AH22: 23 | AI22: 23 | AJ22: 11 | AK22: 18 | AL22: - | AN22: - | AT22: 13 | AU22: 23 | AV22: - | AX22: - | AZ22: 1 | BA22: 1 | BD22: 19
B23: 20 | D23: 32 | E23: 32 | F23: 24 | G23: 27 | H23: 20 | I23: 23 | J23: 30 | K23: 32 | L23: - | N23: - | P23: - | R23: - | T23: - | V23: 45 | W23: 47 | X23: - | Z23: - | AB23: - | AD23: - | AF23: - | AH23: 24 | AI23: 29 | AJ23: 19 | AK23: 19 | AL23: - | AN23: - | AT23: - | AV23: 20 | AW23: 26 | AX23: - | AZ23: 2 | BA23: 28 | BD23: 20
B24: 21 | D24: - | F24: 28 | G24: 29 | H24: 24 | I24: 24 | J24: 33 | K24: 35 | L24: - | N24: 23 | O24: 23 | P24: - | R24: - | T24: - | V24: 48 | W24: 48 | X24: - | Z24: - | AB24: - | AD24: - | AF24: - | AH24: - | AJ24: - | AL24: - | AN24: 20 | AO24: 24 | AT24: - | AV24: - | AX24: 9 | AY24: 10 | AZ24: 29 | BA24: 29 | BD24: 21
B25: 22 | D25: - | F25: - | H25: - | J25: - | L25: - | N25: - | P25: - | R25: - | T25: 20 | U25: 21 | V25: - | X25: - | Z25: 23 | AA25: 26 | AB25: - | AD25: - | AF25: - | AH25: - | AJ25: - | AL25: 30 | AM25: 30 | AN25: - | AT25: - | AV25: - | AX25: 11 | AY25: 16 | AZ25: - | BD25: 22
B26: 23 | D26: - | F26: - | H26: 25 | I26: 28 | J26: - | L26: - | N26: - | P26: - | R26: - | T26: 22 | U26: 28 | V26: - | X26: - | Z26: 27 | AA26: 29 | AB26: - | AD26: - | AF26: - | AH26: - | AJ26: - | AL26: 31 | AM26: 38 | AN26: - | AT26: - | AV26: 27 | AW26: 27 | AX26: - | AZ26: - | BD26: 23
B27: 24 | D27: - | F27: - | H27: 29 | I27: 29 | J27: - | L27: 27 | M27: 28 | N27: 24 | O27: 28 | P27: - | R27: - | T27: 29 | U27: 29 | V27: - | X27: 27 | Y27: 32 | Z27: - | AB27: 24 | AC27: 29 | AD27: 23 | AE27: 29 | AF27: 17 | AG27: 25 | AH27: - | AJ27: - | AL27: 39 | AM27: 39 | AN27: 25 | AO27: 28 | AR27: 0 | AS27: 0 | AT27: - | AV27: 28 | AW27: 32 | AX27: - | AZ27: - | BD27: 24
B28: 25 | D28: - | F28: 30 | G28: 34 | H28: - | J28: 36 | K28: 40 | L28: 29 | M28: 31 | N28: 29 | O28: 29 | P28: 24 | Q28: 25 | R28: 20 | S28: 21 | T28: - | V28: - | X28: - | Z28: - | AB28: - | AD28: - | AF28: - | AH28: - | AJ28: - | AL28: - | AN28: 29 | AO28: 29 | AR28: 1 | AS28: 4 | AT28: - | AV28: - | AX28: - | AZ28: - | BD28: 25
B29: 26 | D29: 33 | E29: 38 | F29: 35 | G29: 35 | H29: - | J29: 41 | K29: 41 | L29: 32 | M29: 32 | N29: - | P29: 26 | Q29: 27 | R29: 22 | S29: 38 | T29: - | V29: 49 | W29: 50 | X29: - | Z29: - | AB29: - | AD29: - | AF29: - | AH29: 30 | AI29: 37 | AJ29: - | AL29: - | AN29: - | AR29: 5 | AS29: 58 | AT29: - | AV29: - | AX29: - | AZ29: - | BD29: 26
B30: 27 | D30: 39 | E30: 39 | F30: - | H30: - | J30: - | L30: - | N30: - | P30: 28 | Q30: 34 | R30: 39 | S30: 39 | T30: - | V30: 51 | W30: 51 | X30: - | Z30: - | AB30: - | AD30: - | AF30: - | AH30: - | AJ30: - | AL30: - | AN30: - | AR30: - | AT30: - | AV30: 33 | AW30: 33 | AX30: - | AZ30: - | BD30: 27
B31: 28 | D31: - | F31: - | H31: 30 | I31: 31 | J31: - | L31: - | N31: 30 | O31: 30 | P31: 35 | Q31: 35 | R31: - | T31: - | V31: 52 | W31: 52 | X31: - | Z31: 30 | AA31: 31 | AB31: - | AD31: - | AF31: - | AH31: - | AJ31: 20 | AK31: 20 | AL31: - | AN31: 30 | AO31: 34 | AR31: - | AT31: 24 | AU31: 34 | AV31: 34 | AW31: 39 | AX31: 17 | AY31: 25 | AZ31: - | BD31: 28
B32: 29 | D32: - | F32: - | H32: 32 | I32: 34 | J32: - | L32: - | N32: 31 | O32: 34 | P32: - | R32: - | T32: - | V32: - | X32: 33 | Y32: 39 | Z32: 32 | AA32: 37 | AB32: 30 | AC32: 34 | AD32: 30 | AF32: 26 | AG32: 33 | AH32: - | AJ32: 21 | AK32: 28 | AL32: - | AN32: - | AR32: - | AT32: 35 | AU32: 35 | AV32: - | AX32: - | AZ32: - | BD32: 29
B33: 30 | D33: - | F33: - | H33: - | J33: - | L33: 33 | M33: 38 | N33: 35 | O33: 35 | P33: - | R33: - | T33: 30 | U33: 39 | V33: - | X33: - | Z33: - | AB33: 35 | AC33: 35 | AD33: 31 | AE33: 37 | AF33: - | AH33: - | AJ33: 29 | AK33: 29 | AL33: 40 | AM33: 48 | AN33: - | AR33: 59 | AS33: 59 | AT33: - | AV33: - | AX33: - | AZ33: - | BD33: 30
B34: 31 | D34: 40 | E34: 45 | F34: 36 | G34: 39 | H34: - | J34: - | L34: 39 | M34: 39 | N34: - | P34: - | R34: - | T34: - | V34: 53 | W34: 54 | X34: - | Z34: - | AB34: - | AD34: - | AF34: - | AH34: 38 | AI34: 43 | AJ34: - | AL34: - | AN34: 35 | AO34: 39 | AR34: - | AT34: - | AV34: - | AX34: - | AZ34: - | BD34: 31
B35: 32 | D35: 46 | E35: 46 | F35: 40 | G35: 41 | H35: 35 | I35: 38 | J35: 42 | K35: 42 | L35: - | N35: - | P35: - | R35: - | T35: - | V35: - | X35: - | Z35: - | AB35: - | AD35: - | AF35: - | AH35: 44 | AI35: 44 | AJ35: - | AL35: 49 | AM35: 49 | AN35: - | AR35: - | AT35: - | AV35: - | AX35: 26 | AY35: 32 | AZ35: - | BD35: 32
B36: 33 | D36: - | F36: - | H36: 39 | I36: 39 | J36: 43 | K36: 47 | L36: - | N36: 36 | O36: 38 | P36: 36 | Q36: 36 | R36: - | T36: - | V36: 55 | W36: 55 | X36: 40 | Y36: 46 | Z36: 38 | AA36: 44 | AB36: - | AD36: - | AF36: - | AH36: - | AJ36: - | AL36: - | AN36: - | AR36: - | AT36: - | AV36: 40 | AW36: 45 | AX36: 33 | AY36: 33 | AZ36: - | BD36: 33
B37: 34 | D37: - | F37: - | H37: - | J37: - | L37: - | N37: 39 | O37: 41 | P37: 37 | Q37: 46 | R37: - | T37: - | V37: - | X37: - | Z37: - | AB37: 36 | AC37: 41 | AD37: - | AF37: - | AH37: - | AJ37: - | AL37: - | AN37: - | AP37: 0 | AQ37: 0 | AR37: - | AT37: - | AV37: 46 | AW37: 46 | AX37: - | AZ37: - | BD37: 34
B38: 35 | D38: - | F38: - | H38: - | J38: - | L38: - | N38: - | P38: 47 | Q38: 47 | R38: - | T38: - | V38: - | X38: - | Z38: - | AB38: - | AD38: 38 | AE38: 43 | AF38: - | AH38: - | AJ38: 30 | AK38: 38 | AL38: - | AN38: 40 | AO38: 44 | AP38: - | AR38: - | AT38: - | AV38: - | AX38: - | AZ38: - | BD38: 35
B39: 36 | D39: 47 | E39: 51 | F39: - | H39: - | J39: - | L39: 40 | M39: 45 | N39: 42 | O39: 43 | P39: - | R39: - | T39: - | V39: - | X39: - | Z39: - | AB39: - | AD39: 44 | AE39: 44 | AF39: 34 | AG39: 42 | AH39: - | AJ39: 39 | AK39: 39 | AL39: - | AN39: - | AP39: 1 | AQ39: 1 | AR39: - | AT39: 36 | AU39: 46 | AV39: - | AX39: - | AZ39: - | BD39: 36
B40: 37 | D40: 52 | E40: 52 | F40: 42 | G40: 46 | H40: 40 | I40: 44 | J40: - | L40: 46 | M40: 46 | N40: 44 | O40: 46 | P40: - | R40: - | T40: 40 | U40: 40 | V40: - | X40: - | Z40: - | AB40: - | AD40: - | AF40: - | AH40: 45 | AI40: 51 | AJ40: - | AL40: - | AN40: - | AP40: 2 | AQ40: 57 | AR40: - | AT40: 47 | AU40: 47 | AV40: - | AX40: - | AZ40: - | BD40: 37
B41: 38 | D41: - | F41: 47 | G41: 47 | H41: - | J41: 48 | K41: 49 | L41: - | N41: 47 | O41: 47 | P41: - | R41: - | T41: 41 | U41: 48 | V41: - | X41: 47 | Y41: 51 | Z41: - | AB41: - | AD41: - | AF41: - | AH41: 52 | AI41: 52 | AJ41: - | AL41: 50 | AM41: 50 | AN41: - | AP41: 58 | AQ41: 58 | AR41: - | AT41: - | AV41: - | AX41: 34 | AY41: 42 | AZ41: 30 | BA41: 31 | BD41: 38
B42: 39 | D42: - | F42: - | H42: - | J42: 50 | K42: 53 | L42: - | N42: - | P42: - | R42: 40 | S42: 42 | T42: 49 | U42: 49 | V42: - | X42: 52 | Y42: 52 | Z42: 45 | AA42: 51 | AB42: 42 | AC42: 47 | AD42: - | AF42: - | AH42: - | AJ42: - | AL42: 51 | AM42: 58 | AN42: - | AP42: - | AR42: - | AT42: - | AV42: 47 | AW42: 51 | AX42: - | AZ42: 32 | BA42: 58 | BD42: 39
B43: 40 | D43: - | F43: - | H43: 45 | I43: 49 | J43: - | L43: 47 | M43: 47 | N43: - | P43: - | R43: 43 | S43: 58 | T43: - | V43: 56 | W43: 57 | X43: - | Z43: 52 | AA43: 52 | AB43: - | AD43: 45 | AE43: 52 | AF43: - | AH43: - | AJ43: - | AL43: - | AN43: 45 | AO43: 48 | AP43: - | AR43: - | AT43: - | AV43: 52 | AW43: 52 | AX43: - | AZ43: 59 | BA43: 59 | BD43: 40
B44: 41 | D44: - | F44: 48 | G44: 48 | H44: - | J44: - | L44: 48 | M44: 51 | N44: 48 | O44: 51 | P44: - | R44: - | T44: - | V44: 58 | W44: 58 | X44: - | Z44: - | AB44: - | AD44: - | AF44: - | AH44: - | AJ44: - | AL44: 59 | AM44: 59 | AN44: 49 | AO44: 49 | AP44: - | AR44: - | AT44: - | AV44: - | AX44: - | AZ44: - | BD44: 41
B45: 42 | D45: 53 | E45: 58 | F45: 49 | G45: 52 | H45: - | J45: - | L45: 52 | M45: 52 | N45: 52 | O45: 52 | P45: - | R45: 59 | S45: 59 | T45: - | V45: - | X45: - | Z45: - | AB45: - | AD45: - | AF45: 43 | AG45: 50 | AH45: - | AJ45: 40 | AK45: 49 | AL45: - | AN45: - | AP45: - | AR45: - | AT45: 48 | AU45: 48 | AV45: - | AX45: 43 | AY45: 49 | AZ45: - | BD45: 42
B46: 43 | D46: 59 | E46: 59 | F46: 53 | G46: 53 | H46: - | J46: - | L46: - | N46: 53 | O46: 53 | P46: 48 | Q46: 58 | R46: - | T46: - | V46: 59 | W46: 59 | X46: 53 | Y46: 59 | Z46: - | AB46: 48 | AC46: 53 | AD46: - | AF46: - | AH46: - | AJ46: - | AL46: - | AN46: - | AP46: - | AR46: - | AT46: 49 | AU46: 58 | AV46: - | AX46: 50 | AY46: 50 | AZ46: - | BD46: 43
B47: 44 | D47: - | F47: - | H47: 50 | I47: 54 | J47: 54 | K47: 54 | L47: - | N47: - | P47: 59 | Q47: 59 | R47: - | T47: 50 | U47: 58 | V47: - | X47: - | Z47: - | AB47: - | AD47: - | AF47: - | AH47: - | AJ47: - | AL47: - | AN47: - | AP47: - | AR47: - | AT47: 59 | AU47: 59 | AV47: - | AX47: - | AZ47: - | BD47: 44
B48: 45 | D48: - | F48: - | H48: - | J48: 55 | K48: 58 | L48: 53 | M48: 54 | N48: - | P48: - | R48: - | T48: - | V48: - | X48: - | Z48: 53 | AA48: 58 | AB48: - | AD48: 53 | AE48: 59 | AF48: - | AH48: 53 | AI48: 58 | AJ48: - | AL48: - | AN48: 50 | AO48: 54 | AP48: 59 | AQ48: 59 | AR48: - | AT48: - | AV48: 53 | AW48: 59 | AX48: 51 | AZ48: - | BD48: 45
B49: 46 | D49: - | F49: 54 | G49: 58 | H49: - | J49: 59 | K49: 59 | L49: 55 | M49: 58 | N49: 54 | O49: 57 | P49: - | R49: - | T49: 59 | U49: 59 | V49: - | X49: - | Z49: 59 | AA49: 59 | AB49: - | AD49: - | AF49: - | AH49: 59 | AI49: 59 | AJ49: 50 | AK49: 58 | AL49: - | AN49: - | AP49: - | AR49: - | AT49: - | AV49: - | AX49: 52 | AY49: 59 | AZ49: - | BD49: 46
B50: 47 | D50: - | F50: 59 | G50: 59 | H50: 55 | I50: 59 | J50: - | L50: 59 | M50: 59 | N50: 58 | O50: 58 | P50: - | R50: - | T50: - | V50: 60 | W50: 62 | X50: - | Z50: - | AB50: 54 | AC50: 58 | AD50: - | AF50: 51 | AG50: 58 | AH50: - | AJ50: 59 | AK50: 59 | AL50: - | AN50: - | AP50: - | AR50: - | AT50: - | AV50: - | AX50: - | AZ50: - | BD50: 47
B51: 48 | D51: 60 | E51: 61 | F51: - | H51: - | J51: - | L51: - | N51: 59 | O51: 59 | P51: - | R51: - | T51: - | V51: - | X51: 60 | Y51: 61 | Z51: - | AB51: 59 | AC51: 59 | AD51: - | AF51: 59 | AG51: 59 | AH51: - | AJ51: - | AL51: 60 | AM51: 61 | AN51: 55 | AO51: 59 | AP51: - | AR51: 60 | AS51: 60 | AT51: - | AV51: - | AX51: - | AZ51: - | BD51: 48
B52: 49 | D52: 62 | E52: 62 | F52: - | H52: - | J52: - | L52: - | N52: - | P52: 60 | Q52: 60 | R52: - | T52: - | V52: 63 | W52: 63 | X52: - | Z52: - | AB52: - | AD52: 60 | AE52: 61 | AF52: - | AH52: - | AJ52: - | AL52: 62 | AM52: 62 | AN52: - | AP52: - | AR52: - | AT52: - | AV52: 60 | AW52: 60 | AX52: 60 | AY52: 61 | AZ52: - | BD52: 49
B53: 50 | D53: - | F53: 60 | G53: 70 | H53: - | J53: - | L53: 60 | M53: 61 | N53: - | P53: - | R53: 60 | S53: 60 | T53: - | V53: - | X53: - | Z53: - | AB53: - | AD53: - | AF53: - | AH53: - | AJ53: 60 | AK53: 62 | AL53: - | AN53: 60 | AO53: 62 | AP53: - | AR53: - | AT53: 60 | AU53: 60 | AV53: 61 | AW53: 61 | AX53: - | AZ53: - | BD53: 50
B54: 51 | D54: - | F54: 71 | G54: 73 | H54: 60 | I54: 64 | J54: 60 | K54: 66 | L54: - | N54: 60 | O54: 60 | P54: 61 | Q54: 61 | R54: - | T54: - | V54: - | X54: - | Z54: 60 | AA54: 61 | AB54: 60 | AC54: 60 | AD54: - | AF54: - | AH54: 60 | AI54: 61 | AJ54: - | AL54: - | AN54: - | AP54: - | AR54: - | AT54: 61 | AU54: 61 | AV54: - | AX54: - | AZ54: 60 | BA54: 60 | BD54: 51
B55: 52 | D55: - | F55: 74 | G55: 74 | H55: - | J55: - | L55: 62 | M55: 62 | N55: - | P55: - | R55: 61 | S55: 61 | T55: 60 | U55: 60 | V55: - | X55: 62 | Y55: 62 | Z55: - | AB55: 61 | AC55: 61 | AD55: - | AF55: 60 | AG55: 61 | AH55: 62 | AI55: 64 | AJ55: 63 | AK55: 63 | AL55: - | AN55: - | AP55: - | AR55: 61 | AS55: 61 | AT55: - | AV55: - | AX55: 62 | AY55: 62 | AZ55: - | BD55: 52
B56: 53 | D56: - | F56: - | H56: - | J56: 67 | K56: 67 | L56: - | N56: - | P56: - | R56: - | T56: 61 | U56: 61 | V56: - | X56: 63 | Y56: 63 | Z56: - | AB56: - | AD56: 62 | AE56: 63 | AF56: 62 | AG56: 62 | AH56: - | AJ56: - | AL56: - | AN56: 63 | AO56: 65 | AP56: - | AR56: - | AT56: - | AV56: - | AX56: 63 | AY56: 63 | AZ56: 61 | BA56: 61 | BD56: 53
B57: 54 | D57: 63 | E57: 63 | F57: - | H57: 65 | I57: 68 | J57: - | L57: - | N57: - | P57: - | R57: - | T57: - | V57: - | X57: - | Z57: - | AB57: - | AD57: - | AF57: - | AH57: - | AJ57: - | AL57: - | AN57: - | AP57: - | AR57: - | AT57: - | AV57: - | AX57: - | AZ57: - | BD57: 54
B58: 55 | D58: - | F58: 75 | G58: 75 | H58: 69 | I58: 69 | J58: - | L58: - | N58: 61 | O58: 62 | P58: - | R58: - | T58: - | V58: - | X58: - | Z58: - | AB58: - | AD58: - | AF58: - | AH58: - | AJ58: - | AL58: 63 | AM58: 64 | AN58: 66 | AO58: 67 | AP58: - | AR58: - | AT58: 62 | AU58: 62 | AV58: - | AX58: 64 | AY58: 65 | AZ58: - | BD58: 55
B59: 56 | D59: 64 | E59: 64 | F59: 76 | G59: 76 | H59: - | J59: - | L59: 63 | M59: 63 | N59: - | P59: 62 | Q59: 62 | R59: - | T59: - | V59: - | X59: - | Z59: 62 | AA59: 62 | AB59: 62 | AC59: 62 | AD59: - | AF59: - | AH59: - | AJ59: 64 | AK59: 66 | AL59: - | AN59: 68 | AO59: 68 | AP59: - | AR59: - | AT59: 63 | AU59: 63 | AV59: 62 | AW59: 62 | AX59: - | AZ59: - | BD59: 56
B60: 57 | D60: - | F60: - | H60: 70 | I60: 74 | J60: 68 | K60: 72 | L60: - | N60: - | P60: 63 | Q60: 63 | R60: - | T60: - | V60: - | X60: 64 | Y60: 64 | Z60: - | AB60: - | AD60: 64 | AE60: 64 | AF60: 63 | AG60: 64 | AH60: 75 | AI60: 76 | AJ60: 67 | AK60: 67 | AL60: 65 | AM60: 65 | AN60: - | AP60: - | AR60: - | AT60: - | AV60: 63 | AW60: 63 | AX60: 66 | AY60: 68 | AZ60: - | BD60: 57
B61: 58 | D61: - | F61: - | H61: - | J61: 73 | K61: 73 | L61: 64 | M61: 64 | N61: - | P61: - | R61: - | T61: - | V61: - | X61: 65 | Y61: 65 | Z61: - | AB61: - | AD61: 65 | AE61: 65 | AF61: 65 | AG61: 65 | AH61: - | AJ61: - | AL61: - | AN61: - | AP61: - | AR61: - | AT61: - | AV61: - | AX61: - | AZ61: - | BD61: 58
B62: 59 | D62: - | F62: - | H62: - | J62: 74 | K62: 74 | L62: - | N62: - | P62: - | R62: - | T62: - | V62: 64 | W62: 65 | X62: - | Z62: - | AB62: 63 | AC62: 63 | AD62: - | AF62: - | AH62: 77 | AI62: 77 | AJ62: - | AL62: - | AN62: 69 | AO62: 70 | AP62: - | AR62: - | AT62: - | AV62: - | AX62: 69 | AY62: 69 | AZ62: - | BD62: 59
B63: 60 | D63: - | F63: - | H63: - | J63: - | L63: - | N63: 63 | O63: 63 | P63: - | R63: 62 | S63: 62 | T63: 62 | U63: 62 | V63: 66 | W63: 66 | X63: - | Z63: 63 | AA63: 63 | AB63: 64 | AC63: 64 | AD63: - | AF63: - | AH63: - | AJ63: - | AL63: - | AN63: 71 | AO63: 71 | AP63: - | AR63: - | AT63: 64 | AU63: 64 | AV63: - | AX63: 70 | AY63: 70 | AZ63: - | BD63: 60
B64: 61 | D64: 65 | E64: 66 | F64: 77 | G64: 77 | H64: 75 | I64: 75 | J64: - | L64: - | N64: - | P64: 64 | Q64: 64 | R64: - | T64: - | V64: - | X64: - | Z64: 64 | AA64: 64 | AB64: - | AD64: 66 | AE64: 66 | AF64: - | AH64: - | AJ64: - | AL64: - | AN64: - | AP64: - | AR64: 62 | AS64: 62 | AT64: 65 | AU64: 65 | AV64: 64 | AW64: 64 | AX64: - | AZ64: 62 | BA64: 62 | BD64: 61
B65: 62 | D65: 67 | E65: 67 | F65: - | H65: - | J65: - | L65: 65 | M65: 66 | N65: - | P65: - | R65: 63 | S65: 63 | T65: - | V65: 67 | W65: 67 | X65: - | Z65: - | AB65: - | AD65: 67 | AE65: 67 | AF65: 66 | AG65: 66 | AH65: - | AJ65: - | AL65: - | AN65: 72 | AO65: 74 | AP65: - | AR65: - | AT65: - | AV65: 65 | AW65: 65 | AX65: 71 | AY65: 71 | AZ65: - | BD65: 62
B66: 63 | D66: - | F66: - | H66: 76 | I66: 76 | J66: 75 | K66: 76 | L66: 67 | M66: 67 | N66: 64 | O66: 64 | P66: 65 | Q66: 65 | R66: - | T66: - | V66: - | X66: 66 | Y66: 67 | Z66: - | AB66: - | AD66: - | AF66: 67 | AG66: 67 | AH66: - | AJ66: 68 | AK66: 68 | AL66: - | AN66: - | AP66: - | AR66: - | AT66: - | AV66: - | AX66: 72 | AY66: 72 | AZ66: 63 | BA66: 63 | BD66: 63
B67: 64 | D67: - | F67: 78 | G67: 78 | H67: - | J67: 77 | K67: 77 | L67: - | N67: - | P67: - | R67: - | T67: 63 | U67: 63 | V67: - | X67: 68 | Y67: 68 | Z67: - | AB67: 65 | AC67: 65 | AD67: - | AF67: 68 | AG67: 68 | AH67: 78 | AI67: 78 | AJ67: 69 | AK67: 69 | AL67: - | AN67: - | AP67: - | AR67: 63 | AS67: 63 | AT67: - | AV67: - | AX67: - | AZ67: - | BD67: 64
B68: 65 | D68: 68 | E68: 68 | F68: 79 | G68: 79 | H68: 77 | I68: 77 | J68: - | L68: - | N68: - | P68: - | R68: - | T68: - | V68: - | X68: - | Z68: 65 | AA68: 65 | AB68: - | AD68: 68 | AE68: 68 | AF68: - | AH68: - | AJ68: 70 | AK68: 70 | AL68: 66 | AM68: 67 | AN68: 75 | AO68: 76 | AP68: 60 | AQ68: 64 | AR68: - | AT68: 66 | AU68: 66 | AV68: - | AX68: - | AZ68: - | BD68: 65
B69: 66 | D69: - | F69: - | H69: - | J69: - | L69: - | N69: 65 | O69: 65 | P69: - | R69: - | T69: 64 | U69: 64 | V69: - | X69: - | Z69: 66 | AA69: 66 | AB69: - | AD69: - | AF69: - | AH69: - | AJ69: - | AL69: - | AN69: 77 | AO69: 77 | AP69: 65 | AQ69: 65 | AR69: - | AT69: 67 | AU69: 67 | AV69: 66 | AW69: 66 | AX69: 73 | AY69: 73 | AZ69: - | BD69: 66
B70: 67 | D70: 69 | E70: 69 | F70: - | H70: - | J70: - | L70: 68 | M70: 68 | N70: 66 | O70: 66 | P70: - | R70: 64 | S70: 64 | T70: - | V70: - | X70: - | Z70: - | AB70: 66 | AC70: 67 | AD70: - | AF70: - | AH70: 79 | AI70: 79 | AJ70: - | AL70: 68 | AM70: 68 | AN70: - | AP70: 66 | AQ70: 66 | AR70: - | AT70: - | AV70: 67 | AW70: 67 | AX70: 74 | AY70: 74 | AZ70: - | BD70: 67
B71: 68 | D71: - | F71: 80 | G71: 80 | H71: 78 | I71: 78 | J71: 78 | K71: 78 | L71: 69 | M71: 69 | N71: - | P71: 66 | Q71: 67 | R71: - | T71: - | V71: 68 | W71: 69 | X71: 69 | Y71: 69 | Z71: - | AB71: - | AD71: - | AF71: 69 | AG71: 70 | AH71: - | AJ71: - | AL71: - | AN71: - | AP71: - | AR71: - | AT71: - | AV71: - | AX71: - | AZ71: - | BD71: 68
B72: 69 | D72: - | F72: - | H72: - | J72: - | L72: - | N72: - | P72: - | R72: 65 | S72: 65 | T72: - | V72: - | X72: 70 | Y72: 70 | Z72: - | AB72: - | AD72: 69 | AE72: 69 | AF72: - | AH72: - | AJ72: - | AL72: - | AN72: 78 | AO72: 78 | AP72: - | AR72: - | AT72: - | AV72: - | AX72: 75 | AY72: 75 | AZ72: 64 | BA72: 64 | BD72: 69
B73: 70 | D73: - | F73: 81 | G73: 81 | H73: - | J73: 79 | K73: 79 | L73: - | N73: - | P73: 68 | Q73: 68 | R73: - | T73: 65 | U73: 65 | V73: 70 | W73: 70 | X73: - | Z73: 67 | AA73: 67 | AB73: - | AD73: 70 | AE73: 70 | AF73: 71 | AG73: 71 | AH73: - | AJ73: 71 | AK73: 71 | AL73: - | AN73: 79 | AO73: 79 | AP73: - | AR73: - | AT73: 68 | AU73: 68 | AV73: - | AX73: 76 | AY73: 77 | AZ73: 65 | BA73: 65 | BD73: 70
B74: 71 | D74: 70 | E74: 71 | F74: - | H74: - | J74: - | L74: - | N74: 67 | O74: 67 | P74: - | R74: - | T74: 66 | U74: 66 | V74: - | X74: - | Z74: - | AB74: 68 | AC74: 68 | AD74: - | AF74: - | AH74: 80 | AI74: 81 | AJ74: 72 | AK74: 72 | AL74: - | AN74: - | AP74: - | AR74: - | AT74: - | AV74: - | AX74: - | AZ74: - | BD74: 71
B75: 72 | D75: - | F75: - | H75: 79 | I75: 79 | J75: - | L75: 70 | M75: 71 | N75: - | P75: - | R75: - | T75: - | V75: - | X75: 71 | Y75: 71 | Z75: - | AB75: - | AD75: 71 | AE75: 71 | AF75: - | AH75: - | AJ75: 73 | AK75: 73 | AL75: 69 | AM75: 70 | AN75: 80 | AO75: 80 | AP75: 67 | AQ75: 67 | AR75: 64 | AS75: 64 | AT75: - | AV75: 68 | AW75: 68 | AX75: 78 | AY75: 79 | AZ75: - | BD75: 72
B76: 73 | D76: 72 | E76: 72 | F76: - | H76: - | J76: 80 | K76: 81 | L76: 72 | M76: 72 | N76: 68 | O76: 68 | P76: - | R76: - | T76: - | V76: - | X76: 72 | Y76: 72 | Z76: 68 | AA76: 68 | AB76: - | AD76: - | AF76: 72 | AG76: 73 | AH76: - | AJ76: - | AL76: - | AN76: 81 | AO76: 81 | AP76: - | AR76: - | AT76: 69 | AU76: 69 | AV76: - | AX76: 80 | AY76: 80 | AZ76: - | BD76: 73
B77: 74 | D77: - | F77: 82 | G77: 82 | H77: 80 | I77: 80 | J77: - | L77: - | N77: 69 | O77: 69 | P77: 69 | Q77: 69 | R77: 66 | S77: 67 | T77: - | V77: - | X77: - | Z77: - | AB77: 69 | AC77: 69 | AD77: 72 | AE77: 72 | AF77: - | AH77: 82 | AI77: 82 | AJ77: 74 | AK77: 74 | AL77: 71 | AM77: 71 | AN77: 82 | AO77: 82 | AP77: - | AR77: 65 | AS77: 65 | AT77: - | AV77: - | AX77: 81 | AY77: 81 | AZ77: - | BD77: 74
B78: 75 | D78: - | F78: - | H78: - | J78: 82 | K78: 82 | L78: - | N78: - | P78: 70 | Q78: 70 | R78: - | T78: - | V78: - | X78: 73 | Y78: 73 | Z78: 69 | AA78: 69 | AB78: 70 | AC78: 70 | AD78: - | AF78: 74 | AG78: 74 | AH78: - | AJ78: - | AL78: - | AN78: - | AP78: - | AR78: - | AT78: 70 | AU78: 70 | AV78: 69 | AW78: 69 | AX78: - | AZ78: - | BD78: 75
B79: 76 | D79: 73 | E79: 73 | F79: 83 | G79: 83 | H79: - | J79: - | L79: - | N79: - | P79: - | R79: 68 | S79: 68 | T79: - | V79: - | X79: - | Z79: - | AB79: - | AD79: 73 | AE79: 73 | AF79: - | AH79: - | AJ79: - | AL79: - | AN79: 83 | AO79: 83 | AP79: - | AR79: 66 | AS79: 66 | AT79: - | AV79: 70 | AW79: 70 | AX79: 82 | AY79: 83 | AZ79: 66 | BA79: 67 | BD79: 76
B80: 77 | D80: - | F80: - | H80: 81 | I80: 81 | J80: - | L80: - | N80: 70 | O80: 70 | P80: - | R80: - | T80: 67 | U80: 67 | V80: - | X80: 74 | Y80: 74 | Z80: 70 | AA80: 70 | AB80: - | AD80: 74 | AE80: 74 | AF80: - | AH80: - | AJ80: - | AL80: - | AN80: 84 | AO80: 84 | AP80: - | AR80: 67 | AS80: 67 | AT80: 71 | AU80: 71 | AV80: - | AX80: - | AZ80: - | BD80: 77
B81: 78 | D81: 74 | E81: 74 | F81: 84 | G81: 84 | H81: 82 | I81: 82 | J81: 83 | K81: 83 | L81: 73 | M81: 73 | N81: - | P81: 71 | Q81: 71 | R81: - | T81: - | V81: - | X81: - | Z81: 71 | AA81: 71 | AB81: - | AD81: - | AF81: 75 | AG81: 76 | AH81: 83 | AI81: 83 | AJ81: 75 | AK81: 78 | AL81: - | AN81: 85 | AO81: 86 | AP81: - | AR81: - | AT81: - | AV81: 71 | AW81: 71 | AX81: 84 | AY81: 84 | AZ81: - | BD81: 78
B82: 79 | D82: - | F82: - | H82: - | J82: - | L82: 74 | M82: 74 | N82: - | P82: - | R82: - | T82: - | V82: 71 | W82: 73 | X82: 75 | Y82: 75 | Z82: - | AB82: 71 | AC82: 71 | AD82: 75 | AE82: 76 | AF82: - | AH82: - | AJ82: - | AL82: 72 | AM82: 73 | AN82: 87 | AO82: 88 | AP82: - | AR82: 68 | AS82: 68 | AT82: 72 | AU82: 72 | AV82: - | AX82: - | AZ82: 68 | BA82: 68 | BD82: 79
B83: 80 | D83: 75 | E83: 76 | F83: 85 | G83: 87 | H83: - | J83: 84 | K83: 84 | L83: - | N83: 71 | O83: 71 | P83: 72 | Q83: 72 | R83: - | T83: - | V83: - | X83: 76 | Y83: 76 | Z83: - | AB83: - | AD83: 77 | AE83: 77 | AF83: 77 | AG83: 77 | AH83: 84 | AI83: 84 | AJ83: 79 | AK83: 79 | AL83: - | AN83: - | AP83: 68 | AQ83: 71 | AR83: - | AT83: - | AV83: - | AX83: 85 | AY83: 87 | AZ83: - | BD83: 80
B84: 81 | D84: 77 | E84: 77 | F84: 88 | G84: 88 | H84: 83 | I84: 83 | J84: - | L84: - | N84: - | P84: - | R84: 69 | S84: 70 | T84: 68 | U84: 68 | V84: 74 | W84: 74 | X84: - | Z84: 72 | AA84: 72 | AB84: 72 | AC84: 72 | AD84: 78 | AE84: 79 | AF84: - | AH84: - | AJ84: - | AL84: 74 | AM84: 74 | AN84: 89 | AO84: 89 | AP84: 72 | AQ84: 73 | AR84: 69 | AS84: 70 | AT84: 73 | AU84: 73 | AV84: 72 | AW84: 72 | AX84: 88 | AY84: 88 | AZ84: 69 | BA84: 69 | BD84: 81
B85: 82 | D85: - | F85: - | H85: - | J85: - | L85: - | N85: - | P85: 73 | Q85: 73 | R85: - | T85: 69 | U85: 69 | V85: - | X85: 77 | Y85: 77 | Z85: - | AB85: 73 | AC85: 73 | AD85: 80 | AE85: 80 | AF85: 78 | AG85: 80 | AH85: 85 | AI85: 88 | AJ85: - | AL85: - | AN85: - | AP85: - | AR85: 71 | AS85: 71 | AT85: - | AV85: - | AX85: - | AZ85: 70 | BA85: 70 | BD85: 82
B86: 83 | D86: - | F86: - | H86: - | J86: - | L86: 75 | M86: 76 | N86: 72 | O86: 73 | P86: - | R86: - | T86: - | V86: - | X86: 78 | Y86: 78 | Z86: 73 | AA86: 73 | AB86: - | AD86: 81 | AE86: 81 | AF86: - | AH86: - | AJ86: - | AL86: - | AN86: 90 | AO86: 91 | AP86: 74 | AQ86: 74 | AR86: 72 | AS86: 72 | AT86: 74 | AU86: 74 | AV86: 73 | AW86: 73 | AX86: 89 | AY86: 92 | AZ86: - | BD86: 83
B87: 84 | D87: 78 | E87: 79 | F87: 89 | G87: 92 | H87: - | J87: 85 | K87: 87 | L87: 77 | M87: 77 | N87: - | P87: 74 | Q87: 74 | R87: 71 | S87: 71 | T87: - | V87: - | X87: - | Z87: 74 | AA87: 74 | AB87: - | AD87: 82 | AE87: 83 | AF87: 81 | AG87: 81 | AH87: 89 | AI87: 89 | AJ87: 80 | AK87: 82 | AL87: 75 | AM87: 78 | AN87: 92 | AO87: 93 | AP87: - | AR87: - | AT87: - | AV87: - | AX87: 93 | AY87: 93 | AZ87: - | BD87: 84
B88: 85 | D88: 80 | E88: 80 | F88: - | H88: 84 | I88: 84 | J88: - | L88: - | N88: - | P88: - | R88: 72 | S88: 72 | T88: 70 | U88: 70 | V88: 75 | W88: 78 | X88: 79 | Y88: 79 | Z88: 75 | AA88: 75 | AB88: 74 | AC88: 74 | AD88: - | AF88: - | AH88: - | AJ88: 83 | AK88: 83 | AL88: - | AN88: - | AP88: - | AR88: 73 | AS88: 74 | AT88: 75 | AU88: 76 | AV88: 74 | AW88: 74 | AX88: - | AZ88: 71 | BA88: 71 | BD88: 85
B89: 86 | D89: - | F89: 93 | G89: 93 | H89: 85 | I89: 86 | J89: 88 | K89: 88 | L89: - | N89: - | P89: - | R89: - | T89: - | V89: - | X89: 80 | Y89: 80 | Z89: 76 | AA89: 76 | AB89: 75 | AC89: 76 | AD89: 84 | AE89: 84 | AF89: 82 | AG89: 83 | AH89: 90 | AI89: 92 | AJ89: - | AL89: 79 | AM89: 79 | AN89: 94 | AP89: 75 | AQ89: 80 | AR89: - | AT89: 77 | AU89: 78 | AV89: 75 | AW89: 78 | AX89: 94 | AY89: 96 | AZ89: - | BD89: 86
B90: 87 | D90: 81 | E90: 81 | F90: - | H90: 87 | I90: 89 | J90: - | L90: 78 | M90: 78 | N90: 74 | O90: 74 | P90: 75 | Q90: 76 | R90: 73 | S90: 73 | T90: 71 | U90: 71 | V90: 79 | W90: 79 | X90: 81 | Y90: 81 | Z90: 77 | AA90: 77 | AB90: 77 | AC90: 77 | AD90: 85 | AE90: 86 | AF90: - | AH90: 93 | AI90: 93 | AJ90: - | AL90: - | AN90: 95 | AO90: 98 | AP90: 81 | AQ90: 82 | AR90: 75 | AS90: 77 | AT90: - | AV90: - | AX90: - | AZ90: 72 | BA90: 72 | BD90: 87
B91: 88 | D91: 82 | E91: 83 | F91: 94 | G91: 96 | H91: 90 | I91: 90 | J91: 89 | K91: 92 | L91: 79 | M91: 79 | N91: - | P91: 77 | Q91: 77 | R91: - | T91: - | V91: - | X91: 82 | Y91: 82 | Z91: 78 | AA91: 78 | AB91: 78 | AC91: 79 | AD91: 87 | AE91: 87 | AF91: 84 | AG91: 84 | AH91: 94 | AI91: 94 | AJ91: 84 | AK91: 84 | AL91: - | AN91: - | AP91: 83 | AQ91: 84 | AR91: 78 | AS91: 80 | AT91: 79 | AU91: 79 | AV91: 79 | AW91: 79 | AX91: 97 | AY91: 97 | AZ91: 73 | BA91: 73 | BD91: 88
B92: 89 | D92: 84 | E92: 84 | F92: - | H92: 91 | I92: 95 | J92: - | L92: - | N92: - | P92: - | R92: 74 | S92: 74 | T92: - | V92: - | X92: 83 | Y92: 83 | Z92: - | AB92: 80 | AC92: 80 | AD92: 88 | AE92: 88 | AF92: 85 | AG92: 86 | AH92: - | AJ92: - | AL92: 80 | AM92: 81 | AN92: 99 | AO92: 99 | AP92: - | AR92: 81 | AS92: 83 | AT92: 80 | AU92: 83 | AV92: 80 | AW92: 83 | AX92: 98 | AY92: 99 | AZ92: - | BD92: 89
B93: 90 | D93: - | F93: 97 | G93: 97 | H93: - | J93: 93 | K93: 93 | L93: - | N93: 75 | O93: 78 | P93: 78 | Q93: 78 | R93: 75 | S93: 76 | T93: 72 | U93: 72 | V93: - | X93: - | Z93: 79 | AA93: 79 | AB93: 81 | AC93: 81 | AD93: 89 | AE93: 91 | AF93: - | AH93: - | AJ93: 85 | AK93: 92 | AL93: 82 | AM93: 83 | AN93: 100 | AO93: 103 | AP93: - | AR93: 84 | AS93: 84 | AT93: - | AV93: 84 | AW93: 84 | AX93: 100 | AY93: 100 | AZ93: 74 | BA93: 74 | BD93: 90
B94: 91 | D94: 85 | E94: 89 | F94: 98 | G94: 99 | H94: 96 | I94: 98 | J94: - | L94: 80 | M94: 82 | N94: 79 | O94: 79 | P94: 79 | Q94: 79 | R94: 77 | S94: 77 | T94: - | V94: - | X94: 84 | Y94: 84 | Z94: 80 | AA94: 81 | AB94: 82 | AC94: 83 | AD94: - | AF94: 87 | AG94: 87 | AH94: 95 | AI94: 98 | AJ94: 93 | AK94: 93 | AL94: 84 | AM94: 84 | AN94: - | AP94: 85 | AQ94: 86 | AR94: - | AT94: 84 | AU94: 84 | AV94: 85 | AW94: 87 | AX94: 101 | AY94: 101 | AZ94: 75 | BA94: 76 | BD94: 91
B95: 92 | D95: - | F95: 100 | G95: 101 | H95: 99 | I95: 101 | J95: - | L95: - | N95: - | P95: 80 | Q95: 81 | R95: 78 | S95: 80 | T95: 73 | U95: 73 | V95: - | X95: 85 | Y95: 85 | Z95: - | AB95: 84 | AC95: 86 | AD95: 92 | AE95: 93 | AF95: 88 | AG95: 89 | AH95: - | AJ95: - | AL95: - | AN95: 104 | AO95: 104 | AP95: 87 | AQ95: 87 | AR95: 85 | AS95: 89 | AT95: 85 | AU95: 89 | AV95: - | AX95: - | AZ95: 77 | BA95: 78 | BD95: 92
B96: 93 | D96: 90 | E96: 90 | F96: - | H96: - | J96: 94 | K96: 96 | L96: 83 | M96: 83 | N96: 80 | O96: 80 | P96: 82 | Q96: 82 | R96: 81 | S96: 81 | T96: 74 | U96: 75 | V96: - | X96: 86 | Y96: 88 | Z96: 82 | AA96: 83 | AB96: 87 | AC96: 88 | AD96: 94 | AE96: 94 | AF96: 90 | AG96: 90 | AH96: - | AJ96: 94 | AK96: 94 | AL96: 85 | AM96: 87 | AN96: 105 | AO96: 107 | AP96: 88 | AQ96: 90 | AR96: 90 | AS96: 93 | AT96: 90 | AU96: 91 | AV96: 88 | AW96: 89 | AX96: 102 | AY96: 102 | AZ96: 79 | BA96: 79 | BD96: 93
B97: 94 | D97: 91 | E97: 95 | F97: 102 | G97: 104 | H97: 102 | I97: 104 | J97: 97 | K97: 97 | L97: 84 | M97: 84 | N97: 81 | O97: 84 | P97: 83 | Q97: 83 | R97: 82 | S97: 83 | T97: 76 | U97: 76 | V97: - | X97: - | Z97: 84 | AA97: 87 | AB97: - | AD97: 95 | AE97: 97 | AF97: 91 | AG97: 92 | AH97: 99 | AI97: 101 | AJ97: 95 | AK97: 101 | AL97: 88 | AM97: 88 | AN97: 108 | AO97: 108 | AP97: 91 | AQ97: 91 | AR97: 94 | AS97: 94 | AT97: - | AV97: 90 | AW97: 91 | AX97: 103 | AY97: 104 | AZ97: 80 | BA97: 81 | BD97: 94
B98: 95 | D98: 96 | E98: 96 | F98: 105 | G98: 105 | H98: 105 | I98: 107 | J98: - | L98: 85 | M98: 87 | N98: - | P98: 84 | Q98: 86 | R98: 84 | S98: 84 | T98: 77 | U98: 77 | V98: - | X98: 89 | Y98: 89 | Z98: 88 | AA98: 91 | AB98: 89 | AC98: 91 | AD98: 98 | AE98: 98 | AF98: 93 | AG98: 94 | AH98: 102 | AI98: 108 | AJ98: 102 | AK98: 108 | AL98: 89 | AM98: 89 | AN98: - | AP98: 92 | AQ98: 93 | AR98: 95 | AS98: 98 | AT98: 92 | AU98: 92 | AV98: 92 | AW98: 92 | AX98: - | AZ98: 82 | BA98: 83 | BD98: 95
B99: 96 | D99: 97 | E99: 101 | F99: 106 | G99: 109 | H99: 108 | I99: 108 | J99: 98 | K99: 101 | L99: - | N99: - | P99: 87 | Q99: 89 | R99: 85 | S99: 87 | T99: 78 | U99: 80 | V99: 80 | W99: 84 | X99: 90 | Y99: 93 | Z99: 92 | AA99: 94 | AB99: 92 | AC99: 93 | AD99: 99 | AE99: 102 | AF99: - | AH99: - | AJ99: 104 | AK99: 104 | AL99: 90 | AM99: 92 | AN99: 109 | AO99: 109 | AP99: 94 | AQ99: 97 | AR99: 99 | AS99: 101 | AT99: 93 | AU99: 95 | AV99: 93 | AW99: 94 | AX99: 105 | AY99: 107 | AZ99: 84 | BA99: 87 | BD99: 96
B100: 97 | D100: - | F100: - | H100: 109 | I100: 110 | J100: 102 | K100: 104 | L100: - | N100: 85 | O100: 92 | P100: 90 | Q100: 92 | R100: 88 | S100: 91 | T100: 81 | U100: 81 | V100: 85 | W100: 95 | X100: 94 | Y100: 95 | Z100: 95 | AA100: 98 | AB100: 94 | AC100: 98 | AD100: 103 | AE100: 105 | AF100: 95 | AG100: 96 | AH100: 104 | AI100: 107 | AJ100: - | AL100: 93 | AM100: 94 | AN100: 110 | AO100: 112 | AP100: 98 | AQ100: 101 | AR100: 102 | AS100: 104 | AT100: 96 | AU100: 98 | AV100: 95 | AW100: 98 | AX100: 108 | AY100: 110 | AZ100: 88 | BA100: 89 | BD100: 97
B101: 98 | D101: 102 | E101: 107 | F101: 110 | G101: 110 | H101: 111 | I101: 113 | J101: 105 | K101: 105 | L101: 88 | M101: 92 | N101: - | P101: 93 | Q101: 95 | R101: 92 | S101: 94 | T101: 82 | U101: 88 | V101: 96 | W101: 99 | X101: 96 | Y101: 101 | Z101: 99 | AA101: 106 | AB101: 99 | AC101: 103 | AD101: 106 | AE101: 106 | AF101: 97 | AG101: 100 | AH101: 108 | AI101: 108 | AJ101: 105 | AK101: 113 | AL101: 95 | AM101: 99 | AN101: 113 | AO101: 113 | AP101: 102 | AQ101: 104 | AR101: 105 | AS101: 108 | AT101: 99 | AU101: 99 | AV101: 99 | AW101: 101 | AX101: 111 | AY101: 113 | AZ101: 90 | BA101: 93 | BD101: 98
...

Sheet PERCENTIL2
B2: Percentil
B3: 1 | C3: 2A | D3: 2B | E3: 3 | F3: 4A | G3: 4B | H3: 5 | I3: 6A | J3: 6B | K3: 7 | L3: 8A | M3: 8B | N3: S | O3: C | P3: P | Q3: A | R3: H | S3: N | T3: D | U3: B | V3: T | W3: R | X3: SS | Y3: CC | Z3: PP
A4: 0 | B4: 2 | C4: 2 | D4: 5 | E4: 2 | F4: 4 | G4: 4 | H4: 10 | I4: 11 | J4: 6 | K4: 1 | L4: 3 | M4: 5 | N4: 4 | O4: 4 | P4: 7 | Q4: 5 | R4: 11 | S4: 3 | T4: 3 | U4: 34 | V4: 24 | W4: 8 | X4: 3 | Y4: 13 | Z4: 17
A5: 1 | B5: 2 | C5: 2 | D5: 6 | E5: 2 | F5: 4 | G5: 4 | H5: 11 | I5: 12 | J5: 7 | K5: 1 | L5: 4 | M5: 5 | N5: 5 | O5: 6 | P5: 9 | Q5: 5 | R5: 12 | S5: 4 | T5: 4 | U5: 36 | V5: 25 | W5: 9 | X5: 4 | Y5: 14 | Z5: 19
A6: 2 | B6: 2 | C6: 2 | D6: 6 | E6: 2 | F6: 4 | G6: 4 | H6: 11 | I6: 12 | J6: 8 | K6: 1 | L6: 5 | M6: 5 | N6: 6 | O6: 6 | P6: 10 | Q6: 6 | R6: 12 | S6: 4 | T6: 4 | U6: 37 | V6: 25 | W6: 10 | X6: 5 | Y6: 15 | Z6: 20
A7: 3 | B7: 2 | C7: 2 | D7: 7 | E7: 2 | F7: 4 | G7: 4 | H7: 12 | I7: 12 | J7: 8 | K7: 1 | L7: 6 | M7: 6 | N7: 6 | O7: 6 | P7: 10 | Q7: 6 | R7: 12 | S7: 4 | T7: 4 | U7: 37 | V7: 25 | W7: 10 | X7: 5 | Y7: 15 | Z7: 20
A8: 4 | B8: 2 | C8: 2 | D8: 7 | E8: 2 | F8: 4 | G8: 4 | H8: 12 | I8: 12 | J8: 8 | K8: 1 | L8: 6 | M8: 6 | N8: 6 | O8: 6 | P8: 10 | Q8: 6 | R8: 12 | S8: 4 | T8: 4 | U8: 37 | V8: 25 | W8: 10 | X8: 5 | Y8: 15 | Z8: 20
A9: 5 | B9: 2 | C9: 2 | D9: 8 | E9: 2 | F9: 4 | G9: 5 | H9: 12 | I9: 12 | J9: 8 | K9: 1 | L9: 6 | M9: 6 | N9: 6 | O9: 7 | P9: 10 | Q9: 6 | R9: 12 | S9: 4 | T9: 8 | U9: 37 | V9: 26 | W9: 10 | X9: 5 | Y9: 15 | Z9: 20
A10: 6 | B10: 2 | C10: 5 | D10: 8 | E10: 3 | F10: 7 | G10: 7 | H10: 12 | I10: 12 | J10: 8 | K10: 1 | L10: 6 | M10: 6 | N10: 9 | O10: 7 | P10: 10 | Q10: 6 | R10: 12 | S10: 4 | T10: 8 | U10: 37 | V10: 26 | W10: 10 | X10: 5 | Y10: 15 | Z10: 20
A11: 7 | B11: 5 | C11: 5 | D11: 9 | E11: 3 | F11: 9 | G11: 8 | H11: 12 | I11: 12 | J11: 8 | K11: 1 | L11: 9 | M11: 6 | N11: 9 | O11: 7 | P11: 10 | Q11: 6 | R11: 12 | S11: 4 | T11: 9 | U11: 37 | V11: 26 | W11: 10 | X11: 8 | Y11: 15 | Z11: 20
A12: 8 | B12: 5 | C12: 6 | D12: 9 | E12: 3 | F12: 9 | G12: 8 | H12: 12 | I12: 12 | J12: 8 | K12: 1 | L12: 9 | M12: 10 | N12: 10 | O12: 12 | P12: 10 | Q12: 10 | R12: 12 | S12: 4 | T12: 9 | U12: 37 | V12: 26 | W12: 10 | X12: 8 | Y12: 16 | Z12: 20
A13: 9 | B13: 5 | C13: 6 | D13: 9 | E13: 3 | F13: 10 | G13: 8 | H13: 12 | I13: 12 | J13: 8 | K13: 1 | L13: 10 | M13: 10 | N13: 10 | O13: 13 | P13: 15 | Q13: 10 | R13: 12 | S13: 4 | T13: 9 | U13: 37 | V13: 26 | W13: 10 | X13: 9 | Y13: 21 | Z13: 20
A14: 10 | B14: 5 | C14: 6 | D14: 13 | E14: 4 | F14: 10 | G14: 8 | H14: 12 | I14: 12 | J14: 13 | K14: 1 | L14: 10 | M14: 10 | N14: 10 | O14: 13 | P14: 15 | Q14: 10 | R14: 17 | S14: 8 | T14: 13 | U14: 37 | V14: 26 | W14: 10 | X14: 9 | Y14: 21 | Z14: 20
A15: 11 | B15: 5 | C15: 6 | D15: 13 | E15: 4 | F15: 10 | G15: 9 | H15: 12 | I15: 12 | J15: 13 | K15: 1 | L15: 10 | M15: 11 | N15: 10 | O15: 13 | P15: 15 | Q15: 10 | R15: 19 | S15: 9 | T15: 14 | U15: 37 | V15: 26 | W15: 10 | X15: 9 | Y15: 22 | Z15: 20
... A104: 100 | B104: 96 | C104: 92 | D104: 92 | E104: 96 | F104: 99 | G104: 99 | H104: 99 | I104: 99 | J104: 99 | K104: 99 | L104: 98 | M104: 98 | N104: 98 | O104: 96 | P104: 98 | Q104: 94 | R104: 94 | S104: 99 | T104: 90 | U104: 97 | V104: 96 | W104: 99 | X104: 98 | Y104: 90 | Z104: 99
A105: 101 | B105: 96 | C105: 92 | D105: 92 | E105: 96 | H105: 99 | I105: 99 | J105: 99 | L105: 98 | M105: 98 | N105: 98 | O105: 96 | P105: 99 | Q105: 94 | R105: 94 | S105: 99 | T105: 90 | U105: 97 | V105: 96 | W105: 99 | X105: 98 | Y105: 91 | Z105: 99
A106: 102 | B106: 98 | C106: 94 | D106: 94 | E106: 97 | H106: 99 | I106: 99 | J106: 99 | L106: 99 | M106: 98 | N106: 98 | O106: 96 | P106: 99 | Q106: 97 | R106: 96 | S106: 99 | T106: 90 | U106: 98 | V106: 97 | W106: 99 | X106: 99 | Y106: 93 | Z106: 99
A107: 103 | B107: 98 | C107: 94 | D107: 94 | E107: 97 | H107: 99 | I107: 99 | J107: 99 | L107: 99 | M107: 98 | N107: 98 | O107: 97 | P107: 99 | Q107: 97 | R107: 96 | S107: 99 | T107: 90 | U107: 98 | V107: 97 | W107: 99 | X107: 99 | Y107: 94 | Z107: 99
A108: 104 | B108: 98 | C108: 94 | D108: 94 | E108: 97 | H108: 99 | I108: 99 | J108: 99 | L108: 99 | M108: 98 | N108: 99 | O108: 97 | P108: 99 | Q108: 97 | R108: 96 | S108: 99 | T108: 92 | U108: 98 | V108: 97 | W108: 99 | X108: 99 | Y108: 94 | Z108: 99
A109: 105 | B109: 98 | C109: 95 | D109: 95 | E109: 98 | H109: 99 | I109: 99 | J109: 99 | L109: 99 | M109: 98 | N109: 99 | O109: 97 | P109: 99 | Q109: 97 | R109: 95 | S109: 99 | T109: 93 | U109: 99 | V109: 98 | W109: 99 | X109: 99 | Y109: 96 | Z109: 99
A110: 106 | B110: 98 | C110: 96 | D110: 95 | E110: 99 | H110: 99 | I110: 99 | J110: 99 | L110: 99 | M110: 98 | N110: 99 | O110: 98 | P110: 99 | Q110: 97 | R110: 95 | S110: 99 | T110: 93 | U110: 99 | V110: 98 | W110: 99 | X110: 99 | Y110: 96 | Z110: 99
A111: 107 | B111: 98 | C111: 96 | D111: 95 | E111: 99 | H111: 99 | I111: 99 | J111: 99 | L111: 99 | M111: 99 | N111: 99 | O111: 99 | P111: 99 | Q111: 97 | R111: 95 | S111: 99 | T111: 93 | U111: 99 | V111: 98 | W111: 99 | X111: 99 | Y111: 96 | Z111: 99
A112: 108 | B112: 99 | C112: 96 | D112: 96 | E112: 99 | H112: 99 | I112: 99 | J112: 99 | L112: 99 | M112: 99 | N112: 99 | O112: 99 | P112: 99 | Q112: 95 | R112: 95 | S112: 99 | T112: 94 | U112: 99 | V112: 98 | W112: 99 | X112: 99 | Y112: 97 | Z112: 99
A113: 109 | B113: 99 | C113: 96 | D113: 97 | E113: 99 | H113: 99 | I113: 99 | J113: 99 | L113: 99 | M113: 99 | N113: 99 | O113: 99 | P113: 99 | Q113: 99 | R113: 98 | S113: 99 | T113: 96 | U113: 99 | V113: 99 | W113: 99 | X113: 99 | Y113: 97 | Z113: 99
A114: 110 | B114: 99 | C114: 98 | D114: 97 | E114: 99 | H114: 99 | I114: 99 | J114: 99 | L114: 99 | M114: 99 | N114: 99 | O114: 99 | P114: 99 | Q114: 99 | R114: 98 | S114: 99 | T114: 97 | U114: 99 | V114: 99 | W114: 99 | X114: 99 | Y114: 97 | Z114: 99
A115: 111 | B115: 99 | C115: 99 | D115: 98 | E115: 99 | H115: 99 | I115: 99 | J115: 99 | L115: 99 | M115: 99 | N115: 99 | O115: 99 | P115: 99 | Q115: 99 | R115: 98 | S115: 99 | T115: 97 | U115: 99 | V115: 99 | W115: 99 | X115: 99 | Y115: 98 | Z115: 99
A116: 112 | B116: 99 | C116: 99 | D116: 98 | E116: 99 | H116: 99 | I116: 99 | J116: 99 | L116: 99 | M116: 99 | N116: 99 | O116: 99 | P116: 99 | Q116: 99 | R116: 98 | S116: 99 | T116: 97 | U116: 99 | V116: 99 | W116: 99 | X116: 99 | Y116: 98 | Z116: 99
... A119: 115 | B119: 99 | C119: 99 | D119: 99 | E119: 99 | H119: 99 | I119: 99 | J119: 99 | L119: 99 | M119: 99 | N119: 99 | O119: 99 | P119: 99 | Q119: 99 | R119: 99 | S119: 99 | T119: 99 | U119: 99 | V119: 99 | W119: 99 | X119: 99 | Y119: 99 | Z119: 99

Sheet PERCENTIL GROSSMAN
B1: 0 | D1: 1 | F1: 2 | H1: 3 | J1: 4 | L1: 5 | N1: 6 | P1: 7 | R1: 8 | T1: 9 | V1: 10 | X1: 11 | Z1: 12
B2: TB | C2: Pc | D2: TB | E2: Pc | F2: TB | G2: Pc | H2: TB | I2: Pc | J2: TB | K2: Pc | L2: TB | M2: Pc | N2: TB | O2: Pc | P2: TB | Q2: Pc | R2: TB | S2: Pc | T2: TB | U2: Pc | V2: TB | W2: Pc | X2: TB | Y2: Pc | Z2: TB | AA2: Pc
A3: 1.1 | B3: 0 | C3: 9 | D3: 20 | E3: 22 | F3: 40 | G3: 38 | H3: 60 | I3: 55 | J3: 68 | K3: 68 | L3: 75 | M3: 80 | N3: 85 | O3: 89 | P3: 90 | Q3: 95 | R3: 95 | S3: 98 | T3: 100 | U3: 99
A4: 1.2 | B4: 0 | C4: 3 | D4: 15 | E4: 10 | F4: 30 | G4: 20 | H4: 45 | I4: 35 | J4: 60 | K4: 48 | L4: 65 | M4: 59 | N4: 70 | O4: 71 | P4: 75 | Q4: 82 | R4: 85 | S4: 93 | T4: 100 | U4: 99
A5: 1.3 | B5: 0 | C5: 13 | D5: 20 | E5: 27 | F5: 40 | G5: 40 | H5: 60 | I5: 51 | J5: 65 | K5: 60 | L5: 70 | M5: 69 | N5: 75 | O5: 79 | P5: 80 | Q5: 87 | R5: 85 | S5: 95 | T5: 100 | U5: 99
A6: 2A.1 | B6: 0 | C6: 4 | D6: 15 | E6: 11 | F6: 30 | G6: 24 | H6: 45 | I6: 37 | J6: 60 | K6: 50 | L6: 75 | M6: 63 | N6: 85 | O6: 74 | P6: 93 | Q6: 87 | R6: 100 | S6: 99
A7: 2A.2 | B7: 0 | C7: 8 | D7: 15 | E7: 20 | F7: 30 | G7: 33 | H7: 45 | I7: 45 | J7: 60 | K7: 57 | L7: 75 | M7: 69 | N7: 85 | O7: 81 | P7: 90 | Q7: 92 | R7: 95 | S7: 97 | T7: 100 | U7: 99
A8: 2A.3 | B8: 0 | C8: 12 | D8: 20 | E8: 25 | F8: 40 | G8: 40 | H8: 60 | I8: 53 | J8: 75 | K8: 65 | L8: 80 | M8: 74 | N8: 85 | O8: 83 | P8: 90 | Q8: 91 | R8: 95 | S8: 96 | T8: 100 | U8: 99
A9: 2B.1 | B9: 0 | C9: 6 | D9: 10 | E9: 12 | F9: 20 | G9: 20 | H9: 30 | I9: 28 | J9: 40 | K9: 38 | L9: 50 | M9: 48 | N9: 60 | O9: 61 | P9: 75 | Q9: 73 | R9: 85 | S9: 87 | T9: 100 | U9: 99
A10: 2B.2 | B10: 0 | C10: 24 | D10: 30 | E10: 41 | F10: 60 | G10: 54 | H10: 75 | I10: 65 | J10: 80 | K10: 75 | L10: 85 | M10: 83 | N10: 89 | O10: 88 | P10: 93 | Q10: 93 | R10: 96 | S10: 97 | T10: 100 | U10: 99
A11: 2B.3 | B11: 0 | C11: 21 | D11: 20 | E11: 35 | F11: 40 | G11: 45 | H11: 60 | I11: 51 | J11: 75 | K11: 58 | L11: 78 | M11: 64 | N11: 80 | O11: 71 | P11: 83 | Q11: 80 | R11: 85 | S11: 89 | T11: 100 | U11: 99
A12: 3.1 | B12: 0 | C12: 6 | D12: 12 | E12: 14 | F12: 24 | G12: 23 | H12: 36 | I12: 34 | J12: 48 | K12: 49 | L12: 60 | M12: 64 | N12: 75 | O12: 77 | P12: 85 | Q12: 88 | R12: 93 | S12: 97 | T12: 100 | U12: 99
A13: 3.2 | B13: 0 | C13: 7 | D13: 20 | E13: 21 | F13: 40 | G13: 41 | H13: 60 | I13: 61 | J13: 75 | K13: 79 | L13: 85 | M13: 90 | N13: 93 | O13: 97 | P13: 100 | Q13: 99
A14: 3.3 | B14: 0 | C14: 10 | D14: 15 | E14: 22 | F14: 30 | G14: 35 | H14: 45 | I14: 46 | J14: 60 | K14: 58 | L14: 75 | M14: 70 | N14: 85 | O14: 80 | P14: 90 | Q14: 88 | R14: 95 | S14: 97 | T14: 100 | U14: 99
A15: 4A.1 | B15: 0 | C15: 31 | D15: 60 | E15: 54 | F15: 68 | G15: 70 | H15: 75 | I15: 81 | J15: 85 | K15: 89 | L15: 90 | M15: 95 | N15: 95 | O15: 98 | P15: 100 | Q15: 99
A16: 4A.2 | B16: 0 | C16: 7 | D16: 15 | E16: 15 | F16: 30 | G16: 25 | H16: 45 | I16: 35 | J16: 60 | K16: 47 | L16: 65 | M16: 58 | N16: 70 | O16: 68 | P16: 75 | Q16: 80 | R16: 85 | S16: 91 | T16: 93 | U16: 98 | V16: 100 | W16: 99
A17: 4A.3 | B17: 0 | C17: 5 | D17: 12 | E17: 15 | F17: 24 | G17: 25 | H17: 36 | I17: 34 | J17: 48 | K17: 43 | L17: 60 | M17: 52 | N17: 64 | O17: 60 | P17: 68 | Q17: 68 | R17: 75 | S17: 81 | T17: 75 | U17: 81 | V17: 85 | W17: 90 | X17: 93 | Y17: 96 | Z17: 100 | AA17: 99
A18: 4B.1 | B18: 0 | C18: 11 | D18: 20 | E18: 27 | F18: 40 | G18: 41 | H18: 60 | I18: 52 | J18: 64 | K18: 61 | L18: 68 | M18: 71 | N18: 71 | O18: 78 | P18: 75 | Q18: 90
A19: 4B.2 | B19: 0 | C19: 7 | D19: 20 | E19: 22 | F19: 40 | G19: 36 | H19: 60 | I19: 46 | J19: 65 | K19: 59 | L19: 70 | M19: 73 | N19: 75 | O19: 86 | P19: 85 | Q19: 95 | R19: 100 | S19: 99 | T19: 100 | U19: 99
A20: 4B.3 | B20: 0 | C20: 7 | D20: 15 | E20: 17 | F20: 30 | G20: 29 | H20: 45 | I20: 43 | J20: 60 | K20: 56 | L20: 68 | M20: 69 | N20: 75 | O20: 84 | P20: 85 | Q20: 95
A21: 5.1 | B21: 0 | C21: 26 | D21: 60 | E21: 47 | F21: 65 | G21: 64 | H21: 70 | I21: 76 | J21: 75 | K21: 84 | L21: 80 | M21: 90 | N21: 85 | O21: 95 | P21: 90 | Q21: 98 | R21: 100 | S21: 99 | T21: 100 | U21: 99
A22: 5.2 | B22: 0 | C22: 6 | D22: 15 | E22: 18 | F22: 30 | G22: 31 | H22: 45 | I22: 40 | J22: 60 | K22: 52 | L22: 64 | M22: 61 | N22: 68 | O22: 71 | P22: 71 | Q22: 78 | R22: 85 | S22: 86 | T22: 85 | U22: 96 | V22: 100 | W22: 99
A23: 5.3 | B23: 0 | C23: 26 | D23: 60 | E23: 50 | F23: 65 | G23: 69 | H23: 70 | I23: 80 | J23: 75 | K23: 90 | L23: 85 | M23: 96 | N23: 90 | O23: 99 | P23: 95 | Q23: 99
A24: 6A.1 | B24: 0 | C24: 21 | D24: 60 | E24: 47 | F24: 65 | G24: 65 | H24: 70 | I24: 79 | J24: 75 | K24: 88 | L24: 85 | M24: 94 | N24: 90 | O24: 98 | P24: 95 | Q24: 99
A25: 6A.2 | B25: 0 | C25: 16 | D25: 30 | E25: 37 | F25: 60 | G25: 60 | H25: 65 | I25: 76 | J25: 70 | K25: 86 | L25: 75 | M25: 93 | N25: 85 | O25: 97 | P25: 89 | Q25: 99 | R25: 96 | S25: 99 | T25: 96 | U25: 99 | V25: 100 | W25: 99
A26: 6A.3 | B26: 0 | C26: 27 | D26: 60 | E26: 48 | F26: 64 | G26: 71 | H26: 68 | I26: 81 | J26: 71 | K26: 87 | L26: 75 | M26: 90 | N26: 80 | O26: 93 | P26: 85 | Q26: 96 | R26: 95 | S26: 99 | T26: 95 | U26: 99 | V26: 100 | W26: 99
A27: 6B.1 | B27: 0 | C27: 11 | D27: 20 | E27: 26 | F27: 40 | G27: 42 | H27: 60 | I27: 55 | J27: 64 | K27: 70 | L27: 68 | M27: 81 | N27: 71 | O27: 87 | P27: 75 | Q27: 93 | R27: 90 | S27: 99 | T27: 90 | U27: 99 | V27: 95 | W27: 99 | X27: 100 | Y27: 99
A28: 6B.2 | B28: 0 | C28: 22 | D28: 60 | E28: 43 | F28: 64 | G28: 63 | H28: 68 | I28: 77 | J28: 71 | K28: 88 | L28: 75 | M28: 95 | N28: 85 | O28: 99 | P28: 100 | Q28: 99
A29: 6B.3 | B29: 0 | C29: 25 | D29: 60 | E29: 47 | F29: 64 | G29: 60 | H29: 68 | I29: 71 | J29: 71 | K29: 80 | L29: 75 | M29: 89 | N29: 85 | O29: 97 | P29: 100 | Q29: 99
A30: 7.1 | B30: 0 | C30: 1 | D30: 12 | E30: 6 | F30: 24 | G30: 16 | H30: 36 | I30: 26 | J30: 48 | K30: 45 | L30: 60 | M30: 61 | N30: 75 | O30: 75 | P30: 85 | Q30: 88 | R30: 100 | S30: 99
A31: 7.2 | B31: 0 | C31: 2 | D31: 9 | E31: 7 | F31: 17 | G31: 14 | H31: 26 | I31: 22 | J31: 34 | K31: 29 | L31: 43 | M31: 39 | N31: 51 | O31: 49 | P31: 60 | Q31: 59 | R31: 75 | S31: 69 | T31: 80 | U31: 80 | V31: 85 | W31: 89 | X31: 93 | Y31: 95 | Z31: 100 | AA31: 99
A32: 7.3 | B32: 0 | C32: 1 | D32: 9 | E32: 1 | F32: 17 | G32: 3 | H32: 26 | I32: 6 | J32: 34 | K32: 11 | L32: 43 | M32: 19 | N32: 51 | O32: 36 | P32: 60 | Q32: 56 | R32: 75 | S32: 81 | T32: 85 | U32: 99
A33: 8A.1 | B33: 0 | C33: 13 | D33: 20 | E33: 28 | F33: 40 | G33: 43 | H33: 60 | I33: 55 | J33: 68 | K33: 66 | L33: 75 | M33: 79 | N33: 80 | O33: 88 | P33: 85 | Q33: 94 | R33: 93 | S33: 98 | T33: 100 | U33: 99
A34: 8A.2 | B34: 0 | C34: 6 | D34: 15 | E34: 15 | F34: 30 | G34: 24 | H34: 45 | I34: 36 | J34: 60 | K34: 47 | L34: 65 | M34: 58 | N34: 70 | O34: 68 | P34: 75 | Q34: 78 | R34: 80 | S34: 86 | T34: 85 | U34: 93 | V34: 93 | W34: 98 | X34: 100 | Y34: 99
A35: 8A.3 | B35: 0 | C35: 15 | D35: 20 | E35: 32 | F35: 40 | G35: 44 | H35: 60 | I35: 55 | J35: 65 | K35: 63 | L35: 70 | M35: 72 | N35: 75 | O35: 80 | P35: 80 | Q35: 85 | R35: 85 | S35: 91 | T35: 93 | U35: 96 | V35: 100 | W35: 99
A36: 8B.1 | B36: 0 | C36: 9 | D36: 15 | E36: 18 | F36: 30 | G36: 32 | H36: 45 | I36: 44 | J36: 60 | K36: 53 | L36: 64 | M36: 64 | N36: 68 | O36: 71 | P36: 71 | Q36: 79 | R36: 75 | S36: 85 | T36: 80 | U36: 90 | V36: 85 | W36: 95 | X36: 93 | Y36: 98 | Z36: 100 | AA36: 99
A37: 8B.2 | B37: 0 | C37: 13 | D37: 20 | E37: 25 | F37: 40 | G37: 37 | H37: 60 | I37: 49 | J37: 65 | K37: 60 | L37: 70 | M37: 71 | N37: 75 | O37: 82 | P37: 80 | Q37: 91 | R37: 85 | S37: 97 | T37: 100 | U37: 99
A38: 8B.3 | B38: 0 | C38: 7 | D38: 12 | E38: 17 | F38: 24 | G38: 23 | H38: 36 | I38: 33 | J38: 48 | K38: 44 | L38: 60 | M38: 54 | N38: 65 | O38: 64 | P38: 70 | Q38: 75 | R38: 75 | S38: 89 | T38: 85 | U38: 99
A39: S.1 | B39: 0 | C39: 7 | D39: 15 | E39: 16 | F39: 30 | G39: 26 | H39: 45 | I39: 35 | J39: 60 | K39: 46 | L39: 65 | M39: 56 | N39: 70 | O39: 66 | P39: 75 | Q39: 79 | R39: 85 | S39: 90 | T39: 100 | U39: 99
A40: S.2 | B40: 0 | C40: 12 | D40: 20 | E40: 27 | F40: 40 | G40: 38 | H40: 60 | I40: 47 | J40: 63 | K40: 57 | L40: 66 | M40: 65 | N40: 69 | O40: 73 | P40: 72 | Q40: 81 | R40: 75 | S40: 87 | T40: 85 | U40: 93 | V40: 93 | W40: 98 | X40: 100 | Y40: 99
A41: S.3 | B41: 0 | C41: 17 | D41: 30 | E41: 32 | F41: 60 | G41: 46 | H41: 64 | I41: 58 | J41: 68 | K41: 69 | L41: 71 | M41: 77 | N41: 75 | O41: 84 | P41: 80 | Q41: 90 | R41: 85 | S41: 95 | T41: 90 | U41: 98 | V41: 95 | W41: 99 | X41: 100 | Y41: 99
A42: C.1 | B42: 0 | C42: 20 | D42: 20 | E42: 35 | F42: 40 | G42: 45 | H42: 60 | I42: 52 | J42: 65 | K42: 61 | L42: 70 | M42: 69 | N42: 75 | O42: 78 | P42: 85 | Q42: 89 | R42: 100 | S42: 99
A43: C.2 | B43: 0 | C43: 10 | D43: 20 | E43: 24 | F43: 40 | G43: 38 | H43: 60 | I43: 52 | J43: 65 | K43: 63 | L43: 70 | M43: 71 | N43: 75 | O43: 79 | P43: 85 | Q43: 85 | R43: 89 | S43: 90 | T43: 93 | U43: 94 | V43: 96 | W43: 99 | X43: 100 | Y43: 99
A44: C.3 | B44: 0 | C44: 16 | D44: 20 | E44: 31 | F44: 40 | G44: 44 | H44: 60 | I44: 54 | J44: 65 | K44: 64 | L44: 70 | M44: 73 | N44: 75 | O44: 82 | P44: 85 | Q44: 88 | R44: 90 | S44: 93 | T44: 95 | U44: 98 | V44: 100 | W44: 99
A45: P.1 | B45: 0 | C45: 12 | D45: 20 | E45: 28 | F45: 40 | G45: 41 | H45: 60 | I45: 57 | J45: 68 | K45: 70 | L45: 75 | M45: 81 | N45: 85 | O45: 89 | P45: 90 | Q45: 96 | R45: 95 | S45: 99 | T45: 100 | U45: 99
A46: P.2 | B46: 0 | C46: 18 | D46: 30 | E46: 32 | F46: 60 | G46: 50 | H46: 68 | I46: 66 | J46: 75 | K46: 80 | L46: 85 | M46: 91 | N46: 93 | O46: 97 | P46: 100 | Q46: 99
A47: P.3 | B47: 0 | C47: 20 | D47: 30 | E47: 36 | F47: 60 | G47: 53 | H47: 68 | I47: 65 | J47: 75 | K47: 76 | L47: 80 | M47: 85 | N47: 85 | O47: 96 | P47: 89 | Q47: 96 | R47: 93 | S47: 98 | T47: 96 | U47: 99 | V47: 100 | W47: 99
